Workbook

Sheet Scenario
A1: Setting | B1: Value
A2: Scenario | B2: Pre-Roxanne: encounters through Route 116
A3: Generated | B3: 2026-08-17T11:15:23
A4: Dex snapshot | B4: C:\Users\prana\Downloads\Decomps\romhack-docs\public\data\dex.json
A5: Dex generatedAt | B5: 2026-08-06T05:10:42.544Z
A6: Google Sheet | B6: https://docs.google.com/spreadsheets/d/1hdZdmDTvVAbuoer8FHvYYZAVdjp9NGGppLklhBIi62w/edit
A7: Level cap / player level | B7: 15
A8: Player Nature mode | B8: fixed: Neutral
A9: Player Ability mode | B9: first
A10: Move ranking metric | B10: expected
A11: Weather | B11: None
A12: Terrain | B12: None
A13: Included maps | B13: MAP_ROUTE101, MAP_ROUTE103, MAP_ROUTE102, MAP_ROUTE104, MAP_PETALBURG_WOODS, MAP_ROUTE116
A14: Included encounter methods | B14: Land, Sand
A15: Excluded prerequisite moves | B15: MOVE_BELCH
A16: Player species/forms analyzed | B16: 32
A17: Boss | B17: Roxanne (Fossil draft)
A18: Target | B18: Lileep Lv. 15
A19: Boss attacker | B19: Lileep Lv. 15
A20: Important | B20: Empty boss move lists use all legal level-up moves. Enter exact trainers.party moves before treating boss offense as final.

Sheet Threshold Summary
A1: Pokémon | B1: Best outgoing move | C1: Outgoing avg % | D1: Strongest incoming move | E1: Incoming avg % | F1: Player Spe | G1: Boss Spe | H1: Outspeeds? | I1: Net score | J1: Rating | K1: Species ID | L1: Level | M1: Nature | N1: Ability | O1: HP EV | P1: Atk EV | Q1: Def EV | R1: SpA EV | S1: SpD EV | T1: Spe EV | U1: Outgoing min | V1: Outgoing max | W1: Incoming min | X1: Incoming max | Y1: Origin Species ID | Z1: Move override
A2: =XLOOKUP(K2,'Pokemon Editor'!$A:$A,'Pokemon Editor'!$B:$B,K2) | B2: =IF($Z2<>"",$Z2,IFERROR(INDEX(FILTER('Move Comparison'!$D$2:$D,'Move Comparison'!$Q$2:$Q=$Y2,'Move Comparison'!$M$2:$M=MAXIFS('Move Comparison'!$M$2:$M,'Move Comparison'!$Q$2:$Q,$Y2),'Move Comparison'!$D$2:$D<>""),1),"")) | C2: =IFERROR(LET(mtype,XLOOKUP($B2,'Move Editor'!$B:$B,'Move Editor'!$C:$C,""),cat,XLOOKUP($B2,'Move Editor'!$B:$B,'Move Editor'!$D:$D,""),pow,XLOOKUP($B2,'Move Editor'!$B:$B,'Move Editor'!$E:$E,0),acc,XLOOKUP($B2,'Move Editor'!$B:$B,'Move Editor'!$F:$F,100),atk,IF(cat="Physical",FLOOR((FLOOR(((2*XLOOKUP($K2,'Pokemon Editor'!$A:$A,'Pokemon Editor'!$F:$F,0)+31+FLOOR($P2/4))*$L2)/100)+5)*XLOOKUP($M2,'Nature Editor'!$A:$A,'Nature Editor'!$B:$B,1)),FLOOR((FLOOR(((2*XLOOKUP($K2,'Pokemon Editor'!$A:$A,'Pokemon Editor'!$H:$H,0)+31+FLOOR($R2/4))*$L2)/100)+5)*XLOOKUP($M2,'Nature Editor'!$A:$A,'Nature Editor'!$D:$D,1))),def,IF(cat="Physical",FLOOR((FLOOR(((2*XLOOKUP('Boss Editor'!$C$4,'Pokemon Editor'!$A:$A,'Pokemon Editor'!$G:$G,0)+31+FLOOR('Boss Editor'!$I$4/4))*'Boss Editor'!$D$4)/100)+5)*XLOOKUP('Boss Editor'!$E$4,'Nature Editor'!$A:$A,'Nature Editor'!$C:$C,1)),FLOOR((FLOOR(((2*XLOOKUP('Boss Editor'!$C$4,'Pokemon Editor'!$A:$A,'Pokemon Editor'!$I:$I,0)+31+FLOOR('Boss Editor'!$K$4/4))*'Boss Editor'!$D$4)/100)+5)*XLOOKUP('Boss Editor'!$E$4,'Nature Editor'!$A:$A,'Nature Editor'!$E:$E,1))),stab,IF(OR(mtype=XLOOKUP($K2,'Pokemon Editor'!$A:$A,'Pokemon Editor'!$C:$C,""),mtype=XLOOKUP($K2,'Pokemon Editor'!$A:$A,'Pokemon Editor'!$D:$D,"")),1.5,1),eff,(INDEX('Type Chart'!$B:$S,MATCH(mtype,'Type Chart'!$A:$A,0),MATCH(XLOOKUP('Boss Editor'!$C$4,'Pokemon Editor'!$A:$A,'Pokemon Editor'!$C:$C,""),'Type Chart'!$B$1:$S$1,0))*IF(XLOOKUP('Boss Editor'!$C$4,'Pokemon Editor'!$A:$A,'Pokemon Editor'!$D:$D,"")="",1,INDEX('Type Chart'!$B:$S,MATCH(mtype,'Type Chart'!$A:$A,0),MATCH(XLOOKUP('Boss Editor'!$C$4,'Pokemon Editor'!$A:$A,'Pokemon Editor'!$D:$D,""),'Type Chart'!$B$1:$S$1,0)))),base,IF(OR(cat="Status",pow=0),0,FLOOR(FLOOR(FLOOR((2*$L2/5+2)*pow*atk/def)/50)+2)),modifier,stab*eff,AVERAGE(ARRAYFORMULA(FLOOR(base*modifier*SEQUENCE(16,1,85,1)/100)))/(FLOOR(((2*XLOOKUP('Boss Editor'!$C$4,'Pokemon Editor'!$A:$A,'Pokemon Editor'!$E:$E,0)+31+FLOOR('Boss Editor'!$G$4/4))*'Boss Editor'!$D$4)/100)+'Boss Editor'!$D$4+10)),0) | D2: Acid | E2: =IFERROR(LET(mtype,XLOOKUP($D2,'Move Editor'!$B:$B,'Move Editor'!$C:$C,""),cat,XLOOKUP($D2,'Move Editor'!$B:$B,'Move Editor'!$D:$D,""),pow,XLOOKUP($D2,'Move Editor'!$B:$B,'Move Editor'!$E:$E,0),acc,XLOOKUP($D2,'Move Editor'!$B:$B,'Move Editor'!$F:$F,100),atk,IF(cat="Physical",FLOOR((FLOOR(((2*XLOOKUP('Boss Editor'!$C$4,'Pokemon Editor'!$A:$A,'Pokemon Editor'!$F:$F,0)+31+FLOOR('Boss Editor'!$H$4/4))*'Boss Editor'!$D$4)/100)+5)*XLOOKUP('Boss Editor'!$E$4,'Nature Editor'!$A:$A,'Nature Editor'!$B:$B,1)),FLOOR((FLOOR(((2*XLOOKUP('Boss Editor'!$C$4,'Pokemon Editor'!$A:$A,'Pokemon Editor'!$H:$H,0)+31+FLOOR('Boss Editor'!$J$4/4))*'Boss Editor'!$D$4)/100)+5)*XLOOKUP('Boss Editor'!$E$4,'Nature Editor'!$A:$A,'Nature Editor'!$D:$D,1))),def,IF(cat="Physical",FLOOR((FLOOR(((2*XLOOKUP($K2,'Pokemon Editor'!$A:$A,'Pokemon Editor'!$G:$G,0)+31+FLOOR($Q2/4))*$L2)/100)+5)*XLOOKUP($M2,'Nature Editor'!$A:$A,'Nature Editor'!$C:$C,1)),FLOOR((FLOOR(((2*XLOOKUP($K2,'Pokemon Editor'!$A:$A,'Pokemon Editor'!$I:$I,0)+31+FLOOR($S2/4))*$L2)/100)+5)*XLOOKUP($M2,'Nature Editor'!$A:$A,'Nature Editor'!$E:$E,1))),stab,IF(OR(mtype=XLOOKUP('Boss Editor'!$C$4,'Pokemon Editor'!$A:$A,'Pokemon Editor'!$C:$C,""),mtype=XLOOKUP('Boss Editor'!$C$4,'Pokemon Editor'!$A:$A,'Pokemon Editor'!$D:$D,"")),1.5,1),eff,(INDEX('Type Chart'!$B:$S,MATCH(mtype,'Type Chart'!$A:$A,0),MATCH(XLOOKUP($K2,'Pokemon Editor'!$A:$A,'Pokemon Editor'!$C:$C,""),'Type Chart'!$B$1:$S$1,0))*IF(XLOOKUP($K2,'Pokemon Editor'!$A:$A,'Pokemon Editor'!$D:$D,"")="",1,INDEX('Type Chart'!$B:$S,MATCH(mtype,'Type Chart'!$A:$A,0),MATCH(XLOOKUP($K2,'Pokemon Editor'!$A:$A,'Pokemon Editor'!$D:$D,""),'Type Chart'!$B$1:$S$1,0)))),base,IF(OR(cat="Status",pow=0),0,FLOOR(FLOOR(FLOOR((2*'Boss Editor'!$D$4/5+2)*pow*atk/def)/50)+2)),modifier,stab*eff,AVERAGE(ARRAYFORMULA(FLOOR(base*modifier*SEQUENCE(16,1,85,1)/100)))/(FLOOR(((2*XLOOKUP($K2,'Pokemon Editor'!$A:$A,'Pokemon Editor'!$E:$E,0)+31+FLOOR($O2/4))*$L2)/100)+$L2+10)),0) | F2: =FLOOR((FLOOR(((2*XLOOKUP($K2,'Pokemon Editor'!$A:$A,'Pokemon Editor'!$J:$J,0)+31+FLOOR($T2/4))*$L2)/100)+5)*XLOOKUP($M2,'Nature Editor'!$A:$A,'Nature Editor'!$F:$F,1)) | G2: =FLOOR((FLOOR(((2*XLOOKUP('Boss Editor'!$C$4,'Pokemon Editor'!$A:$A,'Pokemon Editor'!$J:$J,0)+31+FLOOR('Boss Editor'!$L$4/4))*'Boss Editor'!$D$4)/100)+5)*XLOOKUP('Boss Editor'!$E$4,'Nature Editor'!$A:$A,'Nature Editor'!$F:$F,1)) | H2: =IF(F2>G2,"Yes","No") | I2: =C2-E2 | J2: =IFS(AND(C2>=0.5,E2<0.5),"Dominant",AND(C2>=0.35,E2<0.75),"Strong",AND(C2>=0.25,E2<1),"Viable",AND(C2>=0.15,E2<1.25),"Risky",TRUE,"Poor") | K2: =REDUCE($Y2,SEQUENCE(2),LAMBDA(current_species,unused_step,IFERROR(INDEX(FILTER('Evolution Editor'!$D$2:$D,'Evolution Editor'!$A$2:$A=current_species,'Evolution Editor'!$F$2:$F=TRUE,'Evolution Editor'!$E$2:$E<=$L2),1),current_species))) | L2: 15 | M2: Neutral | N2: ABILITY_IRON_FIST | O2: 0 | P2: 0 | Q2: 0 | R2: 0 | S2: 0 | T2: 0 | U2: =IFERROR(LET(mtype,XLOOKUP($B2,'Move Editor'!$B:$B,'Move Editor'!$C:$C,""),cat,XLOOKUP($B2,'Move Editor'!$B:$B,'Move Editor'!$D:$D,""),pow,XLOOKUP($B2,'Move Editor'!$B:$B,'Move Editor'!$E:$E,0),acc,XLOOKUP($B2,'Move Editor'!$B:$B,'Move Editor'!$F:$F,100),atk,IF(cat="Physical",FLOOR((FLOOR(((2*XLOOKUP($K2,'Pokemon Editor'!$A:$A,'Pokemon Editor'!$F:$F,0)+31+FLOOR($P2/4))*$L2)/100)+5)*XLOOKUP($M2,'Nature Editor'!$A:$A,'Nature Editor'!$B:$B,1)),FLOOR((FLOOR(((2*XLOOKUP($K2,'Pokemon Editor'!$A:$A,'Pokemon Editor'!$H:$H,0)+31+FLOOR($R2/4))*$L2)/100)+5)*XLOOKUP($M2,'Nature Editor'!$A:$A,'Nature Editor'!$D:$D,1))),def,IF(cat="Physical",FLOOR((FLOOR(((2*XLOOKUP('Boss Editor'!$C$4,'Pokemon Editor'!$A:$A,'Pokemon Editor'!$G:$G,0)+31+FLOOR('Boss Editor'!$I$4/4))*'Boss Editor'!$D$4)/100)+5)*XLOOKUP('Boss Editor'!$E$4,'Nature Editor'!$A:$A,'Nature Editor'!$C:$C,1)),FLOOR((FLOOR(((2*XLOOKUP('Boss Editor'!$C$4,'Pokemon Editor'!$A:$A,'Pokemon Editor'!$I:$I,0)+31+FLOOR('Boss Editor'!$K$4/4))*'Boss Editor'!$D$4)/100)+5)*XLOOKUP('Boss Editor'!$E$4,'Nature Editor'!$A:$A,'Nature Editor'!$E:$E,1))),stab,IF(OR(mtype=XLOOKUP($K2,'Pokemon Editor'!$A:$A,'Pokemon Editor'!$C:$C,""),mtype=XLOOKUP($K2,'Pokemon Editor'!$A:$A,'Pokemon Editor'!$D:$D,"")),1.5,1),eff,(INDEX('Type Chart'!$B:$S,MATCH(mtype,'Type Chart'!$A:$A,0),MATCH(XLOOKUP('Boss Editor'!$C$4,'Pokemon Editor'!$A:$A,'Pokemon Editor'!$C:$C,""),'Type Chart'!$B$1:$S$1,0))*IF(XLOOKUP('Boss Editor'!$C$4,'Pokemon Editor'!$A:$A,'Pokemon Editor'!$D:$D,"")="",1,INDEX('Type Chart'!$B:$S,MATCH(mtype,'Type Chart'!$A:$A,0),MATCH(XLOOKUP('Boss Editor'!$C$4,'Pokemon Editor'!$A:$A,'Pokemon Editor'!$D:$D,""),'Type Chart'!$B$1:$S$1,0)))),base,IF(OR(cat="Status",pow=0),0,FLOOR(FLOOR(FLOOR((2*$L2/5+2)*pow*atk/def)/50)+2)),modifier,stab*eff,FLOOR(base*modifier*0.85)),0) | V2: =IFERROR(LET(mtype,XLOOKUP($B2,'Move Editor'!$B:$B,'Move Editor'!$C:$C,""),cat,XLOOKUP($B2,'Move Editor'!$B:$B,'Move Editor'!$D:$D,""),pow,XLOOKUP($B2,'Move Editor'!$B:$B,'Move Editor'!$E:$E,0),acc,XLOOKUP($B2,'Move Editor'!$B:$B,'Move Editor'!$F:$F,100),atk,IF(cat="Physical",FLOOR((FLOOR(((2*XLOOKUP($K2,'Pokemon Editor'!$A:$A,'Pokemon Editor'!$F:$F,0)+31+FLOOR($P2/4))*$L2)/100)+5)*XLOOKUP($M2,'Nature Editor'!$A:$A,'Nature Editor'!$B:$B,1)),FLOOR((FLOOR(((2*XLOOKUP($K2,'Pokemon Editor'!$A:$A,'Pokemon Editor'!$H:$H,0)+31+FLOOR($R2/4))*$L2)/100)+5)*XLOOKUP($M2,'Nature Editor'!$A:$A,'Nature Editor'!$D:$D,1))),def,IF(cat="Physical",FLOOR((FLOOR(((2*XLOOKUP('Boss Editor'!$C$4,'Pokemon Editor'!$A:$A,'Pokemon Editor'!$G:$G,0)+31+FLOOR('Boss Editor'!$I$4/4))*'Boss Editor'!$D$4)/100)+5)*XLOOKUP('Boss Editor'!$E$4,'Nature Editor'!$A:$A,'Nature Editor'!$C:$C,1)),FLOOR((FLOOR(((2*XLOOKUP('Boss Editor'!$C$4,'Pokemon Editor'!$A:$A,'Pokemon Editor'!$I:$I,0)+31+FLOOR('Boss Editor'!$K$4/4))*'Boss Editor'!$D$4)/100)+5)*XLOOKUP('Boss Editor'!$E$4,'Nature Editor'!$A:$A,'Nature Editor'!$E:$E,1))),stab,IF(OR(mtype=XLOOKUP($K2,'Pokemon Editor'!$A:$A,'Pokemon Editor'!$C:$C,""),mtype=XLOOKUP($K2,'Pokemon Editor'!$A:$A,'Pokemon Editor'!$D:$D,"")),1.5,1),eff,(INDEX('Type Chart'!$B:$S,MATCH(mtype,'Type Chart'!$A:$A,0),MATCH(XLOOKUP('Boss Editor'!$C$4,'Pokemon Editor'!$A:$A,'Pokemon Editor'!$C:$C,""),'Type Chart'!$B$1:$S$1,0))*IF(XLOOKUP('Boss Editor'!$C$4,'Pokemon Editor'!$A:$A,'Pokemon Editor'!$D:$D,"")="",1,INDEX('Type Chart'!$B:$S,MATCH(mtype,'Type Chart'!$A:$A,0),MATCH(XLOOKUP('Boss Editor'!$C$4,'Pokemon Editor'!$A:$A,'Pokemon Editor'!$D:$D,""),'Type Chart'!$B$1:$S$1,0)))),base,IF(OR(cat="Status",pow=0),0,FLOOR(FLOOR(FLOOR((2*$L2/5+2)*pow*atk/def)/50)+2)),modifier,stab*eff,FLOOR(base*modifier)),0) | W2: =IFERROR(LET(mtype,XLOOKUP($D2,'Move Editor'!$B:$B,'Move Editor'!$C:$C,""),cat,XLOOKUP($D2,'Move Editor'!$B:$B,'Move Editor'!$D:$D,""),pow,XLOOKUP($D2,'Move Editor'!$B:$B,'Move Editor'!$E:$E,0),acc,XLOOKUP($D2,'Move Editor'!$B:$B,'Move Editor'!$F:$F,100),atk,IF(cat="Physical",FLOOR((FLOOR(((2*XLOOKUP('Boss Editor'!$C$4,'Pokemon Editor'!$A:$A,'Pokemon Editor'!$F:$F,0)+31+FLOOR('Boss Editor'!$H$4/4))*'Boss Editor'!$D$4)/100)+5)*XLOOKUP('Boss Editor'!$E$4,'Nature Editor'!$A:$A,'Nature Editor'!$B:$B,1)),FLOOR((FLOOR(((2*XLOOKUP('Boss Editor'!$C$4,'Pokemon Editor'!$A:$A,'Pokemon Editor'!$H:$H,0)+31+FLOOR('Boss Editor'!$J$4/4))*'Boss Editor'!$D$4)/100)+5)*XLOOKUP('Boss Editor'!$E$4,'Nature Editor'!$A:$A,'Nature Editor'!$D:$D,1))),def,IF(cat="Physical",FLOOR((FLOOR(((2*XLOOKUP($K2,'Pokemon Editor'!$A:$A,'Pokemon Editor'!$G:$G,0)+31+FLOOR($Q2/4))*$L2)/100)+5)*XLOOKUP($M2,'Nature Editor'!$A:$A,'Nature Editor'!$C:$C,1)),FLOOR((FLOOR(((2*XLOOKUP($K2,'Pokemon Editor'!$A:$A,'Pokemon Editor'!$I:$I,0)+31+FLOOR($S2/4))*$L2)/100)+5)*XLOOKUP($M2,'Nature Editor'!$A:$A,'Nature Editor'!$E:$E,1))),stab,IF(OR(mtype=XLOOKUP('Boss Editor'!$C$4,'Pokemon Editor'!$A:$A,'Pokemon Editor'!$C:$C,""),mtype=XLOOKUP('Boss Editor'!$C$4,'Pokemon Editor'!$A:$A,'Pokemon Editor'!$D:$D,"")),1.5,1),eff,(INDEX('Type Chart'!$B:$S,MATCH(mtype,'Type Chart'!$A:$A,0),MATCH(XLOOKUP($K2,'Pokemon Editor'!$A:$A,'Pokemon Editor'!$C:$C,""),'Type Chart'!$B$1:$S$1,0))*IF(XLOOKUP($K2,'Pokemon Editor'!$A:$A,'Pokemon Editor'!$D:$D,"")="",1,INDEX('Type Chart'!$B:$S,MATCH(mtype,'Type Chart'!$A:$A,0),MATCH(XLOOKUP($K2,'Pokemon Editor'!$A:$A,'Pokemon Editor'!$D:$D,""),'Type Chart'!$B$1:$S$1,0)))),base,IF(OR(cat="Status",pow=0),0,FLOOR(FLOOR(FLOOR((2*'Boss Editor'!$D$4/5+2)*pow*atk/def)/50)+2)),modifier,stab*eff,FLOOR(base*modifier*0.85)),0) | X2: =IFERROR(LET(mtype,XLOOKUP($D2,'Move Editor'!$B:$B,'Move Editor'!$C:$C,""),cat,XLOOKUP($D2,'Move Editor'!$B:$B,'Move Editor'!$D:$D,""),pow,XLOOKUP($D2,'Move Editor'!$B:$B,'Move Editor'!$E:$E,0),acc,XLOOKUP($D2,'Move Editor'!$B:$B,'Move Editor'!$F:$F,100),atk,IF(cat="Physical",FLOOR((FLOOR(((2*XLOOKUP('Boss Editor'!$C$4,'Pokemon Editor'!$A:$A,'Pokemon Editor'!$F:$F,0)+31+FLOOR('Boss Editor'!$H$4/4))*'Boss Editor'!$D$4)/100)+5)*XLOOKUP('Boss Editor'!$E$4,'Nature Editor'!$A:$A,'Nature Editor'!$B:$B,1)),FLOOR((FLOOR(((2*XLOOKUP('Boss Editor'!$C$4,'Pokemon Editor'!$A:$A,'Pokemon Editor'!$H:$H,0)+31+FLOOR('Boss Editor'!$J$4/4))*'Boss Editor'!$D$4)/100)+5)*XLOOKUP('Boss Editor'!$E$4,'Nature Editor'!$A:$A,'Nature Editor'!$D:$D,1))),def,IF(cat="Physical",FLOOR((FLOOR(((2*XLOOKUP($K2,'Pokemon Editor'!$A:$A,'Pokemon Editor'!$G:$G,0)+31+FLOOR($Q2/4))*$L2)/100)+5)*XLOOKUP($M2,'Nature Editor'!$A:$A,'Nature Editor'!$C:$C,1)),FLOOR((FLOOR(((2*XLOOKUP($K2,'Pokemon Editor'!$A:$A,'Pokemon Editor'!$I:$I,0)+31+FLOOR($S2/4))*$L2)/100)+5)*XLOOKUP($M2,'Nature Editor'!$A:$A,'Nature Editor'!$E:$E,1))),stab,IF(OR(mtype=XLOOKUP('Boss Editor'!$C$4,'Pokemon Editor'!$A:$A,'Pokemon Editor'!$C:$C,""),mtype=XLOOKUP('Boss Editor'!$C$4,'Pokemon Editor'!$A:$A,'Pokemon Editor'!$D:$D,"")),1.5,1),eff,(INDEX('Type Chart'!$B:$S,MATCH(mtype,'Type Chart'!$A:$A,0),MATCH(XLOOKUP($K2,'Pokemon Editor'!$A:$A,'Pokemon Editor'!$C:$C,""),'Type Chart'!$B$1:$S$1,0))*IF(XLOOKUP($K2,'Pokemon Editor'!$A:$A,'Pokemon Editor'!$D:$D,"")="",1,INDEX('Type Chart'!$B:$S,MATCH(mtype,'Type Chart'!$A:$A,0),MATCH(XLOOKUP($K2,'Pokemon Editor'!$A:$A,'Pokemon Editor'!$D:$D,""),'Type Chart'!$B$1:$S$1,0)))),base,IF(OR(cat="Status",pow=0),0,FLOOR(FLOOR(FLOOR((2*'Boss Editor'!$D$4/5+2)*pow*atk/def)/50)+2)),modifier,stab*eff,FLOOR(base*modifier)),0) | Y2: SPECIES_PANCHAM
A3: =XLOOKUP(K3,'Pokemon Editor'!$A:$A,'Pokemon Editor'!$B:$B,K3) | B3: =IF($Z3<>"",$Z3,IFERROR(INDEX(FILTER('Move Comparison'!$D$2:$D,'Move Comparison'!$Q$2:$Q=$Y3,'Move Comparison'!$M$2:$M=MAXIFS('Move Comparison'!$M$2:$M,'Move Comparison'!$Q$2:$Q,$Y3),'Move Comparison'!$D$2:$D<>""),1),"")) | C3: =IFERROR(LET(mtype,XLOOKUP($B3,'Move Editor'!$B:$B,'Move Editor'!$C:$C,""),cat,XLOOKUP($B3,'Move Editor'!$B:$B,'Move Editor'!$D:$D,""),pow,XLOOKUP($B3,'Move Editor'!$B:$B,'Move Editor'!$E:$E,0),acc,XLOOKUP($B3,'Move Editor'!$B:$B,'Move Editor'!$F:$F,100),atk,IF(cat="Physical",FLOOR((FLOOR(((2*XLOOKUP($K3,'Pokemon Editor'!$A:$A,'Pokemon Editor'!$F:$F,0)+31+FLOOR($P3/4))*$L3)/100)+5)*XLOOKUP($M3,'Nature Editor'!$A:$A,'Nature Editor'!$B:$B,1)),FLOOR((FLOOR(((2*XLOOKUP($K3,'Pokemon Editor'!$A:$A,'Pokemon Editor'!$H:$H,0)+31+FLOOR($R3/4))*$L3)/100)+5)*XLOOKUP($M3,'Nature Editor'!$A:$A,'Nature Editor'!$D:$D,1))),def,IF(cat="Physical",FLOOR((FLOOR(((2*XLOOKUP('Boss Editor'!$C$4,'Pokemon Editor'!$A:$A,'Pokemon Editor'!$G:$G,0)+31+FLOOR('Boss Editor'!$I$4/4))*'Boss Editor'!$D$4)/100)+5)*XLOOKUP('Boss Editor'!$E$4,'Nature Editor'!$A:$A,'Nature Editor'!$C:$C,1)),FLOOR((FLOOR(((2*XLOOKUP('Boss Editor'!$C$4,'Pokemon Editor'!$A:$A,'Pokemon Editor'!$I:$I,0)+31+FLOOR('Boss Editor'!$K$4/4))*'Boss Editor'!$D$4)/100)+5)*XLOOKUP('Boss Editor'!$E$4,'Nature Editor'!$A:$A,'Nature Editor'!$E:$E,1))),stab,IF(OR(mtype=XLOOKUP($K3,'Pokemon Editor'!$A:$A,'Pokemon Editor'!$C:$C,""),mtype=XLOOKUP($K3,'Pokemon Editor'!$A:$A,'Pokemon Editor'!$D:$D,"")),1.5,1),eff,(INDEX('Type Chart'!$B:$S,MATCH(mtype,'Type Chart'!$A:$A,0),MATCH(XLOOKUP('Boss Editor'!$C$4,'Pokemon Editor'!$A:$A,'Pokemon Editor'!$C:$C,""),'Type Chart'!$B$1:$S$1,0))*IF(XLOOKUP('Boss Editor'!$C$4,'Pokemon Editor'!$A:$A,'Pokemon Editor'!$D:$D,"")="",1,INDEX('Type Chart'!$B:$S,MATCH(mtype,'Type Chart'!$A:$A,0),MATCH(XLOOKUP('Boss Editor'!$C$4,'Pokemon Editor'!$A:$A,'Pokemon Editor'!$D:$D,""),'Type Chart'!$B$1:$S$1,0)))),base,IF(OR(cat="Status",pow=0),0,FLOOR(FLOOR(FLOOR((2*$L3/5+2)*pow*atk/def)/50)+2)),modifier,stab*eff,AVERAGE(ARRAYFORMULA(FLOOR(base*modifier*SEQUENCE(16,1,85,1)/100)))/(FLOOR(((2*XLOOKUP('Boss Editor'!$C$4,'Pokemon Editor'!$A:$A,'Pokemon Editor'!$E:$E,0)+31+FLOOR('Boss Editor'!$G$4/4))*'Boss Editor'!$D$4)/100)+'Boss Editor'!$D$4+10)),0) | D3: Astonish | E3: =IFERROR(LET(mtype,XLOOKUP($D3,'Move Editor'!$B:$B,'Move Editor'!$C:$C,""),cat,XLOOKUP($D3,'Move Editor'!$B:$B,'Move Editor'!$D:$D,""),pow,XLOOKUP($D3,'Move Editor'!$B:$B,'Move Editor'!$E:$E,0),acc,XLOOKUP($D3,'Move Editor'!$B:$B,'Move Editor'!$F:$F,100),atk,IF(cat="Physical",FLOOR((FLOOR(((2*XLOOKUP('Boss Editor'!$C$4,'Pokemon Editor'!$A:$A,'Pokemon Editor'!$F:$F,0)+31+FLOOR('Boss Editor'!$H$4/4))*'Boss Editor'!$D$4)/100)+5)*XLOOKUP('Boss Editor'!$E$4,'Nature Editor'!$A:$A,'Nature Editor'!$B:$B,1)),FLOOR((FLOOR(((2*XLOOKUP('Boss Editor'!$C$4,'Pokemon Editor'!$A:$A,'Pokemon Editor'!$H:$H,0)+31+FLOOR('Boss Editor'!$J$4/4))*'Boss Editor'!$D$4)/100)+5)*XLOOKUP('Boss Editor'!$E$4,'Nature Editor'!$A:$A,'Nature Editor'!$D:$D,1))),def,IF(cat="Physical",FLOOR((FLOOR(((2*XLOOKUP($K3,'Pokemon Editor'!$A:$A,'Pokemon Editor'!$G:$G,0)+31+FLOOR($Q3/4))*$L3)/100)+5)*XLOOKUP($M3,'Nature Editor'!$A:$A,'Nature Editor'!$C:$C,1)),FLOOR((FLOOR(((2*XLOOKUP($K3,'Pokemon Editor'!$A:$A,'Pokemon Editor'!$I:$I,0)+31+FLOOR($S3/4))*$L3)/100)+5)*XLOOKUP($M3,'Nature Editor'!$A:$A,'Nature Editor'!$E:$E,1))),stab,IF(OR(mtype=XLOOKUP('Boss Editor'!$C$4,'Pokemon Editor'!$A:$A,'Pokemon Editor'!$C:$C,""),mtype=XLOOKUP('Boss Editor'!$C$4,'Pokemon Editor'!$A:$A,'Pokemon Editor'!$D:$D,"")),1.5,1),eff,(INDEX('Type Chart'!$B:$S,MATCH(mtype,'Type Chart'!$A:$A,0),MATCH(XLOOKUP($K3,'Pokemon Editor'!$A:$A,'Pokemon Editor'!$C:$C,""),'Type Chart'!$B$1:$S$1,0))*IF(XLOOKUP($K3,'Pokemon Editor'!$A:$A,'Pokemon Editor'!$D:$D,"")="",1,INDEX('Type Chart'!$B:$S,MATCH(mtype,'Type Chart'!$A:$A,0),MATCH(XLOOKUP($K3,'Pokemon Editor'!$A:$A,'Pokemon Editor'!$D:$D,""),'Type Chart'!$B$1:$S$1,0)))),base,IF(OR(cat="Status",pow=0),0,FLOOR(FLOOR(FLOOR((2*'Boss Editor'!$D$4/5+2)*pow*atk/def)/50)+2)),modifier,stab*eff,AVERAGE(ARRAYFORMULA(FLOOR(base*modifier*SEQUENCE(16,1,85,1)/100)))/(FLOOR(((2*XLOOKUP($K3,'Pokemon Editor'!$A:$A,'Pokemon Editor'!$E:$E,0)+31+FLOOR($O3/4))*$L3)/100)+$L3+10)),0) | F3: =FLOOR((FLOOR(((2*XLOOKUP($K3,'Pokemon Editor'!$A:$A,'Pokemon Editor'!$J:$J,0)+31+FLOOR($T3/4))*$L3)/100)+5)*XLOOKUP($M3,'Nature Editor'!$A:$A,'Nature Editor'!$F:$F,1)) | G3: =FLOOR((FLOOR(((2*XLOOKUP('Boss Editor'!$C$4,'Pokemon Editor'!$A:$A,'Pokemon Editor'!$J:$J,0)+31+FLOOR('Boss Editor'!$L$4/4))*'Boss Editor'!$D$4)/100)+5)*XLOOKUP('Boss Editor'!$E$4,'Nature Editor'!$A:$A,'Nature Editor'!$F:$F,1)) | H3: =IF(F3>G3,"Yes","No") | I3: =C3-E3 | J3: =IFS(AND(C3>=0.5,E3<0.5),"Dominant",AND(C3>=0.35,E3<0.75),"Strong",AND(C3>=0.25,E3<1),"Viable",AND(C3>=0.15,E3<1.25),"Risky",TRUE,"Poor") | K3: =REDUCE($Y3,SEQUENCE(2),LAMBDA(current_species,unused_step,IFERROR(INDEX(FILTER('Evolution Editor'!$D$2:$D,'Evolution Editor'!$A$2:$A=current_species,'Evolution Editor'!$F$2:$F=TRUE,'Evolution Editor'!$E$2:$E<=$L3),1),current_species))) | L3: 15 | M3: Neutral | N3: ABILITY_MOLD_BREAKER | O3: 0 | P3: 0 | Q3: 0 | R3: 0 | S3: 0 | T3: 0 | U3: =IFERROR(LET(mtype,XLOOKUP($B3,'Move Editor'!$B:$B,'Move Editor'!$C:$C,""),cat,XLOOKUP($B3,'Move Editor'!$B:$B,'Move Editor'!$D:$D,""),pow,XLOOKUP($B3,'Move Editor'!$B:$B,'Move Editor'!$E:$E,0),acc,XLOOKUP($B3,'Move Editor'!$B:$B,'Move Editor'!$F:$F,100),atk,IF(cat="Physical",FLOOR((FLOOR(((2*XLOOKUP($K3,'Pokemon Editor'!$A:$A,'Pokemon Editor'!$F:$F,0)+31+FLOOR($P3/4))*$L3)/100)+5)*XLOOKUP($M3,'Nature Editor'!$A:$A,'Nature Editor'!$B:$B,1)),FLOOR((FLOOR(((2*XLOOKUP($K3,'Pokemon Editor'!$A:$A,'Pokemon Editor'!$H:$H,0)+31+FLOOR($R3/4))*$L3)/100)+5)*XLOOKUP($M3,'Nature Editor'!$A:$A,'Nature Editor'!$D:$D,1))),def,IF(cat="Physical",FLOOR((FLOOR(((2*XLOOKUP('Boss Editor'!$C$4,'Pokemon Editor'!$A:$A,'Pokemon Editor'!$G:$G,0)+31+FLOOR('Boss Editor'!$I$4/4))*'Boss Editor'!$D$4)/100)+5)*XLOOKUP('Boss Editor'!$E$4,'Nature Editor'!$A:$A,'Nature Editor'!$C:$C,1)),FLOOR((FLOOR(((2*XLOOKUP('Boss Editor'!$C$4,'Pokemon Editor'!$A:$A,'Pokemon Editor'!$I:$I,0)+31+FLOOR('Boss Editor'!$K$4/4))*'Boss Editor'!$D$4)/100)+5)*XLOOKUP('Boss Editor'!$E$4,'Nature Editor'!$A:$A,'Nature Editor'!$E:$E,1))),stab,IF(OR(mtype=XLOOKUP($K3,'Pokemon Editor'!$A:$A,'Pokemon Editor'!$C:$C,""),mtype=XLOOKUP($K3,'Pokemon Editor'!$A:$A,'Pokemon Editor'!$D:$D,"")),1.5,1),eff,(INDEX('Type Chart'!$B:$S,MATCH(mtype,'Type Chart'!$A:$A,0),MATCH(XLOOKUP('Boss Editor'!$C$4,'Pokemon Editor'!$A:$A,'Pokemon Editor'!$C:$C,""),'Type Chart'!$B$1:$S$1,0))*IF(XLOOKUP('Boss Editor'!$C$4,'Pokemon Editor'!$A:$A,'Pokemon Editor'!$D:$D,"")="",1,INDEX('Type Chart'!$B:$S,MATCH(mtype,'Type Chart'!$A:$A,0),MATCH(XLOOKUP('Boss Editor'!$C$4,'Pokemon Editor'!$A:$A,'Pokemon Editor'!$D:$D,""),'Type Chart'!$B$1:$S$1,0)))),base,IF(OR(cat="Status",pow=0),0,FLOOR(FLOOR(FLOOR((2*$L3/5+2)*pow*atk/def)/50)+2)),modifier,stab*eff,FLOOR(base*modifier*0.85)),0) | V3: =IFERROR(LET(mtype,XLOOKUP($B3,'Move Editor'!$B:$B,'Move Editor'!$C:$C,""),cat,XLOOKUP($B3,'Move Editor'!$B:$B,'Move Editor'!$D:$D,""),pow,XLOOKUP($B3,'Move Editor'!$B:$B,'Move Editor'!$E:$E,0),acc,XLOOKUP($B3,'Move Editor'!$B:$B,'Move Editor'!$F:$F,100),atk,IF(cat="Physical",FLOOR((FLOOR(((2*XLOOKUP($K3,'Pokemon Editor'!$A:$A,'Pokemon Editor'!$F:$F,0)+31+FLOOR($P3/4))*$L3)/100)+5)*XLOOKUP($M3,'Nature Editor'!$A:$A,'Nature Editor'!$B:$B,1)),FLOOR((FLOOR(((2*XLOOKUP($K3,'Pokemon Editor'!$A:$A,'Pokemon Editor'!$H:$H,0)+31+FLOOR($R3/4))*$L3)/100)+5)*XLOOKUP($M3,'Nature Editor'!$A:$A,'Nature Editor'!$D:$D,1))),def,IF(cat="Physical",FLOOR((FLOOR(((2*XLOOKUP('Boss Editor'!$C$4,'Pokemon Editor'!$A:$A,'Pokemon Editor'!$G:$G,0)+31+FLOOR('Boss Editor'!$I$4/4))*'Boss Editor'!$D$4)/100)+5)*XLOOKUP('Boss Editor'!$E$4,'Nature Editor'!$A:$A,'Nature Editor'!$C:$C,1)),FLOOR((FLOOR(((2*XLOOKUP('Boss Editor'!$C$4,'Pokemon Editor'!$A:$A,'Pokemon Editor'!$I:$I,0)+31+FLOOR('Boss Editor'!$K$4/4))*'Boss Editor'!$D$4)/100)+5)*XLOOKUP('Boss Editor'!$E$4,'Nature Editor'!$A:$A,'Nature Editor'!$E:$E,1))),stab,IF(OR(mtype=XLOOKUP($K3,'Pokemon Editor'!$A:$A,'Pokemon Editor'!$C:$C,""),mtype=XLOOKUP($K3,'Pokemon Editor'!$A:$A,'Pokemon Editor'!$D:$D,"")),1.5,1),eff,(INDEX('Type Chart'!$B:$S,MATCH(mtype,'Type Chart'!$A:$A,0),MATCH(XLOOKUP('Boss Editor'!$C$4,'Pokemon Editor'!$A:$A,'Pokemon Editor'!$C:$C,""),'Type Chart'!$B$1:$S$1,0))*IF(XLOOKUP('Boss Editor'!$C$4,'Pokemon Editor'!$A:$A,'Pokemon Editor'!$D:$D,"")="",1,INDEX('Type Chart'!$B:$S,MATCH(mtype,'Type Chart'!$A:$A,0),MATCH(XLOOKUP('Boss Editor'!$C$4,'Pokemon Editor'!$A:$A,'Pokemon Editor'!$D:$D,""),'Type Chart'!$B$1:$S$1,0)))),base,IF(OR(cat="Status",pow=0),0,FLOOR(FLOOR(FLOOR((2*$L3/5+2)*pow*atk/def)/50)+2)),modifier,stab*eff,FLOOR(base*modifier)),0) | W3: =IFERROR(LET(mtype,XLOOKUP($D3,'Move Editor'!$B:$B,'Move Editor'!$C:$C,""),cat,XLOOKUP($D3,'Move Editor'!$B:$B,'Move Editor'!$D:$D,""),pow,XLOOKUP($D3,'Move Editor'!$B:$B,'Move Editor'!$E:$E,0),acc,XLOOKUP($D3,'Move Editor'!$B:$B,'Move Editor'!$F:$F,100),atk,IF(cat="Physical",FLOOR((FLOOR(((2*XLOOKUP('Boss Editor'!$C$4,'Pokemon Editor'!$A:$A,'Pokemon Editor'!$F:$F,0)+31+FLOOR('Boss Editor'!$H$4/4))*'Boss Editor'!$D$4)/100)+5)*XLOOKUP('Boss Editor'!$E$4,'Nature Editor'!$A:$A,'Nature Editor'!$B:$B,1)),FLOOR((FLOOR(((2*XLOOKUP('Boss Editor'!$C$4,'Pokemon Editor'!$A:$A,'Pokemon Editor'!$H:$H,0)+31+FLOOR('Boss Editor'!$J$4/4))*'Boss Editor'!$D$4)/100)+5)*XLOOKUP('Boss Editor'!$E$4,'Nature Editor'!$A:$A,'Nature Editor'!$D:$D,1))),def,IF(cat="Physical",FLOOR((FLOOR(((2*XLOOKUP($K3,'Pokemon Editor'!$A:$A,'Pokemon Editor'!$G:$G,0)+31+FLOOR($Q3/4))*$L3)/100)+5)*XLOOKUP($M3,'Nature Editor'!$A:$A,'Nature Editor'!$C:$C,1)),FLOOR((FLOOR(((2*XLOOKUP($K3,'Pokemon Editor'!$A:$A,'Pokemon Editor'!$I:$I,0)+31+FLOOR($S3/4))*$L3)/100)+5)*XLOOKUP($M3,'Nature Editor'!$A:$A,'Nature Editor'!$E:$E,1))),stab,IF(OR(mtype=XLOOKUP('Boss Editor'!$C$4,'Pokemon Editor'!$A:$A,'Pokemon Editor'!$C:$C,""),mtype=XLOOKUP('Boss Editor'!$C$4,'Pokemon Editor'!$A:$A,'Pokemon Editor'!$D:$D,"")),1.5,1),eff,(INDEX('Type Chart'!$B:$S,MATCH(mtype,'Type Chart'!$A:$A,0),MATCH(XLOOKUP($K3,'Pokemon Editor'!$A:$A,'Pokemon Editor'!$C:$C,""),'Type Chart'!$B$1:$S$1,0))*IF(XLOOKUP($K3,'Pokemon Editor'!$A:$A,'Pokemon Editor'!$D:$D,"")="",1,INDEX('Type Chart'!$B:$S,MATCH(mtype,'Type Chart'!$A:$A,0),MATCH(XLOOKUP($K3,'Pokemon Editor'!$A:$A,'Pokemon Editor'!$D:$D,""),'Type Chart'!$B$1:$S$1,0)))),base,IF(OR(cat="Status",pow=0),0,FLOOR(FLOOR(FLOOR((2*'Boss Editor'!$D$4/5+2)*pow*atk/def)/50)+2)),modifier,stab*eff,FLOOR(base*modifier*0.85)),0) | X3: =IFERROR(LET(mtype,XLOOKUP($D3,'Move Editor'!$B:$B,'Move Editor'!$C:$C,""),cat,XLOOKUP($D3,'Move Editor'!$B:$B,'Move Editor'!$D:$D,""),pow,XLOOKUP($D3,'Move Editor'!$B:$B,'Move Editor'!$E:$E,0),acc,XLOOKUP($D3,'Move Editor'!$B:$B,'Move Editor'!$F:$F,100),atk,IF(cat="Physical",FLOOR((FLOOR(((2*XLOOKUP('Boss Editor'!$C$4,'Pokemon Editor'!$A:$A,'Pokemon Editor'!$F:$F,0)+31+FLOOR('Boss Editor'!$H$4/4))*'Boss Editor'!$D$4)/100)+5)*XLOOKUP('Boss Editor'!$E$4,'Nature Editor'!$A:$A,'Nature Editor'!$B:$B,1)),FLOOR((FLOOR(((2*XLOOKUP('Boss Editor'!$C$4,'Pokemon Editor'!$A:$A,'Pokemon Editor'!$H:$H,0)+31+FLOOR('Boss Editor'!$J$4/4))*'Boss Editor'!$D$4)/100)+5)*XLOOKUP('Boss Editor'!$E$4,'Nature Editor'!$A:$A,'Nature Editor'!$D:$D,1))),def,IF(cat="Physical",FLOOR((FLOOR(((2*XLOOKUP($K3,'Pokemon Editor'!$A:$A,'Pokemon Editor'!$G:$G,0)+31+FLOOR($Q3/4))*$L3)/100)+5)*XLOOKUP($M3,'Nature Editor'!$A:$A,'Nature Editor'!$C:$C,1)),FLOOR((FLOOR(((2*XLOOKUP($K3,'Pokemon Editor'!$A:$A,'Pokemon Editor'!$I:$I,0)+31+FLOOR($S3/4))*$L3)/100)+5)*XLOOKUP($M3,'Nature Editor'!$A:$A,'Nature Editor'!$E:$E,1))),stab,IF(OR(mtype=XLOOKUP('Boss Editor'!$C$4,'Pokemon Editor'!$A:$A,'Pokemon Editor'!$C:$C,""),mtype=XLOOKUP('Boss Editor'!$C$4,'Pokemon Editor'!$A:$A,'Pokemon Editor'!$D:$D,"")),1.5,1),eff,(INDEX('Type Chart'!$B:$S,MATCH(mtype,'Type Chart'!$A:$A,0),MATCH(XLOOKUP($K3,'Pokemon Editor'!$A:$A,'Pokemon Editor'!$C:$C,""),'Type Chart'!$B$1:$S$1,0))*IF(XLOOKUP($K3,'Pokemon Editor'!$A:$A,'Pokemon Editor'!$D:$D,"")="",1,INDEX('Type Chart'!$B:$S,MATCH(mtype,'Type Chart'!$A:$A,0),MATCH(XLOOKUP($K3,'Pokemon Editor'!$A:$A,'Pokemon Editor'!$D:$D,""),'Type Chart'!$B$1:$S$1,0)))),base,IF(OR(cat="Status",pow=0),0,FLOOR(FLOOR(FLOOR((2*'Boss Editor'!$D$4/5+2)*pow*atk/def)/50)+2)),modifier,stab*eff,FLOOR(base*modifier)),0) | Y3: SPECIES_TINKATINK
A4: =XLOOKUP(K4,'Pokemon Editor'!$A:$A,'Pokemon Editor'!$B:$B,K4) | B4: =IF($Z4<>"",$Z4,IFERROR(INDEX(FILTER('Move Comparison'!$D$2:$D,'Move Comparison'!$Q$2:$Q=$Y4,'Move Comparison'!$M$2:$M=MAXIFS('Move Comparison'!$M$2:$M,'Move Comparison'!$Q$2:$Q,$Y4),'Move Comparison'!$D$2:$D<>""),1),"")) | C4: =IFERROR(LET(mtype,XLOOKUP($B4,'Move Editor'!$B:$B,'Move Editor'!$C:$C,""),cat,XLOOKUP($B4,'Move Editor'!$B:$B,'Move Editor'!$D:$D,""),pow,XLOOKUP($B4,'Move Editor'!$B:$B,'Move Editor'!$E:$E,0),acc,XLOOKUP($B4,'Move Editor'!$B:$B,'Move Editor'!$F:$F,100),atk,IF(cat="Physical",FLOOR((FLOOR(((2*XLOOKUP($K4,'Pokemon Editor'!$A:$A,'Pokemon Editor'!$F:$F,0)+31+FLOOR($P4/4))*$L4)/100)+5)*XLOOKUP($M4,'Nature Editor'!$A:$A,'Nature Editor'!$B:$B,1)),FLOOR((FLOOR(((2*XLOOKUP($K4,'Pokemon Editor'!$A:$A,'Pokemon Editor'!$H:$H,0)+31+FLOOR($R4/4))*$L4)/100)+5)*XLOOKUP($M4,'Nature Editor'!$A:$A,'Nature Editor'!$D:$D,1))),def,IF(cat="Physical",FLOOR((FLOOR(((2*XLOOKUP('Boss Editor'!$C$4,'Pokemon Editor'!$A:$A,'Pokemon Editor'!$G:$G,0)+31+FLOOR('Boss Editor'!$I$4/4))*'Boss Editor'!$D$4)/100)+5)*XLOOKUP('Boss Editor'!$E$4,'Nature Editor'!$A:$A,'Nature Editor'!$C:$C,1)),FLOOR((FLOOR(((2*XLOOKUP('Boss Editor'!$C$4,'Pokemon Editor'!$A:$A,'Pokemon Editor'!$I:$I,0)+31+FLOOR('Boss Editor'!$K$4/4))*'Boss Editor'!$D$4)/100)+5)*XLOOKUP('Boss Editor'!$E$4,'Nature Editor'!$A:$A,'Nature Editor'!$E:$E,1))),stab,IF(OR(mtype=XLOOKUP($K4,'Pokemon Editor'!$A:$A,'Pokemon Editor'!$C:$C,""),mtype=XLOOKUP($K4,'Pokemon Editor'!$A:$A,'Pokemon Editor'!$D:$D,"")),1.5,1),eff,(INDEX('Type Chart'!$B:$S,MATCH(mtype,'Type Chart'!$A:$A,0),MATCH(XLOOKUP('Boss Editor'!$C$4,'Pokemon Editor'!$A:$A,'Pokemon Editor'!$C:$C,""),'Type Chart'!$B$1:$S$1,0))*IF(XLOOKUP('Boss Editor'!$C$4,'Pokemon Editor'!$A:$A,'Pokemon Editor'!$D:$D,"")="",1,INDEX('Type Chart'!$B:$S,MATCH(mtype,'Type Chart'!$A:$A,0),MATCH(XLOOKUP('Boss Editor'!$C$4,'Pokemon Editor'!$A:$A,'Pokemon Editor'!$D:$D,""),'Type Chart'!$B$1:$S$1,0)))),base,IF(OR(cat="Status",pow=0),0,FLOOR(FLOOR(FLOOR((2*$L4/5+2)*pow*atk/def)/50)+2)),modifier,stab*eff,AVERAGE(ARRAYFORMULA(FLOOR(base*modifier*SEQUENCE(16,1,85,1)/100)))/(FLOOR(((2*XLOOKUP('Boss Editor'!$C$4,'Pokemon Editor'!$A:$A,'Pokemon Editor'!$E:$E,0)+31+FLOOR('Boss Editor'!$G$4/4))*'Boss Editor'!$D$4)/100)+'Boss Editor'!$D$4+10)),0) | D4: Acid | E4: =IFERROR(LET(mtype,XLOOKUP($D4,'Move Editor'!$B:$B,'Move Editor'!$C:$C,""),cat,XLOOKUP($D4,'Move Editor'!$B:$B,'Move Editor'!$D:$D,""),pow,XLOOKUP($D4,'Move Editor'!$B:$B,'Move Editor'!$E:$E,0),acc,XLOOKUP($D4,'Move Editor'!$B:$B,'Move Editor'!$F:$F,100),atk,IF(cat="Physical",FLOOR((FLOOR(((2*XLOOKUP('Boss Editor'!$C$4,'Pokemon Editor'!$A:$A,'Pokemon Editor'!$F:$F,0)+31+FLOOR('Boss Editor'!$H$4/4))*'Boss Editor'!$D$4)/100)+5)*XLOOKUP('Boss Editor'!$E$4,'Nature Editor'!$A:$A,'Nature Editor'!$B:$B,1)),FLOOR((FLOOR(((2*XLOOKUP('Boss Editor'!$C$4,'Pokemon Editor'!$A:$A,'Pokemon Editor'!$H:$H,0)+31+FLOOR('Boss Editor'!$J$4/4))*'Boss Editor'!$D$4)/100)+5)*XLOOKUP('Boss Editor'!$E$4,'Nature Editor'!$A:$A,'Nature Editor'!$D:$D,1))),def,IF(cat="Physical",FLOOR((FLOOR(((2*XLOOKUP($K4,'Pokemon Editor'!$A:$A,'Pokemon Editor'!$G:$G,0)+31+FLOOR($Q4/4))*$L4)/100)+5)*XLOOKUP($M4,'Nature Editor'!$A:$A,'Nature Editor'!$C:$C,1)),FLOOR((FLOOR(((2*XLOOKUP($K4,'Pokemon Editor'!$A:$A,'Pokemon Editor'!$I:$I,0)+31+FLOOR($S4/4))*$L4)/100)+5)*XLOOKUP($M4,'Nature Editor'!$A:$A,'Nature Editor'!$E:$E,1))),stab,IF(OR(mtype=XLOOKUP('Boss Editor'!$C$4,'Pokemon Editor'!$A:$A,'Pokemon Editor'!$C:$C,""),mtype=XLOOKUP('Boss Editor'!$C$4,'Pokemon Editor'!$A:$A,'Pokemon Editor'!$D:$D,"")),1.5,1),eff,(INDEX('Type Chart'!$B:$S,MATCH(mtype,'Type Chart'!$A:$A,0),MATCH(XLOOKUP($K4,'Pokemon Editor'!$A:$A,'Pokemon Editor'!$C:$C,""),'Type Chart'!$B$1:$S$1,0))*IF(XLOOKUP($K4,'Pokemon Editor'!$A:$A,'Pokemon Editor'!$D:$D,"")="",1,INDEX('Type Chart'!$B:$S,MATCH(mtype,'Type Chart'!$A:$A,0),MATCH(XLOOKUP($K4,'Pokemon Editor'!$A:$A,'Pokemon Editor'!$D:$D,""),'Type Chart'!$B$1:$S$1,0)))),base,IF(OR(cat="Status",pow=0),0,FLOOR(FLOOR(FLOOR((2*'Boss Editor'!$D$4/5+2)*pow*atk/def)/50)+2)),modifier,stab*eff,AVERAGE(ARRAYFORMULA(FLOOR(base*modifier*SEQUENCE(16,1,85,1)/100)))/(FLOOR(((2*XLOOKUP($K4,'Pokemon Editor'!$A:$A,'Pokemon Editor'!$E:$E,0)+31+FLOOR($O4/4))*$L4)/100)+$L4+10)),0) | F4: =FLOOR((FLOOR(((2*XLOOKUP($K4,'Pokemon Editor'!$A:$A,'Pokemon Editor'!$J:$J,0)+31+FLOOR($T4/4))*$L4)/100)+5)*XLOOKUP($M4,'Nature Editor'!$A:$A,'Nature Editor'!$F:$F,1)) | G4: =FLOOR((FLOOR(((2*XLOOKUP('Boss Editor'!$C$4,'Pokemon Editor'!$A:$A,'Pokemon Editor'!$J:$J,0)+31+FLOOR('Boss Editor'!$L$4/4))*'Boss Editor'!$D$4)/100)+5)*XLOOKUP('Boss Editor'!$E$4,'Nature Editor'!$A:$A,'Nature Editor'!$F:$F,1)) | H4: =IF(F4>G4,"Yes","No") | I4: =C4-E4 | J4: =IFS(AND(C4>=0.5,E4<0.5),"Dominant",AND(C4>=0.35,E4<0.75),"Strong",AND(C4>=0.25,E4<1),"Viable",AND(C4>=0.15,E4<1.25),"Risky",TRUE,"Poor") | K4: =REDUCE($Y4,SEQUENCE(2),LAMBDA(current_species,unused_step,IFERROR(INDEX(FILTER('Evolution Editor'!$D$2:$D,'Evolution Editor'!$A$2:$A=current_species,'Evolution Editor'!$F$2:$F=TRUE,'Evolution Editor'!$E$2:$E<=$L4),1),current_species))) | L4: 15 | M4: Neutral | N4: ABILITY_HONEY_GATHER | O4: 0 | P4: 0 | Q4: 0 | R4: 0 | S4: 0 | T4: 0 | U4: =IFERROR(LET(mtype,XLOOKUP($B4,'Move Editor'!$B:$B,'Move Editor'!$C:$C,""),cat,XLOOKUP($B4,'Move Editor'!$B:$B,'Move Editor'!$D:$D,""),pow,XLOOKUP($B4,'Move Editor'!$B:$B,'Move Editor'!$E:$E,0),acc,XLOOKUP($B4,'Move Editor'!$B:$B,'Move Editor'!$F:$F,100),atk,IF(cat="Physical",FLOOR((FLOOR(((2*XLOOKUP($K4,'Pokemon Editor'!$A:$A,'Pokemon Editor'!$F:$F,0)+31+FLOOR($P4/4))*$L4)/100)+5)*XLOOKUP($M4,'Nature Editor'!$A:$A,'Nature Editor'!$B:$B,1)),FLOOR((FLOOR(((2*XLOOKUP($K4,'Pokemon Editor'!$A:$A,'Pokemon Editor'!$H:$H,0)+31+FLOOR($R4/4))*$L4)/100)+5)*XLOOKUP($M4,'Nature Editor'!$A:$A,'Nature Editor'!$D:$D,1))),def,IF(cat="Physical",FLOOR((FLOOR(((2*XLOOKUP('Boss Editor'!$C$4,'Pokemon Editor'!$A:$A,'Pokemon Editor'!$G:$G,0)+31+FLOOR('Boss Editor'!$I$4/4))*'Boss Editor'!$D$4)/100)+5)*XLOOKUP('Boss Editor'!$E$4,'Nature Editor'!$A:$A,'Nature Editor'!$C:$C,1)),FLOOR((FLOOR(((2*XLOOKUP('Boss Editor'!$C$4,'Pokemon Editor'!$A:$A,'Pokemon Editor'!$I:$I,0)+31+FLOOR('Boss Editor'!$K$4/4))*'Boss Editor'!$D$4)/100)+5)*XLOOKUP('Boss Editor'!$E$4,'Nature Editor'!$A:$A,'Nature Editor'!$E:$E,1))),stab,IF(OR(mtype=XLOOKUP($K4,'Pokemon Editor'!$A:$A,'Pokemon Editor'!$C:$C,""),mtype=XLOOKUP($K4,'Pokemon Editor'!$A:$A,'Pokemon Editor'!$D:$D,"")),1.5,1),eff,(INDEX('Type Chart'!$B:$S,MATCH(mtype,'Type Chart'!$A:$A,0),MATCH(XLOOKUP('Boss Editor'!$C$4,'Pokemon Editor'!$A:$A,'Pokemon Editor'!$C:$C,""),'Type Chart'!$B$1:$S$1,0))*IF(XLOOKUP('Boss Editor'!$C$4,'Pokemon Editor'!$A:$A,'Pokemon Editor'!$D:$D,"")="",1,INDEX('Type Chart'!$B:$S,MATCH(mtype,'Type Chart'!$A:$A,0),MATCH(XLOOKUP('Boss Editor'!$C$4,'Pokemon Editor'!$A:$A,'Pokemon Editor'!$D:$D,""),'Type Chart'!$B$1:$S$1,0)))),base,IF(OR(cat="Status",pow=0),0,FLOOR(FLOOR(FLOOR((2*$L4/5+2)*pow*atk/def)/50)+2)),modifier,stab*eff,FLOOR(base*modifier*0.85)),0) | V4: =IFERROR(LET(mtype,XLOOKUP($B4,'Move Editor'!$B:$B,'Move Editor'!$C:$C,""),cat,XLOOKUP($B4,'Move Editor'!$B:$B,'Move Editor'!$D:$D,""),pow,XLOOKUP($B4,'Move Editor'!$B:$B,'Move Editor'!$E:$E,0),acc,XLOOKUP($B4,'Move Editor'!$B:$B,'Move Editor'!$F:$F,100),atk,IF(cat="Physical",FLOOR((FLOOR(((2*XLOOKUP($K4,'Pokemon Editor'!$A:$A,'Pokemon Editor'!$F:$F,0)+31+FLOOR($P4/4))*$L4)/100)+5)*XLOOKUP($M4,'Nature Editor'!$A:$A,'Nature Editor'!$B:$B,1)),FLOOR((FLOOR(((2*XLOOKUP($K4,'Pokemon Editor'!$A:$A,'Pokemon Editor'!$H:$H,0)+31+FLOOR($R4/4))*$L4)/100)+5)*XLOOKUP($M4,'Nature Editor'!$A:$A,'Nature Editor'!$D:$D,1))),def,IF(cat="Physical",FLOOR((FLOOR(((2*XLOOKUP('Boss Editor'!$C$4,'Pokemon Editor'!$A:$A,'Pokemon Editor'!$G:$G,0)+31+FLOOR('Boss Editor'!$I$4/4))*'Boss Editor'!$D$4)/100)+5)*XLOOKUP('Boss Editor'!$E$4,'Nature Editor'!$A:$A,'Nature Editor'!$C:$C,1)),FLOOR((FLOOR(((2*XLOOKUP('Boss Editor'!$C$4,'Pokemon Editor'!$A:$A,'Pokemon Editor'!$I:$I,0)+31+FLOOR('Boss Editor'!$K$4/4))*'Boss Editor'!$D$4)/100)+5)*XLOOKUP('Boss Editor'!$E$4,'Nature Editor'!$A:$A,'Nature Editor'!$E:$E,1))),stab,IF(OR(mtype=XLOOKUP($K4,'Pokemon Editor'!$A:$A,'Pokemon Editor'!$C:$C,""),mtype=XLOOKUP($K4,'Pokemon Editor'!$A:$A,'Pokemon Editor'!$D:$D,"")),1.5,1),eff,(INDEX('Type Chart'!$B:$S,MATCH(mtype,'Type Chart'!$A:$A,0),MATCH(XLOOKUP('Boss Editor'!$C$4,'Pokemon Editor'!$A:$A,'Pokemon Editor'!$C:$C,""),'Type Chart'!$B$1:$S$1,0))*IF(XLOOKUP('Boss Editor'!$C$4,'Pokemon Editor'!$A:$A,'Pokemon Editor'!$D:$D,"")="",1,INDEX('Type Chart'!$B:$S,MATCH(mtype,'Type Chart'!$A:$A,0),MATCH(XLOOKUP('Boss Editor'!$C$4,'Pokemon Editor'!$A:$A,'Pokemon Editor'!$D:$D,""),'Type Chart'!$B$1:$S$1,0)))),base,IF(OR(cat="Status",pow=0),0,FLOOR(FLOOR(FLOOR((2*$L4/5+2)*pow*atk/def)/50)+2)),modifier,stab*eff,FLOOR(base*modifier)),0) | W4: =IFERROR(LET(mtype,XLOOKUP($D4,'Move Editor'!$B:$B,'Move Editor'!$C:$C,""),cat,XLOOKUP($D4,'Move Editor'!$B:$B,'Move Editor'!$D:$D,""),pow,XLOOKUP($D4,'Move Editor'!$B:$B,'Move Editor'!$E:$E,0),acc,XLOOKUP($D4,'Move Editor'!$B:$B,'Move Editor'!$F:$F,100),atk,IF(cat="Physical",FLOOR((FLOOR(((2*XLOOKUP('Boss Editor'!$C$4,'Pokemon Editor'!$A:$A,'Pokemon Editor'!$F:$F,0)+31+FLOOR('Boss Editor'!$H$4/4))*'Boss Editor'!$D$4)/100)+5)*XLOOKUP('Boss Editor'!$E$4,'Nature Editor'!$A:$A,'Nature Editor'!$B:$B,1)),FLOOR((FLOOR(((2*XLOOKUP('Boss Editor'!$C$4,'Pokemon Editor'!$A:$A,'Pokemon Editor'!$H:$H,0)+31+FLOOR('Boss Editor'!$J$4/4))*'Boss Editor'!$D$4)/100)+5)*XLOOKUP('Boss Editor'!$E$4,'Nature Editor'!$A:$A,'Nature Editor'!$D:$D,1))),def,IF(cat="Physical",FLOOR((FLOOR(((2*XLOOKUP($K4,'Pokemon Editor'!$A:$A,'Pokemon Editor'!$G:$G,0)+31+FLOOR($Q4/4))*$L4)/100)+5)*XLOOKUP($M4,'Nature Editor'!$A:$A,'Nature Editor'!$C:$C,1)),FLOOR((FLOOR(((2*XLOOKUP($K4,'Pokemon Editor'!$A:$A,'Pokemon Editor'!$I:$I,0)+31+FLOOR($S4/4))*$L4)/100)+5)*XLOOKUP($M4,'Nature Editor'!$A:$A,'Nature Editor'!$E:$E,1))),stab,IF(OR(mtype=XLOOKUP('Boss Editor'!$C$4,'Pokemon Editor'!$A:$A,'Pokemon Editor'!$C:$C,""),mtype=XLOOKUP('Boss Editor'!$C$4,'Pokemon Editor'!$A:$A,'Pokemon Editor'!$D:$D,"")),1.5,1),eff,(INDEX('Type Chart'!$B:$S,MATCH(mtype,'Type Chart'!$A:$A,0),MATCH(XLOOKUP($K4,'Pokemon Editor'!$A:$A,'Pokemon Editor'!$C:$C,""),'Type Chart'!$B$1:$S$1,0))*IF(XLOOKUP($K4,'Pokemon Editor'!$A:$A,'Pokemon Editor'!$D:$D,"")="",1,INDEX('Type Chart'!$B:$S,MATCH(mtype,'Type Chart'!$A:$A,0),MATCH(XLOOKUP($K4,'Pokemon Editor'!$A:$A,'Pokemon Editor'!$D:$D,""),'Type Chart'!$B$1:$S$1,0)))),base,IF(OR(cat="Status",pow=0),0,FLOOR(FLOOR(FLOOR((2*'Boss Editor'!$D$4/5+2)*pow*atk/def)/50)+2)),modifier,stab*eff,FLOOR(base*modifier*0.85)),0) | X4: =IFERROR(LET(mtype,XLOOKUP($D4,'Move Editor'!$B:$B,'Move Editor'!$C:$C,""),cat,XLOOKUP($D4,'Move Editor'!$B:$B,'Move Editor'!$D:$D,""),pow,XLOOKUP($D4,'Move Editor'!$B:$B,'Move Editor'!$E:$E,0),acc,XLOOKUP($D4,'Move Editor'!$B:$B,'Move Editor'!$F:$F,100),atk,IF(cat="Physical",FLOOR((FLOOR(((2*XLOOKUP('Boss Editor'!$C$4,'Pokemon Editor'!$A:$A,'Pokemon Editor'!$F:$F,0)+31+FLOOR('Boss Editor'!$H$4/4))*'Boss Editor'!$D$4)/100)+5)*XLOOKUP('Boss Editor'!$E$4,'Nature Editor'!$A:$A,'Nature Editor'!$B:$B,1)),FLOOR((FLOOR(((2*XLOOKUP('Boss Editor'!$C$4,'Pokemon Editor'!$A:$A,'Pokemon Editor'!$H:$H,0)+31+FLOOR('Boss Editor'!$J$4/4))*'Boss Editor'!$D$4)/100)+5)*XLOOKUP('Boss Editor'!$E$4,'Nature Editor'!$A:$A,'Nature Editor'!$D:$D,1))),def,IF(cat="Physical",FLOOR((FLOOR(((2*XLOOKUP($K4,'Pokemon Editor'!$A:$A,'Pokemon Editor'!$G:$G,0)+31+FLOOR($Q4/4))*$L4)/100)+5)*XLOOKUP($M4,'Nature Editor'!$A:$A,'Nature Editor'!$C:$C,1)),FLOOR((FLOOR(((2*XLOOKUP($K4,'Pokemon Editor'!$A:$A,'Pokemon Editor'!$I:$I,0)+31+FLOOR($S4/4))*$L4)/100)+5)*XLOOKUP($M4,'Nature Editor'!$A:$A,'Nature Editor'!$E:$E,1))),stab,IF(OR(mtype=XLOOKUP('Boss Editor'!$C$4,'Pokemon Editor'!$A:$A,'Pokemon Editor'!$C:$C,""),mtype=XLOOKUP('Boss Editor'!$C$4,'Pokemon Editor'!$A:$A,'Pokemon Editor'!$D:$D,"")),1.5,1),eff,(INDEX('Type Chart'!$B:$S,MATCH(mtype,'Type Chart'!$A:$A,0),MATCH(XLOOKUP($K4,'Pokemon Editor'!$A:$A,'Pokemon Editor'!$C:$C,""),'Type Chart'!$B$1:$S$1,0))*IF(XLOOKUP($K4,'Pokemon Editor'!$A:$A,'Pokemon Editor'!$D:$D,"")="",1,INDEX('Type Chart'!$B:$S,MATCH(mtype,'Type Chart'!$A:$A,0),MATCH(XLOOKUP($K4,'Pokemon Editor'!$A:$A,'Pokemon Editor'!$D:$D,""),'Type Chart'!$B$1:$S$1,0)))),base,IF(OR(cat="Status",pow=0),0,FLOOR(FLOOR(FLOOR((2*'Boss Editor'!$D$4/5+2)*pow*atk/def)/50)+2)),modifier,stab*eff,FLOOR(base*modifier)),0) | Y4: SPECIES_COMBEE
A5: =XLOOKUP(K5,'Pokemon Editor'!$A:$A,'Pokemon Editor'!$B:$B,K5) | B5: =IF($Z5<>"",$Z5,IFERROR(INDEX(FILTER('Move Comparison'!$D$2:$D,'Move Comparison'!$Q$2:$Q=$Y5,'Move Comparison'!$M$2:$M=MAXIFS('Move Comparison'!$M$2:$M,'Move Comparison'!$Q$2:$Q,$Y5),'Move Comparison'!$D$2:$D<>""),1),"")) | C5: =IFERROR(LET(mtype,XLOOKUP($B5,'Move Editor'!$B:$B,'Move Editor'!$C:$C,""),cat,XLOOKUP($B5,'Move Editor'!$B:$B,'Move Editor'!$D:$D,""),pow,XLOOKUP($B5,'Move Editor'!$B:$B,'Move Editor'!$E:$E,0),acc,XLOOKUP($B5,'Move Editor'!$B:$B,'Move Editor'!$F:$F,100),atk,IF(cat="Physical",FLOOR((FLOOR(((2*XLOOKUP($K5,'Pokemon Editor'!$A:$A,'Pokemon Editor'!$F:$F,0)+31+FLOOR($P5/4))*$L5)/100)+5)*XLOOKUP($M5,'Nature Editor'!$A:$A,'Nature Editor'!$B:$B,1)),FLOOR((FLOOR(((2*XLOOKUP($K5,'Pokemon Editor'!$A:$A,'Pokemon Editor'!$H:$H,0)+31+FLOOR($R5/4))*$L5)/100)+5)*XLOOKUP($M5,'Nature Editor'!$A:$A,'Nature Editor'!$D:$D,1))),def,IF(cat="Physical",FLOOR((FLOOR(((2*XLOOKUP('Boss Editor'!$C$4,'Pokemon Editor'!$A:$A,'Pokemon Editor'!$G:$G,0)+31+FLOOR('Boss Editor'!$I$4/4))*'Boss Editor'!$D$4)/100)+5)*XLOOKUP('Boss Editor'!$E$4,'Nature Editor'!$A:$A,'Nature Editor'!$C:$C,1)),FLOOR((FLOOR(((2*XLOOKUP('Boss Editor'!$C$4,'Pokemon Editor'!$A:$A,'Pokemon Editor'!$I:$I,0)+31+FLOOR('Boss Editor'!$K$4/4))*'Boss Editor'!$D$4)/100)+5)*XLOOKUP('Boss Editor'!$E$4,'Nature Editor'!$A:$A,'Nature Editor'!$E:$E,1))),stab,IF(OR(mtype=XLOOKUP($K5,'Pokemon Editor'!$A:$A,'Pokemon Editor'!$C:$C,""),mtype=XLOOKUP($K5,'Pokemon Editor'!$A:$A,'Pokemon Editor'!$D:$D,"")),1.5,1),eff,(INDEX('Type Chart'!$B:$S,MATCH(mtype,'Type Chart'!$A:$A,0),MATCH(XLOOKUP('Boss Editor'!$C$4,'Pokemon Editor'!$A:$A,'Pokemon Editor'!$C:$C,""),'Type Chart'!$B$1:$S$1,0))*IF(XLOOKUP('Boss Editor'!$C$4,'Pokemon Editor'!$A:$A,'Pokemon Editor'!$D:$D,"")="",1,INDEX('Type Chart'!$B:$S,MATCH(mtype,'Type Chart'!$A:$A,0),MATCH(XLOOKUP('Boss Editor'!$C$4,'Pokemon Editor'!$A:$A,'Pokemon Editor'!$D:$D,""),'Type Chart'!$B$1:$S$1,0)))),base,IF(OR(cat="Status",pow=0),0,FLOOR(FLOOR(FLOOR((2*$L5/5+2)*pow*atk/def)/50)+2)),modifier,stab*eff,AVERAGE(ARRAYFORMULA(FLOOR(base*modifier*SEQUENCE(16,1,85,1)/100)))/(FLOOR(((2*XLOOKUP('Boss Editor'!$C$4,'Pokemon Editor'!$A:$A,'Pokemon Editor'!$E:$E,0)+31+FLOOR('Boss Editor'!$G$4/4))*'Boss Editor'!$D$4)/100)+'Boss Editor'!$D$4+10)),0) | D5: Acid | E5: =IFERROR(LET(mtype,XLOOKUP($D5,'Move Editor'!$B:$B,'Move Editor'!$C:$C,""),cat,XLOOKUP($D5,'Move Editor'!$B:$B,'Move Editor'!$D:$D,""),pow,XLOOKUP($D5,'Move Editor'!$B:$B,'Move Editor'!$E:$E,0),acc,XLOOKUP($D5,'Move Editor'!$B:$B,'Move Editor'!$F:$F,100),atk,IF(cat="Physical",FLOOR((FLOOR(((2*XLOOKUP('Boss Editor'!$C$4,'Pokemon Editor'!$A:$A,'Pokemon Editor'!$F:$F,0)+31+FLOOR('Boss Editor'!$H$4/4))*'Boss Editor'!$D$4)/100)+5)*XLOOKUP('Boss Editor'!$E$4,'Nature Editor'!$A:$A,'Nature Editor'!$B:$B,1)),FLOOR((FLOOR(((2*XLOOKUP('Boss Editor'!$C$4,'Pokemon Editor'!$A:$A,'Pokemon Editor'!$H:$H,0)+31+FLOOR('Boss Editor'!$J$4/4))*'Boss Editor'!$D$4)/100)+5)*XLOOKUP('Boss Editor'!$E$4,'Nature Editor'!$A:$A,'Nature Editor'!$D:$D,1))),def,IF(cat="Physical",FLOOR((FLOOR(((2*XLOOKUP($K5,'Pokemon Editor'!$A:$A,'Pokemon Editor'!$G:$G,0)+31+FLOOR($Q5/4))*$L5)/100)+5)*XLOOKUP($M5,'Nature Editor'!$A:$A,'Nature Editor'!$C:$C,1)),FLOOR((FLOOR(((2*XLOOKUP($K5,'Pokemon Editor'!$A:$A,'Pokemon Editor'!$I:$I,0)+31+FLOOR($S5/4))*$L5)/100)+5)*XLOOKUP($M5,'Nature Editor'!$A:$A,'Nature Editor'!$E:$E,1))),stab,IF(OR(mtype=XLOOKUP('Boss Editor'!$C$4,'Pokemon Editor'!$A:$A,'Pokemon Editor'!$C:$C,""),mtype=XLOOKUP('Boss Editor'!$C$4,'Pokemon Editor'!$A:$A,'Pokemon Editor'!$D:$D,"")),1.5,1),eff,(INDEX('Type Chart'!$B:$S,MATCH(mtype,'Type Chart'!$A:$A,0),MATCH(XLOOKUP($K5,'Pokemon Editor'!$A:$A,'Pokemon Editor'!$C:$C,""),'Type Chart'!$B$1:$S$1,0))*IF(XLOOKUP($K5,'Pokemon Editor'!$A:$A,'Pokemon Editor'!$D:$D,"")="",1,INDEX('Type Chart'!$B:$S,MATCH(mtype,'Type Chart'!$A:$A,0),MATCH(XLOOKUP($K5,'Pokemon Editor'!$A:$A,'Pokemon Editor'!$D:$D,""),'Type Chart'!$B$1:$S$1,0)))),base,IF(OR(cat="Status",pow=0),0,FLOOR(FLOOR(FLOOR((2*'Boss Editor'!$D$4/5+2)*pow*atk/def)/50)+2)),modifier,stab*eff,AVERAGE(ARRAYFORMULA(FLOOR(base*modifier*SEQUENCE(16,1,85,1)/100)))/(FLOOR(((2*XLOOKUP($K5,'Pokemon Editor'!$A:$A,'Pokemon Editor'!$E:$E,0)+31+FLOOR($O5/4))*$L5)/100)+$L5+10)),0) | F5: =FLOOR((FLOOR(((2*XLOOKUP($K5,'Pokemon Editor'!$A:$A,'Pokemon Editor'!$J:$J,0)+31+FLOOR($T5/4))*$L5)/100)+5)*XLOOKUP($M5,'Nature Editor'!$A:$A,'Nature Editor'!$F:$F,1)) | G5: =FLOOR((FLOOR(((2*XLOOKUP('Boss Editor'!$C$4,'Pokemon Editor'!$A:$A,'Pokemon Editor'!$J:$J,0)+31+FLOOR('Boss Editor'!$L$4/4))*'Boss Editor'!$D$4)/100)+5)*XLOOKUP('Boss Editor'!$E$4,'Nature Editor'!$A:$A,'Nature Editor'!$F:$F,1)) | H5: =IF(F5>G5,"Yes","No") | I5: =C5-E5 | J5: =IFS(AND(C5>=0.5,E5<0.5),"Dominant",AND(C5>=0.35,E5<0.75),"Strong",AND(C5>=0.25,E5<1),"Viable",AND(C5>=0.15,E5<1.25),"Risky",TRUE,"Poor") | K5: =REDUCE($Y5,SEQUENCE(2),LAMBDA(current_species,unused_step,IFERROR(INDEX(FILTER('Evolution Editor'!$D$2:$D,'Evolution Editor'!$A$2:$A=current_species,'Evolution Editor'!$F$2:$F=TRUE,'Evolution Editor'!$E$2:$E<=$L5),1),current_species))) | L5: 15 | M5: Neutral | N5: ABILITY_SWARM | O5: 0 | P5: 0 | Q5: 0 | R5: 0 | S5: 0 | T5: 0 | U5: =IFERROR(LET(mtype,XLOOKUP($B5,'Move Editor'!$B:$B,'Move Editor'!$C:$C,""),cat,XLOOKUP($B5,'Move Editor'!$B:$B,'Move Editor'!$D:$D,""),pow,XLOOKUP($B5,'Move Editor'!$B:$B,'Move Editor'!$E:$E,0),acc,XLOOKUP($B5,'Move Editor'!$B:$B,'Move Editor'!$F:$F,100),atk,IF(cat="Physical",FLOOR((FLOOR(((2*XLOOKUP($K5,'Pokemon Editor'!$A:$A,'Pokemon Editor'!$F:$F,0)+31+FLOOR($P5/4))*$L5)/100)+5)*XLOOKUP($M5,'Nature Editor'!$A:$A,'Nature Editor'!$B:$B,1)),FLOOR((FLOOR(((2*XLOOKUP($K5,'Pokemon Editor'!$A:$A,'Pokemon Editor'!$H:$H,0)+31+FLOOR($R5/4))*$L5)/100)+5)*XLOOKUP($M5,'Nature Editor'!$A:$A,'Nature Editor'!$D:$D,1))),def,IF(cat="Physical",FLOOR((FLOOR(((2*XLOOKUP('Boss Editor'!$C$4,'Pokemon Editor'!$A:$A,'Pokemon Editor'!$G:$G,0)+31+FLOOR('Boss Editor'!$I$4/4))*'Boss Editor'!$D$4)/100)+5)*XLOOKUP('Boss Editor'!$E$4,'Nature Editor'!$A:$A,'Nature Editor'!$C:$C,1)),FLOOR((FLOOR(((2*XLOOKUP('Boss Editor'!$C$4,'Pokemon Editor'!$A:$A,'Pokemon Editor'!$I:$I,0)+31+FLOOR('Boss Editor'!$K$4/4))*'Boss Editor'!$D$4)/100)+5)*XLOOKUP('Boss Editor'!$E$4,'Nature Editor'!$A:$A,'Nature Editor'!$E:$E,1))),stab,IF(OR(mtype=XLOOKUP($K5,'Pokemon Editor'!$A:$A,'Pokemon Editor'!$C:$C,""),mtype=XLOOKUP($K5,'Pokemon Editor'!$A:$A,'Pokemon Editor'!$D:$D,"")),1.5,1),eff,(INDEX('Type Chart'!$B:$S,MATCH(mtype,'Type Chart'!$A:$A,0),MATCH(XLOOKUP('Boss Editor'!$C$4,'Pokemon Editor'!$A:$A,'Pokemon Editor'!$C:$C,""),'Type Chart'!$B$1:$S$1,0))*IF(XLOOKUP('Boss Editor'!$C$4,'Pokemon Editor'!$A:$A,'Pokemon Editor'!$D:$D,"")="",1,INDEX('Type Chart'!$B:$S,MATCH(mtype,'Type Chart'!$A:$A,0),MATCH(XLOOKUP('Boss Editor'!$C$4,'Pokemon Editor'!$A:$A,'Pokemon Editor'!$D:$D,""),'Type Chart'!$B$1:$S$1,0)))),base,IF(OR(cat="Status",pow=0),0,FLOOR(FLOOR(FLOOR((2*$L5/5+2)*pow*atk/def)/50)+2)),modifier,stab*eff,FLOOR(base*modifier*0.85)),0) | V5: =IFERROR(LET(mtype,XLOOKUP($B5,'Move Editor'!$B:$B,'Move Editor'!$C:$C,""),cat,XLOOKUP($B5,'Move Editor'!$B:$B,'Move Editor'!$D:$D,""),pow,XLOOKUP($B5,'Move Editor'!$B:$B,'Move Editor'!$E:$E,0),acc,XLOOKUP($B5,'Move Editor'!$B:$B,'Move Editor'!$F:$F,100),atk,IF(cat="Physical",FLOOR((FLOOR(((2*XLOOKUP($K5,'Pokemon Editor'!$A:$A,'Pokemon Editor'!$F:$F,0)+31+FLOOR($P5/4))*$L5)/100)+5)*XLOOKUP($M5,'Nature Editor'!$A:$A,'Nature Editor'!$B:$B,1)),FLOOR((FLOOR(((2*XLOOKUP($K5,'Pokemon Editor'!$A:$A,'Pokemon Editor'!$H:$H,0)+31+FLOOR($R5/4))*$L5)/100)+5)*XLOOKUP($M5,'Nature Editor'!$A:$A,'Nature Editor'!$D:$D,1))),def,IF(cat="Physical",FLOOR((FLOOR(((2*XLOOKUP('Boss Editor'!$C$4,'Pokemon Editor'!$A:$A,'Pokemon Editor'!$G:$G,0)+31+FLOOR('Boss Editor'!$I$4/4))*'Boss Editor'!$D$4)/100)+5)*XLOOKUP('Boss Editor'!$E$4,'Nature Editor'!$A:$A,'Nature Editor'!$C:$C,1)),FLOOR((FLOOR(((2*XLOOKUP('Boss Editor'!$C$4,'Pokemon Editor'!$A:$A,'Pokemon Editor'!$I:$I,0)+31+FLOOR('Boss Editor'!$K$4/4))*'Boss Editor'!$D$4)/100)+5)*XLOOKUP('Boss Editor'!$E$4,'Nature Editor'!$A:$A,'Nature Editor'!$E:$E,1))),stab,IF(OR(mtype=XLOOKUP($K5,'Pokemon Editor'!$A:$A,'Pokemon Editor'!$C:$C,""),mtype=XLOOKUP($K5,'Pokemon Editor'!$A:$A,'Pokemon Editor'!$D:$D,"")),1.5,1),eff,(INDEX('Type Chart'!$B:$S,MATCH(mtype,'Type Chart'!$A:$A,0),MATCH(XLOOKUP('Boss Editor'!$C$4,'Pokemon Editor'!$A:$A,'Pokemon Editor'!$C:$C,""),'Type Chart'!$B$1:$S$1,0))*IF(XLOOKUP('Boss Editor'!$C$4,'Pokemon Editor'!$A:$A,'Pokemon Editor'!$D:$D,"")="",1,INDEX('Type Chart'!$B:$S,MATCH(mtype,'Type Chart'!$A:$A,0),MATCH(XLOOKUP('Boss Editor'!$C$4,'Pokemon Editor'!$A:$A,'Pokemon Editor'!$D:$D,""),'Type Chart'!$B$1:$S$1,0)))),base,IF(OR(cat="Status",pow=0),0,FLOOR(FLOOR(FLOOR((2*$L5/5+2)*pow*atk/def)/50)+2)),modifier,stab*eff,FLOOR(base*modifier)),0) | W5: =IFERROR(LET(mtype,XLOOKUP($D5,'Move Editor'!$B:$B,'Move Editor'!$C:$C,""),cat,XLOOKUP($D5,'Move Editor'!$B:$B,'Move Editor'!$D:$D,""),pow,XLOOKUP($D5,'Move Editor'!$B:$B,'Move Editor'!$E:$E,0),acc,XLOOKUP($D5,'Move Editor'!$B:$B,'Move Editor'!$F:$F,100),atk,IF(cat="Physical",FLOOR((FLOOR(((2*XLOOKUP('Boss Editor'!$C$4,'Pokemon Editor'!$A:$A,'Pokemon Editor'!$F:$F,0)+31+FLOOR('Boss Editor'!$H$4/4))*'Boss Editor'!$D$4)/100)+5)*XLOOKUP('Boss Editor'!$E$4,'Nature Editor'!$A:$A,'Nature Editor'!$B:$B,1)),FLOOR((FLOOR(((2*XLOOKUP('Boss Editor'!$C$4,'Pokemon Editor'!$A:$A,'Pokemon Editor'!$H:$H,0)+31+FLOOR('Boss Editor'!$J$4/4))*'Boss Editor'!$D$4)/100)+5)*XLOOKUP('Boss Editor'!$E$4,'Nature Editor'!$A:$A,'Nature Editor'!$D:$D,1))),def,IF(cat="Physical",FLOOR((FLOOR(((2*XLOOKUP($K5,'Pokemon Editor'!$A:$A,'Pokemon Editor'!$G:$G,0)+31+FLOOR($Q5/4))*$L5)/100)+5)*XLOOKUP($M5,'Nature Editor'!$A:$A,'Nature Editor'!$C:$C,1)),FLOOR((FLOOR(((2*XLOOKUP($K5,'Pokemon Editor'!$A:$A,'Pokemon Editor'!$I:$I,0)+31+FLOOR($S5/4))*$L5)/100)+5)*XLOOKUP($M5,'Nature Editor'!$A:$A,'Nature Editor'!$E:$E,1))),stab,IF(OR(mtype=XLOOKUP('Boss Editor'!$C$4,'Pokemon Editor'!$A:$A,'Pokemon Editor'!$C:$C,""),mtype=XLOOKUP('Boss Editor'!$C$4,'Pokemon Editor'!$A:$A,'Pokemon Editor'!$D:$D,"")),1.5,1),eff,(INDEX('Type Chart'!$B:$S,MATCH(mtype,'Type Chart'!$A:$A,0),MATCH(XLOOKUP($K5,'Pokemon Editor'!$A:$A,'Pokemon Editor'!$C:$C,""),'Type Chart'!$B$1:$S$1,0))*IF(XLOOKUP($K5,'Pokemon Editor'!$A:$A,'Pokemon Editor'!$D:$D,"")="",1,INDEX('Type Chart'!$B:$S,MATCH(mtype,'Type Chart'!$A:$A,0),MATCH(XLOOKUP($K5,'Pokemon Editor'!$A:$A,'Pokemon Editor'!$D:$D,""),'Type Chart'!$B$1:$S$1,0)))),base,IF(OR(cat="Status",pow=0),0,FLOOR(FLOOR(FLOOR((2*'Boss Editor'!$D$4/5+2)*pow*atk/def)/50)+2)),modifier,stab*eff,FLOOR(base*modifier*0.85)),0) | X5: =IFERROR(LET(mtype,XLOOKUP($D5,'Move Editor'!$B:$B,'Move Editor'!$C:$C,""),cat,XLOOKUP($D5,'Move Editor'!$B:$B,'Move Editor'!$D:$D,""),pow,XLOOKUP($D5,'Move Editor'!$B:$B,'Move Editor'!$E:$E,0),acc,XLOOKUP($D5,'Move Editor'!$B:$B,'Move Editor'!$F:$F,100),atk,IF(cat="Physical",FLOOR((FLOOR(((2*XLOOKUP('Boss Editor'!$C$4,'Pokemon Editor'!$A:$A,'Pokemon Editor'!$F:$F,0)+31+FLOOR('Boss Editor'!$H$4/4))*'Boss Editor'!$D$4)/100)+5)*XLOOKUP('Boss Editor'!$E$4,'Nature Editor'!$A:$A,'Nature Editor'!$B:$B,1)),FLOOR((FLOOR(((2*XLOOKUP('Boss Editor'!$C$4,'Pokemon Editor'!$A:$A,'Pokemon Editor'!$H:$H,0)+31+FLOOR('Boss Editor'!$J$4/4))*'Boss Editor'!$D$4)/100)+5)*XLOOKUP('Boss Editor'!$E$4,'Nature Editor'!$A:$A,'Nature Editor'!$D:$D,1))),def,IF(cat="Physical",FLOOR((FLOOR(((2*XLOOKUP($K5,'Pokemon Editor'!$A:$A,'Pokemon Editor'!$G:$G,0)+31+FLOOR($Q5/4))*$L5)/100)+5)*XLOOKUP($M5,'Nature Editor'!$A:$A,'Nature Editor'!$C:$C,1)),FLOOR((FLOOR(((2*XLOOKUP($K5,'Pokemon Editor'!$A:$A,'Pokemon Editor'!$I:$I,0)+31+FLOOR($S5/4))*$L5)/100)+5)*XLOOKUP($M5,'Nature Editor'!$A:$A,'Nature Editor'!$E:$E,1))),stab,IF(OR(mtype=XLOOKUP('Boss Editor'!$C$4,'Pokemon Editor'!$A:$A,'Pokemon Editor'!$C:$C,""),mtype=XLOOKUP('Boss Editor'!$C$4,'Pokemon Editor'!$A:$A,'Pokemon Editor'!$D:$D,"")),1.5,1),eff,(INDEX('Type Chart'!$B:$S,MATCH(mtype,'Type Chart'!$A:$A,0),MATCH(XLOOKUP($K5,'Pokemon Editor'!$A:$A,'Pokemon Editor'!$C:$C,""),'Type Chart'!$B$1:$S$1,0))*IF(XLOOKUP($K5,'Pokemon Editor'!$A:$A,'Pokemon Editor'!$D:$D,"")="",1,INDEX('Type Chart'!$B:$S,MATCH(mtype,'Type Chart'!$A:$A,0),MATCH(XLOOKUP($K5,'Pokemon Editor'!$A:$A,'Pokemon Editor'!$D:$D,""),'Type Chart'!$B$1:$S$1,0)))),base,IF(OR(cat="Status",pow=0),0,FLOOR(FLOOR(FLOOR((2*'Boss Editor'!$D$4/5+2)*pow*atk/def)/50)+2)),modifier,stab*eff,FLOOR(base*modifier)),0) | Y5: SPECIES_SEWADDLE
A6: =XLOOKUP(K6,'Pokemon Editor'!$A:$A,'Pokemon Editor'!$B:$B,K6) | B6: =IF($Z6<>"",$Z6,IFERROR(INDEX(FILTER('Move Comparison'!$D$2:$D,'Move Comparison'!$Q$2:$Q=$Y6,'Move Comparison'!$M$2:$M=MAXIFS('Move Comparison'!$M$2:$M,'Move Comparison'!$Q$2:$Q,$Y6),'Move Comparison'!$D$2:$D<>""),1),"")) | C6: =IFERROR(LET(mtype,XLOOKUP($B6,'Move Editor'!$B:$B,'Move Editor'!$C:$C,""),cat,XLOOKUP($B6,'Move Editor'!$B:$B,'Move Editor'!$D:$D,""),pow,XLOOKUP($B6,'Move Editor'!$B:$B,'Move Editor'!$E:$E,0),acc,XLOOKUP($B6,'Move Editor'!$B:$B,'Move Editor'!$F:$F,100),atk,IF(cat="Physical",FLOOR((FLOOR(((2*XLOOKUP($K6,'Pokemon Editor'!$A:$A,'Pokemon Editor'!$F:$F,0)+31+FLOOR($P6/4))*$L6)/100)+5)*XLOOKUP($M6,'Nature Editor'!$A:$A,'Nature Editor'!$B:$B,1)),FLOOR((FLOOR(((2*XLOOKUP($K6,'Pokemon Editor'!$A:$A,'Pokemon Editor'!$H:$H,0)+31+FLOOR($R6/4))*$L6)/100)+5)*XLOOKUP($M6,'Nature Editor'!$A:$A,'Nature Editor'!$D:$D,1))),def,IF(cat="Physical",FLOOR((FLOOR(((2*XLOOKUP('Boss Editor'!$C$4,'Pokemon Editor'!$A:$A,'Pokemon Editor'!$G:$G,0)+31+FLOOR('Boss Editor'!$I$4/4))*'Boss Editor'!$D$4)/100)+5)*XLOOKUP('Boss Editor'!$E$4,'Nature Editor'!$A:$A,'Nature Editor'!$C:$C,1)),FLOOR((FLOOR(((2*XLOOKUP('Boss Editor'!$C$4,'Pokemon Editor'!$A:$A,'Pokemon Editor'!$I:$I,0)+31+FLOOR('Boss Editor'!$K$4/4))*'Boss Editor'!$D$4)/100)+5)*XLOOKUP('Boss Editor'!$E$4,'Nature Editor'!$A:$A,'Nature Editor'!$E:$E,1))),stab,IF(OR(mtype=XLOOKUP($K6,'Pokemon Editor'!$A:$A,'Pokemon Editor'!$C:$C,""),mtype=XLOOKUP($K6,'Pokemon Editor'!$A:$A,'Pokemon Editor'!$D:$D,"")),1.5,1),eff,(INDEX('Type Chart'!$B:$S,MATCH(mtype,'Type Chart'!$A:$A,0),MATCH(XLOOKUP('Boss Editor'!$C$4,'Pokemon Editor'!$A:$A,'Pokemon Editor'!$C:$C,""),'Type Chart'!$B$1:$S$1,0))*IF(XLOOKUP('Boss Editor'!$C$4,'Pokemon Editor'!$A:$A,'Pokemon Editor'!$D:$D,"")="",1,INDEX('Type Chart'!$B:$S,MATCH(mtype,'Type Chart'!$A:$A,0),MATCH(XLOOKUP('Boss Editor'!$C$4,'Pokemon Editor'!$A:$A,'Pokemon Editor'!$D:$D,""),'Type Chart'!$B$1:$S$1,0)))),base,IF(OR(cat="Status",pow=0),0,FLOOR(FLOOR(FLOOR((2*$L6/5+2)*pow*atk/def)/50)+2)),modifier,stab*eff,AVERAGE(ARRAYFORMULA(FLOOR(base*modifier*SEQUENCE(16,1,85,1)/100)))/(FLOOR(((2*XLOOKUP('Boss Editor'!$C$4,'Pokemon Editor'!$A:$A,'Pokemon Editor'!$E:$E,0)+31+FLOOR('Boss Editor'!$G$4/4))*'Boss Editor'!$D$4)/100)+'Boss Editor'!$D$4+10)),0) | D6: Acid | E6: =IFERROR(LET(mtype,XLOOKUP($D6,'Move Editor'!$B:$B,'Move Editor'!$C:$C,""),cat,XLOOKUP($D6,'Move Editor'!$B:$B,'Move Editor'!$D:$D,""),pow,XLOOKUP($D6,'Move Editor'!$B:$B,'Move Editor'!$E:$E,0),acc,XLOOKUP($D6,'Move Editor'!$B:$B,'Move Editor'!$F:$F,100),atk,IF(cat="Physical",FLOOR((FLOOR(((2*XLOOKUP('Boss Editor'!$C$4,'Pokemon Editor'!$A:$A,'Pokemon Editor'!$F:$F,0)+31+FLOOR('Boss Editor'!$H$4/4))*'Boss Editor'!$D$4)/100)+5)*XLOOKUP('Boss Editor'!$E$4,'Nature Editor'!$A:$A,'Nature Editor'!$B:$B,1)),FLOOR((FLOOR(((2*XLOOKUP('Boss Editor'!$C$4,'Pokemon Editor'!$A:$A,'Pokemon Editor'!$H:$H,0)+31+FLOOR('Boss Editor'!$J$4/4))*'Boss Editor'!$D$4)/100)+5)*XLOOKUP('Boss Editor'!$E$4,'Nature Editor'!$A:$A,'Nature Editor'!$D:$D,1))),def,IF(cat="Physical",FLOOR((FLOOR(((2*XLOOKUP($K6,'Pokemon Editor'!$A:$A,'Pokemon Editor'!$G:$G,0)+31+FLOOR($Q6/4))*$L6)/100)+5)*XLOOKUP($M6,'Nature Editor'!$A:$A,'Nature Editor'!$C:$C,1)),FLOOR((FLOOR(((2*XLOOKUP($K6,'Pokemon Editor'!$A:$A,'Pokemon Editor'!$I:$I,0)+31+FLOOR($S6/4))*$L6)/100)+5)*XLOOKUP($M6,'Nature Editor'!$A:$A,'Nature Editor'!$E:$E,1))),stab,IF(OR(mtype=XLOOKUP('Boss Editor'!$C$4,'Pokemon Editor'!$A:$A,'Pokemon Editor'!$C:$C,""),mtype=XLOOKUP('Boss Editor'!$C$4,'Pokemon Editor'!$A:$A,'Pokemon Editor'!$D:$D,"")),1.5,1),eff,(INDEX('Type Chart'!$B:$S,MATCH(mtype,'Type Chart'!$A:$A,0),MATCH(XLOOKUP($K6,'Pokemon Editor'!$A:$A,'Pokemon Editor'!$C:$C,""),'Type Chart'!$B$1:$S$1,0))*IF(XLOOKUP($K6,'Pokemon Editor'!$A:$A,'Pokemon Editor'!$D:$D,"")="",1,INDEX('Type Chart'!$B:$S,MATCH(mtype,'Type Chart'!$A:$A,0),MATCH(XLOOKUP($K6,'Pokemon Editor'!$A:$A,'Pokemon Editor'!$D:$D,""),'Type Chart'!$B$1:$S$1,0)))),base,IF(OR(cat="Status",pow=0),0,FLOOR(FLOOR(FLOOR((2*'Boss Editor'!$D$4/5+2)*pow*atk/def)/50)+2)),modifier,stab*eff,AVERAGE(ARRAYFORMULA(FLOOR(base*modifier*SEQUENCE(16,1,85,1)/100)))/(FLOOR(((2*XLOOKUP($K6,'Pokemon Editor'!$A:$A,'Pokemon Editor'!$E:$E,0)+31+FLOOR($O6/4))*$L6)/100)+$L6+10)),0) | F6: =FLOOR((FLOOR(((2*XLOOKUP($K6,'Pokemon Editor'!$A:$A,'Pokemon Editor'!$J:$J,0)+31+FLOOR($T6/4))*$L6)/100)+5)*XLOOKUP($M6,'Nature Editor'!$A:$A,'Nature Editor'!$F:$F,1)) | G6: =FLOOR((FLOOR(((2*XLOOKUP('Boss Editor'!$C$4,'Pokemon Editor'!$A:$A,'Pokemon Editor'!$J:$J,0)+31+FLOOR('Boss Editor'!$L$4/4))*'Boss Editor'!$D$4)/100)+5)*XLOOKUP('Boss Editor'!$E$4,'Nature Editor'!$A:$A,'Nature Editor'!$F:$F,1)) | H6: =IF(F6>G6,"Yes","No") | I6: =C6-E6 | J6: =IFS(AND(C6>=0.5,E6<0.5),"Dominant",AND(C6>=0.35,E6<0.75),"Strong",AND(C6>=0.25,E6<1),"Viable",AND(C6>=0.15,E6<1.25),"Risky",TRUE,"Poor") | K6: =REDUCE($Y6,SEQUENCE(2),LAMBDA(current_species,unused_step,IFERROR(INDEX(FILTER('Evolution Editor'!$D$2:$D,'Evolution Editor'!$A$2:$A=current_species,'Evolution Editor'!$F$2:$F=TRUE,'Evolution Editor'!$E$2:$E<=$L6),1),current_species))) | L6: 15 | M6: Neutral | N6: ABILITY_TORRENT | O6: 0 | P6: 0 | Q6: 0 | R6: 0 | S6: 0 | T6: 0 | U6: =IFERROR(LET(mtype,XLOOKUP($B6,'Move Editor'!$B:$B,'Move Editor'!$C:$C,""),cat,XLOOKUP($B6,'Move Editor'!$B:$B,'Move Editor'!$D:$D,""),pow,XLOOKUP($B6,'Move Editor'!$B:$B,'Move Editor'!$E:$E,0),acc,XLOOKUP($B6,'Move Editor'!$B:$B,'Move Editor'!$F:$F,100),atk,IF(cat="Physical",FLOOR((FLOOR(((2*XLOOKUP($K6,'Pokemon Editor'!$A:$A,'Pokemon Editor'!$F:$F,0)+31+FLOOR($P6/4))*$L6)/100)+5)*XLOOKUP($M6,'Nature Editor'!$A:$A,'Nature Editor'!$B:$B,1)),FLOOR((FLOOR(((2*XLOOKUP($K6,'Pokemon Editor'!$A:$A,'Pokemon Editor'!$H:$H,0)+31+FLOOR($R6/4))*$L6)/100)+5)*XLOOKUP($M6,'Nature Editor'!$A:$A,'Nature Editor'!$D:$D,1))),def,IF(cat="Physical",FLOOR((FLOOR(((2*XLOOKUP('Boss Editor'!$C$4,'Pokemon Editor'!$A:$A,'Pokemon Editor'!$G:$G,0)+31+FLOOR('Boss Editor'!$I$4/4))*'Boss Editor'!$D$4)/100)+5)*XLOOKUP('Boss Editor'!$E$4,'Nature Editor'!$A:$A,'Nature Editor'!$C:$C,1)),FLOOR((FLOOR(((2*XLOOKUP('Boss Editor'!$C$4,'Pokemon Editor'!$A:$A,'Pokemon Editor'!$I:$I,0)+31+FLOOR('Boss Editor'!$K$4/4))*'Boss Editor'!$D$4)/100)+5)*XLOOKUP('Boss Editor'!$E$4,'Nature Editor'!$A:$A,'Nature Editor'!$E:$E,1))),stab,IF(OR(mtype=XLOOKUP($K6,'Pokemon Editor'!$A:$A,'Pokemon Editor'!$C:$C,""),mtype=XLOOKUP($K6,'Pokemon Editor'!$A:$A,'Pokemon Editor'!$D:$D,"")),1.5,1),eff,(INDEX('Type Chart'!$B:$S,MATCH(mtype,'Type Chart'!$A:$A,0),MATCH(XLOOKUP('Boss Editor'!$C$4,'Pokemon Editor'!$A:$A,'Pokemon Editor'!$C:$C,""),'Type Chart'!$B$1:$S$1,0))*IF(XLOOKUP('Boss Editor'!$C$4,'Pokemon Editor'!$A:$A,'Pokemon Editor'!$D:$D,"")="",1,INDEX('Type Chart'!$B:$S,MATCH(mtype,'Type Chart'!$A:$A,0),MATCH(XLOOKUP('Boss Editor'!$C$4,'Pokemon Editor'!$A:$A,'Pokemon Editor'!$D:$D,""),'Type Chart'!$B$1:$S$1,0)))),base,IF(OR(cat="Status",pow=0),0,FLOOR(FLOOR(FLOOR((2*$L6/5+2)*pow*atk/def)/50)+2)),modifier,stab*eff,FLOOR(base*modifier*0.85)),0) | V6: =IFERROR(LET(mtype,XLOOKUP($B6,'Move Editor'!$B:$B,'Move Editor'!$C:$C,""),cat,XLOOKUP($B6,'Move Editor'!$B:$B,'Move Editor'!$D:$D,""),pow,XLOOKUP($B6,'Move Editor'!$B:$B,'Move Editor'!$E:$E,0),acc,XLOOKUP($B6,'Move Editor'!$B:$B,'Move Editor'!$F:$F,100),atk,IF(cat="Physical",FLOOR((FLOOR(((2*XLOOKUP($K6,'Pokemon Editor'!$A:$A,'Pokemon Editor'!$F:$F,0)+31+FLOOR($P6/4))*$L6)/100)+5)*XLOOKUP($M6,'Nature Editor'!$A:$A,'Nature Editor'!$B:$B,1)),FLOOR((FLOOR(((2*XLOOKUP($K6,'Pokemon Editor'!$A:$A,'Pokemon Editor'!$H:$H,0)+31+FLOOR($R6/4))*$L6)/100)+5)*XLOOKUP($M6,'Nature Editor'!$A:$A,'Nature Editor'!$D:$D,1))),def,IF(cat="Physical",FLOOR((FLOOR(((2*XLOOKUP('Boss Editor'!$C$4,'Pokemon Editor'!$A:$A,'Pokemon Editor'!$G:$G,0)+31+FLOOR('Boss Editor'!$I$4/4))*'Boss Editor'!$D$4)/100)+5)*XLOOKUP('Boss Editor'!$E$4,'Nature Editor'!$A:$A,'Nature Editor'!$C:$C,1)),FLOOR((FLOOR(((2*XLOOKUP('Boss Editor'!$C$4,'Pokemon Editor'!$A:$A,'Pokemon Editor'!$I:$I,0)+31+FLOOR('Boss Editor'!$K$4/4))*'Boss Editor'!$D$4)/100)+5)*XLOOKUP('Boss Editor'!$E$4,'Nature Editor'!$A:$A,'Nature Editor'!$E:$E,1))),stab,IF(OR(mtype=XLOOKUP($K6,'Pokemon Editor'!$A:$A,'Pokemon Editor'!$C:$C,""),mtype=XLOOKUP($K6,'Pokemon Editor'!$A:$A,'Pokemon Editor'!$D:$D,"")),1.5,1),eff,(INDEX('Type Chart'!$B:$S,MATCH(mtype,'Type Chart'!$A:$A,0),MATCH(XLOOKUP('Boss Editor'!$C$4,'Pokemon Editor'!$A:$A,'Pokemon Editor'!$C:$C,""),'Type Chart'!$B$1:$S$1,0))*IF(XLOOKUP('Boss Editor'!$C$4,'Pokemon Editor'!$A:$A,'Pokemon Editor'!$D:$D,"")="",1,INDEX('Type Chart'!$B:$S,MATCH(mtype,'Type Chart'!$A:$A,0),MATCH(XLOOKUP('Boss Editor'!$C$4,'Pokemon Editor'!$A:$A,'Pokemon Editor'!$D:$D,""),'Type Chart'!$B$1:$S$1,0)))),base,IF(OR(cat="Status",pow=0),0,FLOOR(FLOOR(FLOOR((2*$L6/5+2)*pow*atk/def)/50)+2)),modifier,stab*eff,FLOOR(base*modifier)),0) | W6: =IFERROR(LET(mtype,XLOOKUP($D6,'Move Editor'!$B:$B,'Move Editor'!$C:$C,""),cat,XLOOKUP($D6,'Move Editor'!$B:$B,'Move Editor'!$D:$D,""),pow,XLOOKUP($D6,'Move Editor'!$B:$B,'Move Editor'!$E:$E,0),acc,XLOOKUP($D6,'Move Editor'!$B:$B,'Move Editor'!$F:$F,100),atk,IF(cat="Physical",FLOOR((FLOOR(((2*XLOOKUP('Boss Editor'!$C$4,'Pokemon Editor'!$A:$A,'Pokemon Editor'!$F:$F,0)+31+FLOOR('Boss Editor'!$H$4/4))*'Boss Editor'!$D$4)/100)+5)*XLOOKUP('Boss Editor'!$E$4,'Nature Editor'!$A:$A,'Nature Editor'!$B:$B,1)),FLOOR((FLOOR(((2*XLOOKUP('Boss Editor'!$C$4,'Pokemon Editor'!$A:$A,'Pokemon Editor'!$H:$H,0)+31+FLOOR('Boss Editor'!$J$4/4))*'Boss Editor'!$D$4)/100)+5)*XLOOKUP('Boss Editor'!$E$4,'Nature Editor'!$A:$A,'Nature Editor'!$D:$D,1))),def,IF(cat="Physical",FLOOR((FLOOR(((2*XLOOKUP($K6,'Pokemon Editor'!$A:$A,'Pokemon Editor'!$G:$G,0)+31+FLOOR($Q6/4))*$L6)/100)+5)*XLOOKUP($M6,'Nature Editor'!$A:$A,'Nature Editor'!$C:$C,1)),FLOOR((FLOOR(((2*XLOOKUP($K6,'Pokemon Editor'!$A:$A,'Pokemon Editor'!$I:$I,0)+31+FLOOR($S6/4))*$L6)/100)+5)*XLOOKUP($M6,'Nature Editor'!$A:$A,'Nature Editor'!$E:$E,1))),stab,IF(OR(mtype=XLOOKUP('Boss Editor'!$C$4,'Pokemon Editor'!$A:$A,'Pokemon Editor'!$C:$C,""),mtype=XLOOKUP('Boss Editor'!$C$4,'Pokemon Editor'!$A:$A,'Pokemon Editor'!$D:$D,"")),1.5,1),eff,(INDEX('Type Chart'!$B:$S,MATCH(mtype,'Type Chart'!$A:$A,0),MATCH(XLOOKUP($K6,'Pokemon Editor'!$A:$A,'Pokemon Editor'!$C:$C,""),'Type Chart'!$B$1:$S$1,0))*IF(XLOOKUP($K6,'Pokemon Editor'!$A:$A,'Pokemon Editor'!$D:$D,"")="",1,INDEX('Type Chart'!$B:$S,MATCH(mtype,'Type Chart'!$A:$A,0),MATCH(XLOOKUP($K6,'Pokemon Editor'!$A:$A,'Pokemon Editor'!$D:$D,""),'Type Chart'!$B$1:$S$1,0)))),base,IF(OR(cat="Status",pow=0),0,FLOOR(FLOOR(FLOOR((2*'Boss Editor'!$D$4/5+2)*pow*atk/def)/50)+2)),modifier,stab*eff,FLOOR(base*modifier*0.85)),0) | X6: =IFERROR(LET(mtype,XLOOKUP($D6,'Move Editor'!$B:$B,'Move Editor'!$C:$C,""),cat,XLOOKUP($D6,'Move Editor'!$B:$B,'Move Editor'!$D:$D,""),pow,XLOOKUP($D6,'Move Editor'!$B:$B,'Move Editor'!$E:$E,0),acc,XLOOKUP($D6,'Move Editor'!$B:$B,'Move Editor'!$F:$F,100),atk,IF(cat="Physical",FLOOR((FLOOR(((2*XLOOKUP('Boss Editor'!$C$4,'Pokemon Editor'!$A:$A,'Pokemon Editor'!$F:$F,0)+31+FLOOR('Boss Editor'!$H$4/4))*'Boss Editor'!$D$4)/100)+5)*XLOOKUP('Boss Editor'!$E$4,'Nature Editor'!$A:$A,'Nature Editor'!$B:$B,1)),FLOOR((FLOOR(((2*XLOOKUP('Boss Editor'!$C$4,'Pokemon Editor'!$A:$A,'Pokemon Editor'!$H:$H,0)+31+FLOOR('Boss Editor'!$J$4/4))*'Boss Editor'!$D$4)/100)+5)*XLOOKUP('Boss Editor'!$E$4,'Nature Editor'!$A:$A,'Nature Editor'!$D:$D,1))),def,IF(cat="Physical",FLOOR((FLOOR(((2*XLOOKUP($K6,'Pokemon Editor'!$A:$A,'Pokemon Editor'!$G:$G,0)+31+FLOOR($Q6/4))*$L6)/100)+5)*XLOOKUP($M6,'Nature Editor'!$A:$A,'Nature Editor'!$C:$C,1)),FLOOR((FLOOR(((2*XLOOKUP($K6,'Pokemon Editor'!$A:$A,'Pokemon Editor'!$I:$I,0)+31+FLOOR($S6/4))*$L6)/100)+5)*XLOOKUP($M6,'Nature Editor'!$A:$A,'Nature Editor'!$E:$E,1))),stab,IF(OR(mtype=XLOOKUP('Boss Editor'!$C$4,'Pokemon Editor'!$A:$A,'Pokemon Editor'!$C:$C,""),mtype=XLOOKUP('Boss Editor'!$C$4,'Pokemon Editor'!$A:$A,'Pokemon Editor'!$D:$D,"")),1.5,1),eff,(INDEX('Type Chart'!$B:$S,MATCH(mtype,'Type Chart'!$A:$A,0),MATCH(XLOOKUP($K6,'Pokemon Editor'!$A:$A,'Pokemon Editor'!$C:$C,""),'Type Chart'!$B$1:$S$1,0))*IF(XLOOKUP($K6,'Pokemon Editor'!$A:$A,'Pokemon Editor'!$D:$D,"")="",1,INDEX('Type Chart'!$B:$S,MATCH(mtype,'Type Chart'!$A:$A,0),MATCH(XLOOKUP($K6,'Pokemon Editor'!$A:$A,'Pokemon Editor'!$D:$D,""),'Type Chart'!$B$1:$S$1,0)))),base,IF(OR(cat="Status",pow=0),0,FLOOR(FLOOR(FLOOR((2*'Boss Editor'!$D$4/5+2)*pow*atk/def)/50)+2)),modifier,stab*eff,FLOOR(base*modifier)),0) | Y6: SPECIES_MUDKIP
A7: =XLOOKUP(K7,'Pokemon Editor'!$A:$A,'Pokemon Editor'!$B:$B,K7) | B7: =IF($Z7<>"",$Z7,IFERROR(INDEX(FILTER('Move Comparison'!$D$2:$D,'Move Comparison'!$Q$2:$Q=$Y7,'Move Comparison'!$M$2:$M=MAXIFS('Move Comparison'!$M$2:$M,'Move Comparison'!$Q$2:$Q,$Y7),'Move Comparison'!$D$2:$D<>""),1),"")) | C7: =IFERROR(LET(mtype,XLOOKUP($B7,'Move Editor'!$B:$B,'Move Editor'!$C:$C,""),cat,XLOOKUP($B7,'Move Editor'!$B:$B,'Move Editor'!$D:$D,""),pow,XLOOKUP($B7,'Move Editor'!$B:$B,'Move Editor'!$E:$E,0),acc,XLOOKUP($B7,'Move Editor'!$B:$B,'Move Editor'!$F:$F,100),atk,IF(cat="Physical",FLOOR((FLOOR(((2*XLOOKUP($K7,'Pokemon Editor'!$A:$A,'Pokemon Editor'!$F:$F,0)+31+FLOOR($P7/4))*$L7)/100)+5)*XLOOKUP($M7,'Nature Editor'!$A:$A,'Nature Editor'!$B:$B,1)),FLOOR((FLOOR(((2*XLOOKUP($K7,'Pokemon Editor'!$A:$A,'Pokemon Editor'!$H:$H,0)+31+FLOOR($R7/4))*$L7)/100)+5)*XLOOKUP($M7,'Nature Editor'!$A:$A,'Nature Editor'!$D:$D,1))),def,IF(cat="Physical",FLOOR((FLOOR(((2*XLOOKUP('Boss Editor'!$C$4,'Pokemon Editor'!$A:$A,'Pokemon Editor'!$G:$G,0)+31+FLOOR('Boss Editor'!$I$4/4))*'Boss Editor'!$D$4)/100)+5)*XLOOKUP('Boss Editor'!$E$4,'Nature Editor'!$A:$A,'Nature Editor'!$C:$C,1)),FLOOR((FLOOR(((2*XLOOKUP('Boss Editor'!$C$4,'Pokemon Editor'!$A:$A,'Pokemon Editor'!$I:$I,0)+31+FLOOR('Boss Editor'!$K$4/4))*'Boss Editor'!$D$4)/100)+5)*XLOOKUP('Boss Editor'!$E$4,'Nature Editor'!$A:$A,'Nature Editor'!$E:$E,1))),stab,IF(OR(mtype=XLOOKUP($K7,'Pokemon Editor'!$A:$A,'Pokemon Editor'!$C:$C,""),mtype=XLOOKUP($K7,'Pokemon Editor'!$A:$A,'Pokemon Editor'!$D:$D,"")),1.5,1),eff,(INDEX('Type Chart'!$B:$S,MATCH(mtype,'Type Chart'!$A:$A,0),MATCH(XLOOKUP('Boss Editor'!$C$4,'Pokemon Editor'!$A:$A,'Pokemon Editor'!$C:$C,""),'Type Chart'!$B$1:$S$1,0))*IF(XLOOKUP('Boss Editor'!$C$4,'Pokemon Editor'!$A:$A,'Pokemon Editor'!$D:$D,"")="",1,INDEX('Type Chart'!$B:$S,MATCH(mtype,'Type Chart'!$A:$A,0),MATCH(XLOOKUP('Boss Editor'!$C$4,'Pokemon Editor'!$A:$A,'Pokemon Editor'!$D:$D,""),'Type Chart'!$B$1:$S$1,0)))),base,IF(OR(cat="Status",pow=0),0,FLOOR(FLOOR(FLOOR((2*$L7/5+2)*pow*atk/def)/50)+2)),modifier,stab*eff,AVERAGE(ARRAYFORMULA(FLOOR(base*modifier*SEQUENCE(16,1,85,1)/100)))/(FLOOR(((2*XLOOKUP('Boss Editor'!$C$4,'Pokemon Editor'!$A:$A,'Pokemon Editor'!$E:$E,0)+31+FLOOR('Boss Editor'!$G$4/4))*'Boss Editor'!$D$4)/100)+'Boss Editor'!$D$4+10)),0) | D7: Astonish | E7: =IFERROR(LET(mtype,XLOOKUP($D7,'Move Editor'!$B:$B,'Move Editor'!$C:$C,""),cat,XLOOKUP($D7,'Move Editor'!$B:$B,'Move Editor'!$D:$D,""),pow,XLOOKUP($D7,'Move Editor'!$B:$B,'Move Editor'!$E:$E,0),acc,XLOOKUP($D7,'Move Editor'!$B:$B,'Move Editor'!$F:$F,100),atk,IF(cat="Physical",FLOOR((FLOOR(((2*XLOOKUP('Boss Editor'!$C$4,'Pokemon Editor'!$A:$A,'Pokemon Editor'!$F:$F,0)+31+FLOOR('Boss Editor'!$H$4/4))*'Boss Editor'!$D$4)/100)+5)*XLOOKUP('Boss Editor'!$E$4,'Nature Editor'!$A:$A,'Nature Editor'!$B:$B,1)),FLOOR((FLOOR(((2*XLOOKUP('Boss Editor'!$C$4,'Pokemon Editor'!$A:$A,'Pokemon Editor'!$H:$H,0)+31+FLOOR('Boss Editor'!$J$4/4))*'Boss Editor'!$D$4)/100)+5)*XLOOKUP('Boss Editor'!$E$4,'Nature Editor'!$A:$A,'Nature Editor'!$D:$D,1))),def,IF(cat="Physical",FLOOR((FLOOR(((2*XLOOKUP($K7,'Pokemon Editor'!$A:$A,'Pokemon Editor'!$G:$G,0)+31+FLOOR($Q7/4))*$L7)/100)+5)*XLOOKUP($M7,'Nature Editor'!$A:$A,'Nature Editor'!$C:$C,1)),FLOOR((FLOOR(((2*XLOOKUP($K7,'Pokemon Editor'!$A:$A,'Pokemon Editor'!$I:$I,0)+31+FLOOR($S7/4))*$L7)/100)+5)*XLOOKUP($M7,'Nature Editor'!$A:$A,'Nature Editor'!$E:$E,1))),stab,IF(OR(mtype=XLOOKUP('Boss Editor'!$C$4,'Pokemon Editor'!$A:$A,'Pokemon Editor'!$C:$C,""),mtype=XLOOKUP('Boss Editor'!$C$4,'Pokemon Editor'!$A:$A,'Pokemon Editor'!$D:$D,"")),1.5,1),eff,(INDEX('Type Chart'!$B:$S,MATCH(mtype,'Type Chart'!$A:$A,0),MATCH(XLOOKUP($K7,'Pokemon Editor'!$A:$A,'Pokemon Editor'!$C:$C,""),'Type Chart'!$B$1:$S$1,0))*IF(XLOOKUP($K7,'Pokemon Editor'!$A:$A,'Pokemon Editor'!$D:$D,"")="",1,INDEX('Type Chart'!$B:$S,MATCH(mtype,'Type Chart'!$A:$A,0),MATCH(XLOOKUP($K7,'Pokemon Editor'!$A:$A,'Pokemon Editor'!$D:$D,""),'Type Chart'!$B$1:$S$1,0)))),base,IF(OR(cat="Status",pow=0),0,FLOOR(FLOOR(FLOOR((2*'Boss Editor'!$D$4/5+2)*pow*atk/def)/50)+2)),modifier,stab*eff,AVERAGE(ARRAYFORMULA(FLOOR(base*modifier*SEQUENCE(16,1,85,1)/100)))/(FLOOR(((2*XLOOKUP($K7,'Pokemon Editor'!$A:$A,'Pokemon Editor'!$E:$E,0)+31+FLOOR($O7/4))*$L7)/100)+$L7+10)),0) | F7: =FLOOR((FLOOR(((2*XLOOKUP($K7,'Pokemon Editor'!$A:$A,'Pokemon Editor'!$J:$J,0)+31+FLOOR($T7/4))*$L7)/100)+5)*XLOOKUP($M7,'Nature Editor'!$A:$A,'Nature Editor'!$F:$F,1)) | G7: =FLOOR((FLOOR(((2*XLOOKUP('Boss Editor'!$C$4,'Pokemon Editor'!$A:$A,'Pokemon Editor'!$J:$J,0)+31+FLOOR('Boss Editor'!$L$4/4))*'Boss Editor'!$D$4)/100)+5)*XLOOKUP('Boss Editor'!$E$4,'Nature Editor'!$A:$A,'Nature Editor'!$F:$F,1)) | H7: =IF(F7>G7,"Yes","No") | I7: =C7-E7 | J7: =IFS(AND(C7>=0.5,E7<0.5),"Dominant",AND(C7>=0.35,E7<0.75),"Strong",AND(C7>=0.25,E7<1),"Viable",AND(C7>=0.15,E7<1.25),"Risky",TRUE,"Poor") | K7: =REDUCE($Y7,SEQUENCE(2),LAMBDA(current_species,unused_step,IFERROR(INDEX(FILTER('Evolution Editor'!$D$2:$D,'Evolution Editor'!$A$2:$A=current_species,'Evolution Editor'!$F$2:$F=TRUE,'Evolution Editor'!$E$2:$E<=$L7),1),current_species))) | L7: 15 | M7: Neutral | N7: ABILITY_POISON_POINT | O7: 0 | P7: 0 | Q7: 0 | R7: 0 | S7: 0 | T7: 0 | U7: =IFERROR(LET(mtype,XLOOKUP($B7,'Move Editor'!$B:$B,'Move Editor'!$C:$C,""),cat,XLOOKUP($B7,'Move Editor'!$B:$B,'Move Editor'!$D:$D,""),pow,XLOOKUP($B7,'Move Editor'!$B:$B,'Move Editor'!$E:$E,0),acc,XLOOKUP($B7,'Move Editor'!$B:$B,'Move Editor'!$F:$F,100),atk,IF(cat="Physical",FLOOR((FLOOR(((2*XLOOKUP($K7,'Pokemon Editor'!$A:$A,'Pokemon Editor'!$F:$F,0)+31+FLOOR($P7/4))*$L7)/100)+5)*XLOOKUP($M7,'Nature Editor'!$A:$A,'Nature Editor'!$B:$B,1)),FLOOR((FLOOR(((2*XLOOKUP($K7,'Pokemon Editor'!$A:$A,'Pokemon Editor'!$H:$H,0)+31+FLOOR($R7/4))*$L7)/100)+5)*XLOOKUP($M7,'Nature Editor'!$A:$A,'Nature Editor'!$D:$D,1))),def,IF(cat="Physical",FLOOR((FLOOR(((2*XLOOKUP('Boss Editor'!$C$4,'Pokemon Editor'!$A:$A,'Pokemon Editor'!$G:$G,0)+31+FLOOR('Boss Editor'!$I$4/4))*'Boss Editor'!$D$4)/100)+5)*XLOOKUP('Boss Editor'!$E$4,'Nature Editor'!$A:$A,'Nature Editor'!$C:$C,1)),FLOOR((FLOOR(((2*XLOOKUP('Boss Editor'!$C$4,'Pokemon Editor'!$A:$A,'Pokemon Editor'!$I:$I,0)+31+FLOOR('Boss Editor'!$K$4/4))*'Boss Editor'!$D$4)/100)+5)*XLOOKUP('Boss Editor'!$E$4,'Nature Editor'!$A:$A,'Nature Editor'!$E:$E,1))),stab,IF(OR(mtype=XLOOKUP($K7,'Pokemon Editor'!$A:$A,'Pokemon Editor'!$C:$C,""),mtype=XLOOKUP($K7,'Pokemon Editor'!$A:$A,'Pokemon Editor'!$D:$D,"")),1.5,1),eff,(INDEX('Type Chart'!$B:$S,MATCH(mtype,'Type Chart'!$A:$A,0),MATCH(XLOOKUP('Boss Editor'!$C$4,'Pokemon Editor'!$A:$A,'Pokemon Editor'!$C:$C,""),'Type Chart'!$B$1:$S$1,0))*IF(XLOOKUP('Boss Editor'!$C$4,'Pokemon Editor'!$A:$A,'Pokemon Editor'!$D:$D,"")="",1,INDEX('Type Chart'!$B:$S,MATCH(mtype,'Type Chart'!$A:$A,0),MATCH(XLOOKUP('Boss Editor'!$C$4,'Pokemon Editor'!$A:$A,'Pokemon Editor'!$D:$D,""),'Type Chart'!$B$1:$S$1,0)))),base,IF(OR(cat="Status",pow=0),0,FLOOR(FLOOR(FLOOR((2*$L7/5+2)*pow*atk/def)/50)+2)),modifier,stab*eff,FLOOR(base*modifier*0.85)),0) | V7: =IFERROR(LET(mtype,XLOOKUP($B7,'Move Editor'!$B:$B,'Move Editor'!$C:$C,""),cat,XLOOKUP($B7,'Move Editor'!$B:$B,'Move Editor'!$D:$D,""),pow,XLOOKUP($B7,'Move Editor'!$B:$B,'Move Editor'!$E:$E,0),acc,XLOOKUP($B7,'Move Editor'!$B:$B,'Move Editor'!$F:$F,100),atk,IF(cat="Physical",FLOOR((FLOOR(((2*XLOOKUP($K7,'Pokemon Editor'!$A:$A,'Pokemon Editor'!$F:$F,0)+31+FLOOR($P7/4))*$L7)/100)+5)*XLOOKUP($M7,'Nature Editor'!$A:$A,'Nature Editor'!$B:$B,1)),FLOOR((FLOOR(((2*XLOOKUP($K7,'Pokemon Editor'!$A:$A,'Pokemon Editor'!$H:$H,0)+31+FLOOR($R7/4))*$L7)/100)+5)*XLOOKUP($M7,'Nature Editor'!$A:$A,'Nature Editor'!$D:$D,1))),def,IF(cat="Physical",FLOOR((FLOOR(((2*XLOOKUP('Boss Editor'!$C$4,'Pokemon Editor'!$A:$A,'Pokemon Editor'!$G:$G,0)+31+FLOOR('Boss Editor'!$I$4/4))*'Boss Editor'!$D$4)/100)+5)*XLOOKUP('Boss Editor'!$E$4,'Nature Editor'!$A:$A,'Nature Editor'!$C:$C,1)),FLOOR((FLOOR(((2*XLOOKUP('Boss Editor'!$C$4,'Pokemon Editor'!$A:$A,'Pokemon Editor'!$I:$I,0)+31+FLOOR('Boss Editor'!$K$4/4))*'Boss Editor'!$D$4)/100)+5)*XLOOKUP('Boss Editor'!$E$4,'Nature Editor'!$A:$A,'Nature Editor'!$E:$E,1))),stab,IF(OR(mtype=XLOOKUP($K7,'Pokemon Editor'!$A:$A,'Pokemon Editor'!$C:$C,""),mtype=XLOOKUP($K7,'Pokemon Editor'!$A:$A,'Pokemon Editor'!$D:$D,"")),1.5,1),eff,(INDEX('Type Chart'!$B:$S,MATCH(mtype,'Type Chart'!$A:$A,0),MATCH(XLOOKUP('Boss Editor'!$C$4,'Pokemon Editor'!$A:$A,'Pokemon Editor'!$C:$C,""),'Type Chart'!$B$1:$S$1,0))*IF(XLOOKUP('Boss Editor'!$C$4,'Pokemon Editor'!$A:$A,'Pokemon Editor'!$D:$D,"")="",1,INDEX('Type Chart'!$B:$S,MATCH(mtype,'Type Chart'!$A:$A,0),MATCH(XLOOKUP('Boss Editor'!$C$4,'Pokemon Editor'!$A:$A,'Pokemon Editor'!$D:$D,""),'Type Chart'!$B$1:$S$1,0)))),base,IF(OR(cat="Status",pow=0),0,FLOOR(FLOOR(FLOOR((2*$L7/5+2)*pow*atk/def)/50)+2)),modifier,stab*eff,FLOOR(base*modifier)),0) | W7: =IFERROR(LET(mtype,XLOOKUP($D7,'Move Editor'!$B:$B,'Move Editor'!$C:$C,""),cat,XLOOKUP($D7,'Move Editor'!$B:$B,'Move Editor'!$D:$D,""),pow,XLOOKUP($D7,'Move Editor'!$B:$B,'Move Editor'!$E:$E,0),acc,XLOOKUP($D7,'Move Editor'!$B:$B,'Move Editor'!$F:$F,100),atk,IF(cat="Physical",FLOOR((FLOOR(((2*XLOOKUP('Boss Editor'!$C$4,'Pokemon Editor'!$A:$A,'Pokemon Editor'!$F:$F,0)+31+FLOOR('Boss Editor'!$H$4/4))*'Boss Editor'!$D$4)/100)+5)*XLOOKUP('Boss Editor'!$E$4,'Nature Editor'!$A:$A,'Nature Editor'!$B:$B,1)),FLOOR((FLOOR(((2*XLOOKUP('Boss Editor'!$C$4,'Pokemon Editor'!$A:$A,'Pokemon Editor'!$H:$H,0)+31+FLOOR('Boss Editor'!$J$4/4))*'Boss Editor'!$D$4)/100)+5)*XLOOKUP('Boss Editor'!$E$4,'Nature Editor'!$A:$A,'Nature Editor'!$D:$D,1))),def,IF(cat="Physical",FLOOR((FLOOR(((2*XLOOKUP($K7,'Pokemon Editor'!$A:$A,'Pokemon Editor'!$G:$G,0)+31+FLOOR($Q7/4))*$L7)/100)+5)*XLOOKUP($M7,'Nature Editor'!$A:$A,'Nature Editor'!$C:$C,1)),FLOOR((FLOOR(((2*XLOOKUP($K7,'Pokemon Editor'!$A:$A,'Pokemon Editor'!$I:$I,0)+31+FLOOR($S7/4))*$L7)/100)+5)*XLOOKUP($M7,'Nature Editor'!$A:$A,'Nature Editor'!$E:$E,1))),stab,IF(OR(mtype=XLOOKUP('Boss Editor'!$C$4,'Pokemon Editor'!$A:$A,'Pokemon Editor'!$C:$C,""),mtype=XLOOKUP('Boss Editor'!$C$4,'Pokemon Editor'!$A:$A,'Pokemon Editor'!$D:$D,"")),1.5,1),eff,(INDEX('Type Chart'!$B:$S,MATCH(mtype,'Type Chart'!$A:$A,0),MATCH(XLOOKUP($K7,'Pokemon Editor'!$A:$A,'Pokemon Editor'!$C:$C,""),'Type Chart'!$B$1:$S$1,0))*IF(XLOOKUP($K7,'Pokemon Editor'!$A:$A,'Pokemon Editor'!$D:$D,"")="",1,INDEX('Type Chart'!$B:$S,MATCH(mtype,'Type Chart'!$A:$A,0),MATCH(XLOOKUP($K7,'Pokemon Editor'!$A:$A,'Pokemon Editor'!$D:$D,""),'Type Chart'!$B$1:$S$1,0)))),base,IF(OR(cat="Status",pow=0),0,FLOOR(FLOOR(FLOOR((2*'Boss Editor'!$D$4/5+2)*pow*atk/def)/50)+2)),modifier,stab*eff,FLOOR(base*modifier*0.85)),0) | X7: =IFERROR(LET(mtype,XLOOKUP($D7,'Move Editor'!$B:$B,'Move Editor'!$C:$C,""),cat,XLOOKUP($D7,'Move Editor'!$B:$B,'Move Editor'!$D:$D,""),pow,XLOOKUP($D7,'Move Editor'!$B:$B,'Move Editor'!$E:$E,0),acc,XLOOKUP($D7,'Move Editor'!$B:$B,'Move Editor'!$F:$F,100),atk,IF(cat="Physical",FLOOR((FLOOR(((2*XLOOKUP('Boss Editor'!$C$4,'Pokemon Editor'!$A:$A,'Pokemon Editor'!$F:$F,0)+31+FLOOR('Boss Editor'!$H$4/4))*'Boss Editor'!$D$4)/100)+5)*XLOOKUP('Boss Editor'!$E$4,'Nature Editor'!$A:$A,'Nature Editor'!$B:$B,1)),FLOOR((FLOOR(((2*XLOOKUP('Boss Editor'!$C$4,'Pokemon Editor'!$A:$A,'Pokemon Editor'!$H:$H,0)+31+FLOOR('Boss Editor'!$J$4/4))*'Boss Editor'!$D$4)/100)+5)*XLOOKUP('Boss Editor'!$E$4,'Nature Editor'!$A:$A,'Nature Editor'!$D:$D,1))),def,IF(cat="Physical",FLOOR((FLOOR(((2*XLOOKUP($K7,'Pokemon Editor'!$A:$A,'Pokemon Editor'!$G:$G,0)+31+FLOOR($Q7/4))*$L7)/100)+5)*XLOOKUP($M7,'Nature Editor'!$A:$A,'Nature Editor'!$C:$C,1)),FLOOR((FLOOR(((2*XLOOKUP($K7,'Pokemon Editor'!$A:$A,'Pokemon Editor'!$I:$I,0)+31+FLOOR($S7/4))*$L7)/100)+5)*XLOOKUP($M7,'Nature Editor'!$A:$A,'Nature Editor'!$E:$E,1))),stab,IF(OR(mtype=XLOOKUP('Boss Editor'!$C$4,'Pokemon Editor'!$A:$A,'Pokemon Editor'!$C:$C,""),mtype=XLOOKUP('Boss Editor'!$C$4,'Pokemon Editor'!$A:$A,'Pokemon Editor'!$D:$D,"")),1.5,1),eff,(INDEX('Type Chart'!$B:$S,MATCH(mtype,'Type Chart'!$A:$A,0),MATCH(XLOOKUP($K7,'Pokemon Editor'!$A:$A,'Pokemon Editor'!$C:$C,""),'Type Chart'!$B$1:$S$1,0))*IF(XLOOKUP($K7,'Pokemon Editor'!$A:$A,'Pokemon Editor'!$D:$D,"")="",1,INDEX('Type Chart'!$B:$S,MATCH(mtype,'Type Chart'!$A:$A,0),MATCH(XLOOKUP($K7,'Pokemon Editor'!$A:$A,'Pokemon Editor'!$D:$D,""),'Type Chart'!$B$1:$S$1,0)))),base,IF(OR(cat="Status",pow=0),0,FLOOR(FLOOR(FLOOR((2*'Boss Editor'!$D$4/5+2)*pow*atk/def)/50)+2)),modifier,stab*eff,FLOOR(base*modifier)),0) | Y7: SPECIES_VENIPEDE
A8: =XLOOKUP(K8,'Pokemon Editor'!$A:$A,'Pokemon Editor'!$B:$B,K8) | B8: =IF($Z8<>"",$Z8,IFERROR(INDEX(FILTER('Move Comparison'!$D$2:$D,'Move Comparison'!$Q$2:$Q=$Y8,'Move Comparison'!$M$2:$M=MAXIFS('Move Comparison'!$M$2:$M,'Move Comparison'!$Q$2:$Q,$Y8),'Move Comparison'!$D$2:$D<>""),1),"")) | C8: =IFERROR(LET(mtype,XLOOKUP($B8,'Move Editor'!$B:$B,'Move Editor'!$C:$C,""),cat,XLOOKUP($B8,'Move Editor'!$B:$B,'Move Editor'!$D:$D,""),pow,XLOOKUP($B8,'Move Editor'!$B:$B,'Move Editor'!$E:$E,0),acc,XLOOKUP($B8,'Move Editor'!$B:$B,'Move Editor'!$F:$F,100),atk,IF(cat="Physical",FLOOR((FLOOR(((2*XLOOKUP($K8,'Pokemon Editor'!$A:$A,'Pokemon Editor'!$F:$F,0)+31+FLOOR($P8/4))*$L8)/100)+5)*XLOOKUP($M8,'Nature Editor'!$A:$A,'Nature Editor'!$B:$B,1)),FLOOR((FLOOR(((2*XLOOKUP($K8,'Pokemon Editor'!$A:$A,'Pokemon Editor'!$H:$H,0)+31+FLOOR($R8/4))*$L8)/100)+5)*XLOOKUP($M8,'Nature Editor'!$A:$A,'Nature Editor'!$D:$D,1))),def,IF(cat="Physical",FLOOR((FLOOR(((2*XLOOKUP('Boss Editor'!$C$4,'Pokemon Editor'!$A:$A,'Pokemon Editor'!$G:$G,0)+31+FLOOR('Boss Editor'!$I$4/4))*'Boss Editor'!$D$4)/100)+5)*XLOOKUP('Boss Editor'!$E$4,'Nature Editor'!$A:$A,'Nature Editor'!$C:$C,1)),FLOOR((FLOOR(((2*XLOOKUP('Boss Editor'!$C$4,'Pokemon Editor'!$A:$A,'Pokemon Editor'!$I:$I,0)+31+FLOOR('Boss Editor'!$K$4/4))*'Boss Editor'!$D$4)/100)+5)*XLOOKUP('Boss Editor'!$E$4,'Nature Editor'!$A:$A,'Nature Editor'!$E:$E,1))),stab,IF(OR(mtype=XLOOKUP($K8,'Pokemon Editor'!$A:$A,'Pokemon Editor'!$C:$C,""),mtype=XLOOKUP($K8,'Pokemon Editor'!$A:$A,'Pokemon Editor'!$D:$D,"")),1.5,1),eff,(INDEX('Type Chart'!$B:$S,MATCH(mtype,'Type Chart'!$A:$A,0),MATCH(XLOOKUP('Boss Editor'!$C$4,'Pokemon Editor'!$A:$A,'Pokemon Editor'!$C:$C,""),'Type Chart'!$B$1:$S$1,0))*IF(XLOOKUP('Boss Editor'!$C$4,'Pokemon Editor'!$A:$A,'Pokemon Editor'!$D:$D,"")="",1,INDEX('Type Chart'!$B:$S,MATCH(mtype,'Type Chart'!$A:$A,0),MATCH(XLOOKUP('Boss Editor'!$C$4,'Pokemon Editor'!$A:$A,'Pokemon Editor'!$D:$D,""),'Type Chart'!$B$1:$S$1,0)))),base,IF(OR(cat="Status",pow=0),0,FLOOR(FLOOR(FLOOR((2*$L8/5+2)*pow*atk/def)/50)+2)),modifier,stab*eff,AVERAGE(ARRAYFORMULA(FLOOR(base*modifier*SEQUENCE(16,1,85,1)/100)))/(FLOOR(((2*XLOOKUP('Boss Editor'!$C$4,'Pokemon Editor'!$A:$A,'Pokemon Editor'!$E:$E,0)+31+FLOOR('Boss Editor'!$G$4/4))*'Boss Editor'!$D$4)/100)+'Boss Editor'!$D$4+10)),0) | D8: Acid | E8: =IFERROR(LET(mtype,XLOOKUP($D8,'Move Editor'!$B:$B,'Move Editor'!$C:$C,""),cat,XLOOKUP($D8,'Move Editor'!$B:$B,'Move Editor'!$D:$D,""),pow,XLOOKUP($D8,'Move Editor'!$B:$B,'Move Editor'!$E:$E,0),acc,XLOOKUP($D8,'Move Editor'!$B:$B,'Move Editor'!$F:$F,100),atk,IF(cat="Physical",FLOOR((FLOOR(((2*XLOOKUP('Boss Editor'!$C$4,'Pokemon Editor'!$A:$A,'Pokemon Editor'!$F:$F,0)+31+FLOOR('Boss Editor'!$H$4/4))*'Boss Editor'!$D$4)/100)+5)*XLOOKUP('Boss Editor'!$E$4,'Nature Editor'!$A:$A,'Nature Editor'!$B:$B,1)),FLOOR((FLOOR(((2*XLOOKUP('Boss Editor'!$C$4,'Pokemon Editor'!$A:$A,'Pokemon Editor'!$H:$H,0)+31+FLOOR('Boss Editor'!$J$4/4))*'Boss Editor'!$D$4)/100)+5)*XLOOKUP('Boss Editor'!$E$4,'Nature Editor'!$A:$A,'Nature Editor'!$D:$D,1))),def,IF(cat="Physical",FLOOR((FLOOR(((2*XLOOKUP($K8,'Pokemon Editor'!$A:$A,'Pokemon Editor'!$G:$G,0)+31+FLOOR($Q8/4))*$L8)/100)+5)*XLOOKUP($M8,'Nature Editor'!$A:$A,'Nature Editor'!$C:$C,1)),FLOOR((FLOOR(((2*XLOOKUP($K8,'Pokemon Editor'!$A:$A,'Pokemon Editor'!$I:$I,0)+31+FLOOR($S8/4))*$L8)/100)+5)*XLOOKUP($M8,'Nature Editor'!$A:$A,'Nature Editor'!$E:$E,1))),stab,IF(OR(mtype=XLOOKUP('Boss Editor'!$C$4,'Pokemon Editor'!$A:$A,'Pokemon Editor'!$C:$C,""),mtype=XLOOKUP('Boss Editor'!$C$4,'Pokemon Editor'!$A:$A,'Pokemon Editor'!$D:$D,"")),1.5,1),eff,(INDEX('Type Chart'!$B:$S,MATCH(mtype,'Type Chart'!$A:$A,0),MATCH(XLOOKUP($K8,'Pokemon Editor'!$A:$A,'Pokemon Editor'!$C:$C,""),'Type Chart'!$B$1:$S$1,0))*IF(XLOOKUP($K8,'Pokemon Editor'!$A:$A,'Pokemon Editor'!$D:$D,"")="",1,INDEX('Type Chart'!$B:$S,MATCH(mtype,'Type Chart'!$A:$A,0),MATCH(XLOOKUP($K8,'Pokemon Editor'!$A:$A,'Pokemon Editor'!$D:$D,""),'Type Chart'!$B$1:$S$1,0)))),base,IF(OR(cat="Status",pow=0),0,FLOOR(FLOOR(FLOOR((2*'Boss Editor'!$D$4/5+2)*pow*atk/def)/50)+2)),modifier,stab*eff,AVERAGE(ARRAYFORMULA(FLOOR(base*modifier*SEQUENCE(16,1,85,1)/100)))/(FLOOR(((2*XLOOKUP($K8,'Pokemon Editor'!$A:$A,'Pokemon Editor'!$E:$E,0)+31+FLOOR($O8/4))*$L8)/100)+$L8+10)),0) | F8: =FLOOR((FLOOR(((2*XLOOKUP($K8,'Pokemon Editor'!$A:$A,'Pokemon Editor'!$J:$J,0)+31+FLOOR($T8/4))*$L8)/100)+5)*XLOOKUP($M8,'Nature Editor'!$A:$A,'Nature Editor'!$F:$F,1)) | G8: =FLOOR((FLOOR(((2*XLOOKUP('Boss Editor'!$C$4,'Pokemon Editor'!$A:$A,'Pokemon Editor'!$J:$J,0)+31+FLOOR('Boss Editor'!$L$4/4))*'Boss Editor'!$D$4)/100)+5)*XLOOKUP('Boss Editor'!$E$4,'Nature Editor'!$A:$A,'Nature Editor'!$F:$F,1)) | H8: =IF(F8>G8,"Yes","No") | I8: =C8-E8 | J8: =IFS(AND(C8>=0.5,E8<0.5),"Dominant",AND(C8>=0.35,E8<0.75),"Strong",AND(C8>=0.25,E8<1),"Viable",AND(C8>=0.15,E8<1.25),"Risky",TRUE,"Poor") | K8: =REDUCE($Y8,SEQUENCE(2),LAMBDA(current_species,unused_step,IFERROR(INDEX(FILTER('Evolution Editor'!$D$2:$D,'Evolution Editor'!$A$2:$A=current_species,'Evolution Editor'!$F$2:$F=TRUE,'Evolution Editor'!$E$2:$E<=$L8),1),current_species))) | L8: 15 | M8: Neutral | N8: ABILITY_SWARM | O8: 0 | P8: 0 | Q8: 0 | R8: 0 | S8: 0 | T8: 0 | U8: =IFERROR(LET(mtype,XLOOKUP($B8,'Move Editor'!$B:$B,'Move Editor'!$C:$C,""),cat,XLOOKUP($B8,'Move Editor'!$B:$B,'Move Editor'!$D:$D,""),pow,XLOOKUP($B8,'Move Editor'!$B:$B,'Move Editor'!$E:$E,0),acc,XLOOKUP($B8,'Move Editor'!$B:$B,'Move Editor'!$F:$F,100),atk,IF(cat="Physical",FLOOR((FLOOR(((2*XLOOKUP($K8,'Pokemon Editor'!$A:$A,'Pokemon Editor'!$F:$F,0)+31+FLOOR($P8/4))*$L8)/100)+5)*XLOOKUP($M8,'Nature Editor'!$A:$A,'Nature Editor'!$B:$B,1)),FLOOR((FLOOR(((2*XLOOKUP($K8,'Pokemon Editor'!$A:$A,'Pokemon Editor'!$H:$H,0)+31+FLOOR($R8/4))*$L8)/100)+5)*XLOOKUP($M8,'Nature Editor'!$A:$A,'Nature Editor'!$D:$D,1))),def,IF(cat="Physical",FLOOR((FLOOR(((2*XLOOKUP('Boss Editor'!$C$4,'Pokemon Editor'!$A:$A,'Pokemon Editor'!$G:$G,0)+31+FLOOR('Boss Editor'!$I$4/4))*'Boss Editor'!$D$4)/100)+5)*XLOOKUP('Boss Editor'!$E$4,'Nature Editor'!$A:$A,'Nature Editor'!$C:$C,1)),FLOOR((FLOOR(((2*XLOOKUP('Boss Editor'!$C$4,'Pokemon Editor'!$A:$A,'Pokemon Editor'!$I:$I,0)+31+FLOOR('Boss Editor'!$K$4/4))*'Boss Editor'!$D$4)/100)+5)*XLOOKUP('Boss Editor'!$E$4,'Nature Editor'!$A:$A,'Nature Editor'!$E:$E,1))),stab,IF(OR(mtype=XLOOKUP($K8,'Pokemon Editor'!$A:$A,'Pokemon Editor'!$C:$C,""),mtype=XLOOKUP($K8,'Pokemon Editor'!$A:$A,'Pokemon Editor'!$D:$D,"")),1.5,1),eff,(INDEX('Type Chart'!$B:$S,MATCH(mtype,'Type Chart'!$A:$A,0),MATCH(XLOOKUP('Boss Editor'!$C$4,'Pokemon Editor'!$A:$A,'Pokemon Editor'!$C:$C,""),'Type Chart'!$B$1:$S$1,0))*IF(XLOOKUP('Boss Editor'!$C$4,'Pokemon Editor'!$A:$A,'Pokemon Editor'!$D:$D,"")="",1,INDEX('Type Chart'!$B:$S,MATCH(mtype,'Type Chart'!$A:$A,0),MATCH(XLOOKUP('Boss Editor'!$C$4,'Pokemon Editor'!$A:$A,'Pokemon Editor'!$D:$D,""),'Type Chart'!$B$1:$S$1,0)))),base,IF(OR(cat="Status",pow=0),0,FLOOR(FLOOR(FLOOR((2*$L8/5+2)*pow*atk/def)/50)+2)),modifier,stab*eff,FLOOR(base*modifier*0.85)),0) | V8: =IFERROR(LET(mtype,XLOOKUP($B8,'Move Editor'!$B:$B,'Move Editor'!$C:$C,""),cat,XLOOKUP($B8,'Move Editor'!$B:$B,'Move Editor'!$D:$D,""),pow,XLOOKUP($B8,'Move Editor'!$B:$B,'Move Editor'!$E:$E,0),acc,XLOOKUP($B8,'Move Editor'!$B:$B,'Move Editor'!$F:$F,100),atk,IF(cat="Physical",FLOOR((FLOOR(((2*XLOOKUP($K8,'Pokemon Editor'!$A:$A,'Pokemon Editor'!$F:$F,0)+31+FLOOR($P8/4))*$L8)/100)+5)*XLOOKUP($M8,'Nature Editor'!$A:$A,'Nature Editor'!$B:$B,1)),FLOOR((FLOOR(((2*XLOOKUP($K8,'Pokemon Editor'!$A:$A,'Pokemon Editor'!$H:$H,0)+31+FLOOR($R8/4))*$L8)/100)+5)*XLOOKUP($M8,'Nature Editor'!$A:$A,'Nature Editor'!$D:$D,1))),def,IF(cat="Physical",FLOOR((FLOOR(((2*XLOOKUP('Boss Editor'!$C$4,'Pokemon Editor'!$A:$A,'Pokemon Editor'!$G:$G,0)+31+FLOOR('Boss Editor'!$I$4/4))*'Boss Editor'!$D$4)/100)+5)*XLOOKUP('Boss Editor'!$E$4,'Nature Editor'!$A:$A,'Nature Editor'!$C:$C,1)),FLOOR((FLOOR(((2*XLOOKUP('Boss Editor'!$C$4,'Pokemon Editor'!$A:$A,'Pokemon Editor'!$I:$I,0)+31+FLOOR('Boss Editor'!$K$4/4))*'Boss Editor'!$D$4)/100)+5)*XLOOKUP('Boss Editor'!$E$4,'Nature Editor'!$A:$A,'Nature Editor'!$E:$E,1))),stab,IF(OR(mtype=XLOOKUP($K8,'Pokemon Editor'!$A:$A,'Pokemon Editor'!$C:$C,""),mtype=XLOOKUP($K8,'Pokemon Editor'!$A:$A,'Pokemon Editor'!$D:$D,"")),1.5,1),eff,(INDEX('Type Chart'!$B:$S,MATCH(mtype,'Type Chart'!$A:$A,0),MATCH(XLOOKUP('Boss Editor'!$C$4,'Pokemon Editor'!$A:$A,'Pokemon Editor'!$C:$C,""),'Type Chart'!$B$1:$S$1,0))*IF(XLOOKUP('Boss Editor'!$C$4,'Pokemon Editor'!$A:$A,'Pokemon Editor'!$D:$D,"")="",1,INDEX('Type Chart'!$B:$S,MATCH(mtype,'Type Chart'!$A:$A,0),MATCH(XLOOKUP('Boss Editor'!$C$4,'Pokemon Editor'!$A:$A,'Pokemon Editor'!$D:$D,""),'Type Chart'!$B$1:$S$1,0)))),base,IF(OR(cat="Status",pow=0),0,FLOOR(FLOOR(FLOOR((2*$L8/5+2)*pow*atk/def)/50)+2)),modifier,stab*eff,FLOOR(base*modifier)),0) | W8: =IFERROR(LET(mtype,XLOOKUP($D8,'Move Editor'!$B:$B,'Move Editor'!$C:$C,""),cat,XLOOKUP($D8,'Move Editor'!$B:$B,'Move Editor'!$D:$D,""),pow,XLOOKUP($D8,'Move Editor'!$B:$B,'Move Editor'!$E:$E,0),acc,XLOOKUP($D8,'Move Editor'!$B:$B,'Move Editor'!$F:$F,100),atk,IF(cat="Physical",FLOOR((FLOOR(((2*XLOOKUP('Boss Editor'!$C$4,'Pokemon Editor'!$A:$A,'Pokemon Editor'!$F:$F,0)+31+FLOOR('Boss Editor'!$H$4/4))*'Boss Editor'!$D$4)/100)+5)*XLOOKUP('Boss Editor'!$E$4,'Nature Editor'!$A:$A,'Nature Editor'!$B:$B,1)),FLOOR((FLOOR(((2*XLOOKUP('Boss Editor'!$C$4,'Pokemon Editor'!$A:$A,'Pokemon Editor'!$H:$H,0)+31+FLOOR('Boss Editor'!$J$4/4))*'Boss Editor'!$D$4)/100)+5)*XLOOKUP('Boss Editor'!$E$4,'Nature Editor'!$A:$A,'Nature Editor'!$D:$D,1))),def,IF(cat="Physical",FLOOR((FLOOR(((2*XLOOKUP($K8,'Pokemon Editor'!$A:$A,'Pokemon Editor'!$G:$G,0)+31+FLOOR($Q8/4))*$L8)/100)+5)*XLOOKUP($M8,'Nature Editor'!$A:$A,'Nature Editor'!$C:$C,1)),FLOOR((FLOOR(((2*XLOOKUP($K8,'Pokemon Editor'!$A:$A,'Pokemon Editor'!$I:$I,0)+31+FLOOR($S8/4))*$L8)/100)+5)*XLOOKUP($M8,'Nature Editor'!$A:$A,'Nature Editor'!$E:$E,1))),stab,IF(OR(mtype=XLOOKUP('Boss Editor'!$C$4,'Pokemon Editor'!$A:$A,'Pokemon Editor'!$C:$C,""),mtype=XLOOKUP('Boss Editor'!$C$4,'Pokemon Editor'!$A:$A,'Pokemon Editor'!$D:$D,"")),1.5,1),eff,(INDEX('Type Chart'!$B:$S,MATCH(mtype,'Type Chart'!$A:$A,0),MATCH(XLOOKUP($K8,'Pokemon Editor'!$A:$A,'Pokemon Editor'!$C:$C,""),'Type Chart'!$B$1:$S$1,0))*IF(XLOOKUP($K8,'Pokemon Editor'!$A:$A,'Pokemon Editor'!$D:$D,"")="",1,INDEX('Type Chart'!$B:$S,MATCH(mtype,'Type Chart'!$A:$A,0),MATCH(XLOOKUP($K8,'Pokemon Editor'!$A:$A,'Pokemon Editor'!$D:$D,""),'Type Chart'!$B$1:$S$1,0)))),base,IF(OR(cat="Status",pow=0),0,FLOOR(FLOOR(FLOOR((2*'Boss Editor'!$D$4/5+2)*pow*atk/def)/50)+2)),modifier,stab*eff,FLOOR(base*modifier*0.85)),0) | X8: =IFERROR(LET(mtype,XLOOKUP($D8,'Move Editor'!$B:$B,'Move Editor'!$C:$C,""),cat,XLOOKUP($D8,'Move Editor'!$B:$B,'Move Editor'!$D:$D,""),pow,XLOOKUP($D8,'Move Editor'!$B:$B,'Move Editor'!$E:$E,0),acc,XLOOKUP($D8,'Move Editor'!$B:$B,'Move Editor'!$F:$F,100),atk,IF(cat="Physical",FLOOR((FLOOR(((2*XLOOKUP('Boss Editor'!$C$4,'Pokemon Editor'!$A:$A,'Pokemon Editor'!$F:$F,0)+31+FLOOR('Boss Editor'!$H$4/4))*'Boss Editor'!$D$4)/100)+5)*XLOOKUP('Boss Editor'!$E$4,'Nature Editor'!$A:$A,'Nature Editor'!$B:$B,1)),FLOOR((FLOOR(((2*XLOOKUP('Boss Editor'!$C$4,'Pokemon Editor'!$A:$A,'Pokemon Editor'!$H:$H,0)+31+FLOOR('Boss Editor'!$J$4/4))*'Boss Editor'!$D$4)/100)+5)*XLOOKUP('Boss Editor'!$E$4,'Nature Editor'!$A:$A,'Nature Editor'!$D:$D,1))),def,IF(cat="Physical",FLOOR((FLOOR(((2*XLOOKUP($K8,'Pokemon Editor'!$A:$A,'Pokemon Editor'!$G:$G,0)+31+FLOOR($Q8/4))*$L8)/100)+5)*XLOOKUP($M8,'Nature Editor'!$A:$A,'Nature Editor'!$C:$C,1)),FLOOR((FLOOR(((2*XLOOKUP($K8,'Pokemon Editor'!$A:$A,'Pokemon Editor'!$I:$I,0)+31+FLOOR($S8/4))*$L8)/100)+5)*XLOOKUP($M8,'Nature Editor'!$A:$A,'Nature Editor'!$E:$E,1))),stab,IF(OR(mtype=XLOOKUP('Boss Editor'!$C$4,'Pokemon Editor'!$A:$A,'Pokemon Editor'!$C:$C,""),mtype=XLOOKUP('Boss Editor'!$C$4,'Pokemon Editor'!$A:$A,'Pokemon Editor'!$D:$D,"")),1.5,1),eff,(INDEX('Type Chart'!$B:$S,MATCH(mtype,'Type Chart'!$A:$A,0),MATCH(XLOOKUP($K8,'Pokemon Editor'!$A:$A,'Pokemon Editor'!$C:$C,""),'Type Chart'!$B$1:$S$1,0))*IF(XLOOKUP($K8,'Pokemon Editor'!$A:$A,'Pokemon Editor'!$D:$D,"")="",1,INDEX('Type Chart'!$B:$S,MATCH(mtype,'Type Chart'!$A:$A,0),MATCH(XLOOKUP($K8,'Pokemon Editor'!$A:$A,'Pokemon Editor'!$D:$D,""),'Type Chart'!$B$1:$S$1,0)))),base,IF(OR(cat="Status",pow=0),0,FLOOR(FLOOR(FLOOR((2*'Boss Editor'!$D$4/5+2)*pow*atk/def)/50)+2)),modifier,stab*eff,FLOOR(base*modifier)),0) | Y8: SPECIES_BLIPBUG
A9: =XLOOKUP(K9,'Pokemon Editor'!$A:$A,'Pokemon Editor'!$B:$B,K9) | B9: =IF($Z9<>"",$Z9,IFERROR(INDEX(FILTER('Move Comparison'!$D$2:$D,'Move Comparison'!$Q$2:$Q=$Y9,'Move Comparison'!$M$2:$M=MAXIFS('Move Comparison'!$M$2:$M,'Move Comparison'!$Q$2:$Q,$Y9),'Move Comparison'!$D$2:$D<>""),1),"")) | C9: =IFERROR(LET(mtype,XLOOKUP($B9,'Move Editor'!$B:$B,'Move Editor'!$C:$C,""),cat,XLOOKUP($B9,'Move Editor'!$B:$B,'Move Editor'!$D:$D,""),pow,XLOOKUP($B9,'Move Editor'!$B:$B,'Move Editor'!$E:$E,0),acc,XLOOKUP($B9,'Move Editor'!$B:$B,'Move Editor'!$F:$F,100),atk,IF(cat="Physical",FLOOR((FLOOR(((2*XLOOKUP($K9,'Pokemon Editor'!$A:$A,'Pokemon Editor'!$F:$F,0)+31+FLOOR($P9/4))*$L9)/100)+5)*XLOOKUP($M9,'Nature Editor'!$A:$A,'Nature Editor'!$B:$B,1)),FLOOR((FLOOR(((2*XLOOKUP($K9,'Pokemon Editor'!$A:$A,'Pokemon Editor'!$H:$H,0)+31+FLOOR($R9/4))*$L9)/100)+5)*XLOOKUP($M9,'Nature Editor'!$A:$A,'Nature Editor'!$D:$D,1))),def,IF(cat="Physical",FLOOR((FLOOR(((2*XLOOKUP('Boss Editor'!$C$4,'Pokemon Editor'!$A:$A,'Pokemon Editor'!$G:$G,0)+31+FLOOR('Boss Editor'!$I$4/4))*'Boss Editor'!$D$4)/100)+5)*XLOOKUP('Boss Editor'!$E$4,'Nature Editor'!$A:$A,'Nature Editor'!$C:$C,1)),FLOOR((FLOOR(((2*XLOOKUP('Boss Editor'!$C$4,'Pokemon Editor'!$A:$A,'Pokemon Editor'!$I:$I,0)+31+FLOOR('Boss Editor'!$K$4/4))*'Boss Editor'!$D$4)/100)+5)*XLOOKUP('Boss Editor'!$E$4,'Nature Editor'!$A:$A,'Nature Editor'!$E:$E,1))),stab,IF(OR(mtype=XLOOKUP($K9,'Pokemon Editor'!$A:$A,'Pokemon Editor'!$C:$C,""),mtype=XLOOKUP($K9,'Pokemon Editor'!$A:$A,'Pokemon Editor'!$D:$D,"")),1.5,1),eff,(INDEX('Type Chart'!$B:$S,MATCH(mtype,'Type Chart'!$A:$A,0),MATCH(XLOOKUP('Boss Editor'!$C$4,'Pokemon Editor'!$A:$A,'Pokemon Editor'!$C:$C,""),'Type Chart'!$B$1:$S$1,0))*IF(XLOOKUP('Boss Editor'!$C$4,'Pokemon Editor'!$A:$A,'Pokemon Editor'!$D:$D,"")="",1,INDEX('Type Chart'!$B:$S,MATCH(mtype,'Type Chart'!$A:$A,0),MATCH(XLOOKUP('Boss Editor'!$C$4,'Pokemon Editor'!$A:$A,'Pokemon Editor'!$D:$D,""),'Type Chart'!$B$1:$S$1,0)))),base,IF(OR(cat="Status",pow=0),0,FLOOR(FLOOR(FLOOR((2*$L9/5+2)*pow*atk/def)/50)+2)),modifier,stab*eff,AVERAGE(ARRAYFORMULA(FLOOR(base*modifier*SEQUENCE(16,1,85,1)/100)))/(FLOOR(((2*XLOOKUP('Boss Editor'!$C$4,'Pokemon Editor'!$A:$A,'Pokemon Editor'!$E:$E,0)+31+FLOOR('Boss Editor'!$G$4/4))*'Boss Editor'!$D$4)/100)+'Boss Editor'!$D$4+10)),0) | D9: Acid | E9: =IFERROR(LET(mtype,XLOOKUP($D9,'Move Editor'!$B:$B,'Move Editor'!$C:$C,""),cat,XLOOKUP($D9,'Move Editor'!$B:$B,'Move Editor'!$D:$D,""),pow,XLOOKUP($D9,'Move Editor'!$B:$B,'Move Editor'!$E:$E,0),acc,XLOOKUP($D9,'Move Editor'!$B:$B,'Move Editor'!$F:$F,100),atk,IF(cat="Physical",FLOOR((FLOOR(((2*XLOOKUP('Boss Editor'!$C$4,'Pokemon Editor'!$A:$A,'Pokemon Editor'!$F:$F,0)+31+FLOOR('Boss Editor'!$H$4/4))*'Boss Editor'!$D$4)/100)+5)*XLOOKUP('Boss Editor'!$E$4,'Nature Editor'!$A:$A,'Nature Editor'!$B:$B,1)),FLOOR((FLOOR(((2*XLOOKUP('Boss Editor'!$C$4,'Pokemon Editor'!$A:$A,'Pokemon Editor'!$H:$H,0)+31+FLOOR('Boss Editor'!$J$4/4))*'Boss Editor'!$D$4)/100)+5)*XLOOKUP('Boss Editor'!$E$4,'Nature Editor'!$A:$A,'Nature Editor'!$D:$D,1))),def,IF(cat="Physical",FLOOR((FLOOR(((2*XLOOKUP($K9,'Pokemon Editor'!$A:$A,'Pokemon Editor'!$G:$G,0)+31+FLOOR($Q9/4))*$L9)/100)+5)*XLOOKUP($M9,'Nature Editor'!$A:$A,'Nature Editor'!$C:$C,1)),FLOOR((FLOOR(((2*XLOOKUP($K9,'Pokemon Editor'!$A:$A,'Pokemon Editor'!$I:$I,0)+31+FLOOR($S9/4))*$L9)/100)+5)*XLOOKUP($M9,'Nature Editor'!$A:$A,'Nature Editor'!$E:$E,1))),stab,IF(OR(mtype=XLOOKUP('Boss Editor'!$C$4,'Pokemon Editor'!$A:$A,'Pokemon Editor'!$C:$C,""),mtype=XLOOKUP('Boss Editor'!$C$4,'Pokemon Editor'!$A:$A,'Pokemon Editor'!$D:$D,"")),1.5,1),eff,(INDEX('Type Chart'!$B:$S,MATCH(mtype,'Type Chart'!$A:$A,0),MATCH(XLOOKUP($K9,'Pokemon Editor'!$A:$A,'Pokemon Editor'!$C:$C,""),'Type Chart'!$B$1:$S$1,0))*IF(XLOOKUP($K9,'Pokemon Editor'!$A:$A,'Pokemon Editor'!$D:$D,"")="",1,INDEX('Type Chart'!$B:$S,MATCH(mtype,'Type Chart'!$A:$A,0),MATCH(XLOOKUP($K9,'Pokemon Editor'!$A:$A,'Pokemon Editor'!$D:$D,""),'Type Chart'!$B$1:$S$1,0)))),base,IF(OR(cat="Status",pow=0),0,FLOOR(FLOOR(FLOOR((2*'Boss Editor'!$D$4/5+2)*pow*atk/def)/50)+2)),modifier,stab*eff,AVERAGE(ARRAYFORMULA(FLOOR(base*modifier*SEQUENCE(16,1,85,1)/100)))/(FLOOR(((2*XLOOKUP($K9,'Pokemon Editor'!$A:$A,'Pokemon Editor'!$E:$E,0)+31+FLOOR($O9/4))*$L9)/100)+$L9+10)),0) | F9: =FLOOR((FLOOR(((2*XLOOKUP($K9,'Pokemon Editor'!$A:$A,'Pokemon Editor'!$J:$J,0)+31+FLOOR($T9/4))*$L9)/100)+5)*XLOOKUP($M9,'Nature Editor'!$A:$A,'Nature Editor'!$F:$F,1)) | G9: =FLOOR((FLOOR(((2*XLOOKUP('Boss Editor'!$C$4,'Pokemon Editor'!$A:$A,'Pokemon Editor'!$J:$J,0)+31+FLOOR('Boss Editor'!$L$4/4))*'Boss Editor'!$D$4)/100)+5)*XLOOKUP('Boss Editor'!$E$4,'Nature Editor'!$A:$A,'Nature Editor'!$F:$F,1)) | H9: =IF(F9>G9,"Yes","No") | I9: =C9-E9 | J9: =IFS(AND(C9>=0.5,E9<0.5),"Dominant",AND(C9>=0.35,E9<0.75),"Strong",AND(C9>=0.25,E9<1),"Viable",AND(C9>=0.15,E9<1.25),"Risky",TRUE,"Poor") | K9: =REDUCE($Y9,SEQUENCE(2),LAMBDA(current_species,unused_step,IFERROR(INDEX(FILTER('Evolution Editor'!$D$2:$D,'Evolution Editor'!$A$2:$A=current_species,'Evolution Editor'!$F$2:$F=TRUE,'Evolution Editor'!$E$2:$E<=$L9),1),current_species))) | L9: 15 | M9: Neutral | N9: ABILITY_KEEN_EYE | O9: 0 | P9: 0 | Q9: 0 | R9: 0 | S9: 0 | T9: 0 | U9: =IFERROR(LET(mtype,XLOOKUP($B9,'Move Editor'!$B:$B,'Move Editor'!$C:$C,""),cat,XLOOKUP($B9,'Move Editor'!$B:$B,'Move Editor'!$D:$D,""),pow,XLOOKUP($B9,'Move Editor'!$B:$B,'Move Editor'!$E:$E,0),acc,XLOOKUP($B9,'Move Editor'!$B:$B,'Move Editor'!$F:$F,100),atk,IF(cat="Physical",FLOOR((FLOOR(((2*XLOOKUP($K9,'Pokemon Editor'!$A:$A,'Pokemon Editor'!$F:$F,0)+31+FLOOR($P9/4))*$L9)/100)+5)*XLOOKUP($M9,'Nature Editor'!$A:$A,'Nature Editor'!$B:$B,1)),FLOOR((FLOOR(((2*XLOOKUP($K9,'Pokemon Editor'!$A:$A,'Pokemon Editor'!$H:$H,0)+31+FLOOR($R9/4))*$L9)/100)+5)*XLOOKUP($M9,'Nature Editor'!$A:$A,'Nature Editor'!$D:$D,1))),def,IF(cat="Physical",FLOOR((FLOOR(((2*XLOOKUP('Boss Editor'!$C$4,'Pokemon Editor'!$A:$A,'Pokemon Editor'!$G:$G,0)+31+FLOOR('Boss Editor'!$I$4/4))*'Boss Editor'!$D$4)/100)+5)*XLOOKUP('Boss Editor'!$E$4,'Nature Editor'!$A:$A,'Nature Editor'!$C:$C,1)),FLOOR((FLOOR(((2*XLOOKUP('Boss Editor'!$C$4,'Pokemon Editor'!$A:$A,'Pokemon Editor'!$I:$I,0)+31+FLOOR('Boss Editor'!$K$4/4))*'Boss Editor'!$D$4)/100)+5)*XLOOKUP('Boss Editor'!$E$4,'Nature Editor'!$A:$A,'Nature Editor'!$E:$E,1))),stab,IF(OR(mtype=XLOOKUP($K9,'Pokemon Editor'!$A:$A,'Pokemon Editor'!$C:$C,""),mtype=XLOOKUP($K9,'Pokemon Editor'!$A:$A,'Pokemon Editor'!$D:$D,"")),1.5,1),eff,(INDEX('Type Chart'!$B:$S,MATCH(mtype,'Type Chart'!$A:$A,0),MATCH(XLOOKUP('Boss Editor'!$C$4,'Pokemon Editor'!$A:$A,'Pokemon Editor'!$C:$C,""),'Type Chart'!$B$1:$S$1,0))*IF(XLOOKUP('Boss Editor'!$C$4,'Pokemon Editor'!$A:$A,'Pokemon Editor'!$D:$D,"")="",1,INDEX('Type Chart'!$B:$S,MATCH(mtype,'Type Chart'!$A:$A,0),MATCH(XLOOKUP('Boss Editor'!$C$4,'Pokemon Editor'!$A:$A,'Pokemon Editor'!$D:$D,""),'Type Chart'!$B$1:$S$1,0)))),base,IF(OR(cat="Status",pow=0),0,FLOOR(FLOOR(FLOOR((2*$L9/5+2)*pow*atk/def)/50)+2)),modifier,stab*eff,FLOOR(base*modifier*0.85)),0) | V9: =IFERROR(LET(mtype,XLOOKUP($B9,'Move Editor'!$B:$B,'Move Editor'!$C:$C,""),cat,XLOOKUP($B9,'Move Editor'!$B:$B,'Move Editor'!$D:$D,""),pow,XLOOKUP($B9,'Move Editor'!$B:$B,'Move Editor'!$E:$E,0),acc,XLOOKUP($B9,'Move Editor'!$B:$B,'Move Editor'!$F:$F,100),atk,IF(cat="Physical",FLOOR((FLOOR(((2*XLOOKUP($K9,'Pokemon Editor'!$A:$A,'Pokemon Editor'!$F:$F,0)+31+FLOOR($P9/4))*$L9)/100)+5)*XLOOKUP($M9,'Nature Editor'!$A:$A,'Nature Editor'!$B:$B,1)),FLOOR((FLOOR(((2*XLOOKUP($K9,'Pokemon Editor'!$A:$A,'Pokemon Editor'!$H:$H,0)+31+FLOOR($R9/4))*$L9)/100)+5)*XLOOKUP($M9,'Nature Editor'!$A:$A,'Nature Editor'!$D:$D,1))),def,IF(cat="Physical",FLOOR((FLOOR(((2*XLOOKUP('Boss Editor'!$C$4,'Pokemon Editor'!$A:$A,'Pokemon Editor'!$G:$G,0)+31+FLOOR('Boss Editor'!$I$4/4))*'Boss Editor'!$D$4)/100)+5)*XLOOKUP('Boss Editor'!$E$4,'Nature Editor'!$A:$A,'Nature Editor'!$C:$C,1)),FLOOR((FLOOR(((2*XLOOKUP('Boss Editor'!$C$4,'Pokemon Editor'!$A:$A,'Pokemon Editor'!$I:$I,0)+31+FLOOR('Boss Editor'!$K$4/4))*'Boss Editor'!$D$4)/100)+5)*XLOOKUP('Boss Editor'!$E$4,'Nature Editor'!$A:$A,'Nature Editor'!$E:$E,1))),stab,IF(OR(mtype=XLOOKUP($K9,'Pokemon Editor'!$A:$A,'Pokemon Editor'!$C:$C,""),mtype=XLOOKUP($K9,'Pokemon Editor'!$A:$A,'Pokemon Editor'!$D:$D,"")),1.5,1),eff,(INDEX('Type Chart'!$B:$S,MATCH(mtype,'Type Chart'!$A:$A,0),MATCH(XLOOKUP('Boss Editor'!$C$4,'Pokemon Editor'!$A:$A,'Pokemon Editor'!$C:$C,""),'Type Chart'!$B$1:$S$1,0))*IF(XLOOKUP('Boss Editor'!$C$4,'Pokemon Editor'!$A:$A,'Pokemon Editor'!$D:$D,"")="",1,INDEX('Type Chart'!$B:$S,MATCH(mtype,'Type Chart'!$A:$A,0),MATCH(XLOOKUP('Boss Editor'!$C$4,'Pokemon Editor'!$A:$A,'Pokemon Editor'!$D:$D,""),'Type Chart'!$B$1:$S$1,0)))),base,IF(OR(cat="Status",pow=0),0,FLOOR(FLOOR(FLOOR((2*$L9/5+2)*pow*atk/def)/50)+2)),modifier,stab*eff,FLOOR(base*modifier)),0) | W9: =IFERROR(LET(mtype,XLOOKUP($D9,'Move Editor'!$B:$B,'Move Editor'!$C:$C,""),cat,XLOOKUP($D9,'Move Editor'!$B:$B,'Move Editor'!$D:$D,""),pow,XLOOKUP($D9,'Move Editor'!$B:$B,'Move Editor'!$E:$E,0),acc,XLOOKUP($D9,'Move Editor'!$B:$B,'Move Editor'!$F:$F,100),atk,IF(cat="Physical",FLOOR((FLOOR(((2*XLOOKUP('Boss Editor'!$C$4,'Pokemon Editor'!$A:$A,'Pokemon Editor'!$F:$F,0)+31+FLOOR('Boss Editor'!$H$4/4))*'Boss Editor'!$D$4)/100)+5)*XLOOKUP('Boss Editor'!$E$4,'Nature Editor'!$A:$A,'Nature Editor'!$B:$B,1)),FLOOR((FLOOR(((2*XLOOKUP('Boss Editor'!$C$4,'Pokemon Editor'!$A:$A,'Pokemon Editor'!$H:$H,0)+31+FLOOR('Boss Editor'!$J$4/4))*'Boss Editor'!$D$4)/100)+5)*XLOOKUP('Boss Editor'!$E$4,'Nature Editor'!$A:$A,'Nature Editor'!$D:$D,1))),def,IF(cat="Physical",FLOOR((FLOOR(((2*XLOOKUP($K9,'Pokemon Editor'!$A:$A,'Pokemon Editor'!$G:$G,0)+31+FLOOR($Q9/4))*$L9)/100)+5)*XLOOKUP($M9,'Nature Editor'!$A:$A,'Nature Editor'!$C:$C,1)),FLOOR((FLOOR(((2*XLOOKUP($K9,'Pokemon Editor'!$A:$A,'Pokemon Editor'!$I:$I,0)+31+FLOOR($S9/4))*$L9)/100)+5)*XLOOKUP($M9,'Nature Editor'!$A:$A,'Nature Editor'!$E:$E,1))),stab,IF(OR(mtype=XLOOKUP('Boss Editor'!$C$4,'Pokemon Editor'!$A:$A,'Pokemon Editor'!$C:$C,""),mtype=XLOOKUP('Boss Editor'!$C$4,'Pokemon Editor'!$A:$A,'Pokemon Editor'!$D:$D,"")),1.5,1),eff,(INDEX('Type Chart'!$B:$S,MATCH(mtype,'Type Chart'!$A:$A,0),MATCH(XLOOKUP($K9,'Pokemon Editor'!$A:$A,'Pokemon Editor'!$C:$C,""),'Type Chart'!$B$1:$S$1,0))*IF(XLOOKUP($K9,'Pokemon Editor'!$A:$A,'Pokemon Editor'!$D:$D,"")="",1,INDEX('Type Chart'!$B:$S,MATCH(mtype,'Type Chart'!$A:$A,0),MATCH(XLOOKUP($K9,'Pokemon Editor'!$A:$A,'Pokemon Editor'!$D:$D,""),'Type Chart'!$B$1:$S$1,0)))),base,IF(OR(cat="Status",pow=0),0,FLOOR(FLOOR(FLOOR((2*'Boss Editor'!$D$4/5+2)*pow*atk/def)/50)+2)),modifier,stab*eff,FLOOR(base*modifier*0.85)),0) | X9: =IFERROR(LET(mtype,XLOOKUP($D9,'Move Editor'!$B:$B,'Move Editor'!$C:$C,""),cat,XLOOKUP($D9,'Move Editor'!$B:$B,'Move Editor'!$D:$D,""),pow,XLOOKUP($D9,'Move Editor'!$B:$B,'Move Editor'!$E:$E,0),acc,XLOOKUP($D9,'Move Editor'!$B:$B,'Move Editor'!$F:$F,100),atk,IF(cat="Physical",FLOOR((FLOOR(((2*XLOOKUP('Boss Editor'!$C$4,'Pokemon Editor'!$A:$A,'Pokemon Editor'!$F:$F,0)+31+FLOOR('Boss Editor'!$H$4/4))*'Boss Editor'!$D$4)/100)+5)*XLOOKUP('Boss Editor'!$E$4,'Nature Editor'!$A:$A,'Nature Editor'!$B:$B,1)),FLOOR((FLOOR(((2*XLOOKUP('Boss Editor'!$C$4,'Pokemon Editor'!$A:$A,'Pokemon Editor'!$H:$H,0)+31+FLOOR('Boss Editor'!$J$4/4))*'Boss Editor'!$D$4)/100)+5)*XLOOKUP('Boss Editor'!$E$4,'Nature Editor'!$A:$A,'Nature Editor'!$D:$D,1))),def,IF(cat="Physical",FLOOR((FLOOR(((2*XLOOKUP($K9,'Pokemon Editor'!$A:$A,'Pokemon Editor'!$G:$G,0)+31+FLOOR($Q9/4))*$L9)/100)+5)*XLOOKUP($M9,'Nature Editor'!$A:$A,'Nature Editor'!$C:$C,1)),FLOOR((FLOOR(((2*XLOOKUP($K9,'Pokemon Editor'!$A:$A,'Pokemon Editor'!$I:$I,0)+31+FLOOR($S9/4))*$L9)/100)+5)*XLOOKUP($M9,'Nature Editor'!$A:$A,'Nature Editor'!$E:$E,1))),stab,IF(OR(mtype=XLOOKUP('Boss Editor'!$C$4,'Pokemon Editor'!$A:$A,'Pokemon Editor'!$C:$C,""),mtype=XLOOKUP('Boss Editor'!$C$4,'Pokemon Editor'!$A:$A,'Pokemon Editor'!$D:$D,"")),1.5,1),eff,(INDEX('Type Chart'!$B:$S,MATCH(mtype,'Type Chart'!$A:$A,0),MATCH(XLOOKUP($K9,'Pokemon Editor'!$A:$A,'Pokemon Editor'!$C:$C,""),'Type Chart'!$B$1:$S$1,0))*IF(XLOOKUP($K9,'Pokemon Editor'!$A:$A,'Pokemon Editor'!$D:$D,"")="",1,INDEX('Type Chart'!$B:$S,MATCH(mtype,'Type Chart'!$A:$A,0),MATCH(XLOOKUP($K9,'Pokemon Editor'!$A:$A,'Pokemon Editor'!$D:$D,""),'Type Chart'!$B$1:$S$1,0)))),base,IF(OR(cat="Status",pow=0),0,FLOOR(FLOOR(FLOOR((2*'Boss Editor'!$D$4/5+2)*pow*atk/def)/50)+2)),modifier,stab*eff,FLOOR(base*modifier)),0) | Y9: SPECIES_DUCKLETT
A10: =XLOOKUP(K10,'Pokemon Editor'!$A:$A,'Pokemon Editor'!$B:$B,K10) | B10: =IF($Z10<>"",$Z10,IFERROR(INDEX(FILTER('Move Comparison'!$D$2:$D,'Move Comparison'!$Q$2:$Q=$Y10,'Move Comparison'!$M$2:$M=MAXIFS('Move Comparison'!$M$2:$M,'Move Comparison'!$Q$2:$Q,$Y10),'Move Comparison'!$D$2:$D<>""),1),"")) | C10: =IFERROR(LET(mtype,XLOOKUP($B10,'Move Editor'!$B:$B,'Move Editor'!$C:$C,""),cat,XLOOKUP($B10,'Move Editor'!$B:$B,'Move Editor'!$D:$D,""),pow,XLOOKUP($B10,'Move Editor'!$B:$B,'Move Editor'!$E:$E,0),acc,XLOOKUP($B10,'Move Editor'!$B:$B,'Move Editor'!$F:$F,100),atk,IF(cat="Physical",FLOOR((FLOOR(((2*XLOOKUP($K10,'Pokemon Editor'!$A:$A,'Pokemon Editor'!$F:$F,0)+31+FLOOR($P10/4))*$L10)/100)+5)*XLOOKUP($M10,'Nature Editor'!$A:$A,'Nature Editor'!$B:$B,1)),FLOOR((FLOOR(((2*XLOOKUP($K10,'Pokemon Editor'!$A:$A,'Pokemon Editor'!$H:$H,0)+31+FLOOR($R10/4))*$L10)/100)+5)*XLOOKUP($M10,'Nature Editor'!$A:$A,'Nature Editor'!$D:$D,1))),def,IF(cat="Physical",FLOOR((FLOOR(((2*XLOOKUP('Boss Editor'!$C$4,'Pokemon Editor'!$A:$A,'Pokemon Editor'!$G:$G,0)+31+FLOOR('Boss Editor'!$I$4/4))*'Boss Editor'!$D$4)/100)+5)*XLOOKUP('Boss Editor'!$E$4,'Nature Editor'!$A:$A,'Nature Editor'!$C:$C,1)),FLOOR((FLOOR(((2*XLOOKUP('Boss Editor'!$C$4,'Pokemon Editor'!$A:$A,'Pokemon Editor'!$I:$I,0)+31+FLOOR('Boss Editor'!$K$4/4))*'Boss Editor'!$D$4)/100)+5)*XLOOKUP('Boss Editor'!$E$4,'Nature Editor'!$A:$A,'Nature Editor'!$E:$E,1))),stab,IF(OR(mtype=XLOOKUP($K10,'Pokemon Editor'!$A:$A,'Pokemon Editor'!$C:$C,""),mtype=XLOOKUP($K10,'Pokemon Editor'!$A:$A,'Pokemon Editor'!$D:$D,"")),1.5,1),eff,(INDEX('Type Chart'!$B:$S,MATCH(mtype,'Type Chart'!$A:$A,0),MATCH(XLOOKUP('Boss Editor'!$C$4,'Pokemon Editor'!$A:$A,'Pokemon Editor'!$C:$C,""),'Type Chart'!$B$1:$S$1,0))*IF(XLOOKUP('Boss Editor'!$C$4,'Pokemon Editor'!$A:$A,'Pokemon Editor'!$D:$D,"")="",1,INDEX('Type Chart'!$B:$S,MATCH(mtype,'Type Chart'!$A:$A,0),MATCH(XLOOKUP('Boss Editor'!$C$4,'Pokemon Editor'!$A:$A,'Pokemon Editor'!$D:$D,""),'Type Chart'!$B$1:$S$1,0)))),base,IF(OR(cat="Status",pow=0),0,FLOOR(FLOOR(FLOOR((2*$L10/5+2)*pow*atk/def)/50)+2)),modifier,stab*eff,AVERAGE(ARRAYFORMULA(FLOOR(base*modifier*SEQUENCE(16,1,85,1)/100)))/(FLOOR(((2*XLOOKUP('Boss Editor'!$C$4,'Pokemon Editor'!$A:$A,'Pokemon Editor'!$E:$E,0)+31+FLOOR('Boss Editor'!$G$4/4))*'Boss Editor'!$D$4)/100)+'Boss Editor'!$D$4+10)),0) | D10: Acid | E10: =IFERROR(LET(mtype,XLOOKUP($D10,'Move Editor'!$B:$B,'Move Editor'!$C:$C,""),cat,XLOOKUP($D10,'Move Editor'!$B:$B,'Move Editor'!$D:$D,""),pow,XLOOKUP($D10,'Move Editor'!$B:$B,'Move Editor'!$E:$E,0),acc,XLOOKUP($D10,'Move Editor'!$B:$B,'Move Editor'!$F:$F,100),atk,IF(cat="Physical",FLOOR((FLOOR(((2*XLOOKUP('Boss Editor'!$C$4,'Pokemon Editor'!$A:$A,'Pokemon Editor'!$F:$F,0)+31+FLOOR('Boss Editor'!$H$4/4))*'Boss Editor'!$D$4)/100)+5)*XLOOKUP('Boss Editor'!$E$4,'Nature Editor'!$A:$A,'Nature Editor'!$B:$B,1)),FLOOR((FLOOR(((2*XLOOKUP('Boss Editor'!$C$4,'Pokemon Editor'!$A:$A,'Pokemon Editor'!$H:$H,0)+31+FLOOR('Boss Editor'!$J$4/4))*'Boss Editor'!$D$4)/100)+5)*XLOOKUP('Boss Editor'!$E$4,'Nature Editor'!$A:$A,'Nature Editor'!$D:$D,1))),def,IF(cat="Physical",FLOOR((FLOOR(((2*XLOOKUP($K10,'Pokemon Editor'!$A:$A,'Pokemon Editor'!$G:$G,0)+31+FLOOR($Q10/4))*$L10)/100)+5)*XLOOKUP($M10,'Nature Editor'!$A:$A,'Nature Editor'!$C:$C,1)),FLOOR((FLOOR(((2*XLOOKUP($K10,'Pokemon Editor'!$A:$A,'Pokemon Editor'!$I:$I,0)+31+FLOOR($S10/4))*$L10)/100)+5)*XLOOKUP($M10,'Nature Editor'!$A:$A,'Nature Editor'!$E:$E,1))),stab,IF(OR(mtype=XLOOKUP('Boss Editor'!$C$4,'Pokemon Editor'!$A:$A,'Pokemon Editor'!$C:$C,""),mtype=XLOOKUP('Boss Editor'!$C$4,'Pokemon Editor'!$A:$A,'Pokemon Editor'!$D:$D,"")),1.5,1),eff,(INDEX('Type Chart'!$B:$S,MATCH(mtype,'Type Chart'!$A:$A,0),MATCH(XLOOKUP($K10,'Pokemon Editor'!$A:$A,'Pokemon Editor'!$C:$C,""),'Type Chart'!$B$1:$S$1,0))*IF(XLOOKUP($K10,'Pokemon Editor'!$A:$A,'Pokemon Editor'!$D:$D,"")="",1,INDEX('Type Chart'!$B:$S,MATCH(mtype,'Type Chart'!$A:$A,0),MATCH(XLOOKUP($K10,'Pokemon Editor'!$A:$A,'Pokemon Editor'!$D:$D,""),'Type Chart'!$B$1:$S$1,0)))),base,IF(OR(cat="Status",pow=0),0,FLOOR(FLOOR(FLOOR((2*'Boss Editor'!$D$4/5+2)*pow*atk/def)/50)+2)),modifier,stab*eff,AVERAGE(ARRAYFORMULA(FLOOR(base*modifier*SEQUENCE(16,1,85,1)/100)))/(FLOOR(((2*XLOOKUP($K10,'Pokemon Editor'!$A:$A,'Pokemon Editor'!$E:$E,0)+31+FLOOR($O10/4))*$L10)/100)+$L10+10)),0) | F10: =FLOOR((FLOOR(((2*XLOOKUP($K10,'Pokemon Editor'!$A:$A,'Pokemon Editor'!$J:$J,0)+31+FLOOR($T10/4))*$L10)/100)+5)*XLOOKUP($M10,'Nature Editor'!$A:$A,'Nature Editor'!$F:$F,1)) | G10: =FLOOR((FLOOR(((2*XLOOKUP('Boss Editor'!$C$4,'Pokemon Editor'!$A:$A,'Pokemon Editor'!$J:$J,0)+31+FLOOR('Boss Editor'!$L$4/4))*'Boss Editor'!$D$4)/100)+5)*XLOOKUP('Boss Editor'!$E$4,'Nature Editor'!$A:$A,'Nature Editor'!$F:$F,1)) | H10: =IF(F10>G10,"Yes","No") | I10: =C10-E10 | J10: =IFS(AND(C10>=0.5,E10<0.5),"Dominant",AND(C10>=0.35,E10<0.75),"Strong",AND(C10>=0.25,E10<1),"Viable",AND(C10>=0.15,E10<1.25),"Risky",TRUE,"Poor") | K10: =REDUCE($Y10,SEQUENCE(2),LAMBDA(current_species,unused_step,IFERROR(INDEX(FILTER('Evolution Editor'!$D$2:$D,'Evolution Editor'!$A$2:$A=current_species,'Evolution Editor'!$F$2:$F=TRUE,'Evolution Editor'!$E$2:$E<=$L10),1),current_species))) | L10: 15 | M10: Neutral | N10: ABILITY_RIVALRY | O10: 0 | P10: 0 | Q10: 0 | R10: 0 | S10: 0 | T10: 0 | U10: =IFERROR(LET(mtype,XLOOKUP($B10,'Move Editor'!$B:$B,'Move Editor'!$C:$C,""),cat,XLOOKUP($B10,'Move Editor'!$B:$B,'Move Editor'!$D:$D,""),pow,XLOOKUP($B10,'Move Editor'!$B:$B,'Move Editor'!$E:$E,0),acc,XLOOKUP($B10,'Move Editor'!$B:$B,'Move Editor'!$F:$F,100),atk,IF(cat="Physical",FLOOR((FLOOR(((2*XLOOKUP($K10,'Pokemon Editor'!$A:$A,'Pokemon Editor'!$F:$F,0)+31+FLOOR($P10/4))*$L10)/100)+5)*XLOOKUP($M10,'Nature Editor'!$A:$A,'Nature Editor'!$B:$B,1)),FLOOR((FLOOR(((2*XLOOKUP($K10,'Pokemon Editor'!$A:$A,'Pokemon Editor'!$H:$H,0)+31+FLOOR($R10/4))*$L10)/100)+5)*XLOOKUP($M10,'Nature Editor'!$A:$A,'Nature Editor'!$D:$D,1))),def,IF(cat="Physical",FLOOR((FLOOR(((2*XLOOKUP('Boss Editor'!$C$4,'Pokemon Editor'!$A:$A,'Pokemon Editor'!$G:$G,0)+31+FLOOR('Boss Editor'!$I$4/4))*'Boss Editor'!$D$4)/100)+5)*XLOOKUP('Boss Editor'!$E$4,'Nature Editor'!$A:$A,'Nature Editor'!$C:$C,1)),FLOOR((FLOOR(((2*XLOOKUP('Boss Editor'!$C$4,'Pokemon Editor'!$A:$A,'Pokemon Editor'!$I:$I,0)+31+FLOOR('Boss Editor'!$K$4/4))*'Boss Editor'!$D$4)/100)+5)*XLOOKUP('Boss Editor'!$E$4,'Nature Editor'!$A:$A,'Nature Editor'!$E:$E,1))),stab,IF(OR(mtype=XLOOKUP($K10,'Pokemon Editor'!$A:$A,'Pokemon Editor'!$C:$C,""),mtype=XLOOKUP($K10,'Pokemon Editor'!$A:$A,'Pokemon Editor'!$D:$D,"")),1.5,1),eff,(INDEX('Type Chart'!$B:$S,MATCH(mtype,'Type Chart'!$A:$A,0),MATCH(XLOOKUP('Boss Editor'!$C$4,'Pokemon Editor'!$A:$A,'Pokemon Editor'!$C:$C,""),'Type Chart'!$B$1:$S$1,0))*IF(XLOOKUP('Boss Editor'!$C$4,'Pokemon Editor'!$A:$A,'Pokemon Editor'!$D:$D,"")="",1,INDEX('Type Chart'!$B:$S,MATCH(mtype,'Type Chart'!$A:$A,0),MATCH(XLOOKUP('Boss Editor'!$C$4,'Pokemon Editor'!$A:$A,'Pokemon Editor'!$D:$D,""),'Type Chart'!$B$1:$S$1,0)))),base,IF(OR(cat="Status",pow=0),0,FLOOR(FLOOR(FLOOR((2*$L10/5+2)*pow*atk/def)/50)+2)),modifier,stab*eff,FLOOR(base*modifier*0.85)),0) | V10: =IFERROR(LET(mtype,XLOOKUP($B10,'Move Editor'!$B:$B,'Move Editor'!$C:$C,""),cat,XLOOKUP($B10,'Move Editor'!$B:$B,'Move Editor'!$D:$D,""),pow,XLOOKUP($B10,'Move Editor'!$B:$B,'Move Editor'!$E:$E,0),acc,XLOOKUP($B10,'Move Editor'!$B:$B,'Move Editor'!$F:$F,100),atk,IF(cat="Physical",FLOOR((FLOOR(((2*XLOOKUP($K10,'Pokemon Editor'!$A:$A,'Pokemon Editor'!$F:$F,0)+31+FLOOR($P10/4))*$L10)/100)+5)*XLOOKUP($M10,'Nature Editor'!$A:$A,'Nature Editor'!$B:$B,1)),FLOOR((FLOOR(((2*XLOOKUP($K10,'Pokemon Editor'!$A:$A,'Pokemon Editor'!$H:$H,0)+31+FLOOR($R10/4))*$L10)/100)+5)*XLOOKUP($M10,'Nature Editor'!$A:$A,'Nature Editor'!$D:$D,1))),def,IF(cat="Physical",FLOOR((FLOOR(((2*XLOOKUP('Boss Editor'!$C$4,'Pokemon Editor'!$A:$A,'Pokemon Editor'!$G:$G,0)+31+FLOOR('Boss Editor'!$I$4/4))*'Boss Editor'!$D$4)/100)+5)*XLOOKUP('Boss Editor'!$E$4,'Nature Editor'!$A:$A,'Nature Editor'!$C:$C,1)),FLOOR((FLOOR(((2*XLOOKUP('Boss Editor'!$C$4,'Pokemon Editor'!$A:$A,'Pokemon Editor'!$I:$I,0)+31+FLOOR('Boss Editor'!$K$4/4))*'Boss Editor'!$D$4)/100)+5)*XLOOKUP('Boss Editor'!$E$4,'Nature Editor'!$A:$A,'Nature Editor'!$E:$E,1))),stab,IF(OR(mtype=XLOOKUP($K10,'Pokemon Editor'!$A:$A,'Pokemon Editor'!$C:$C,""),mtype=XLOOKUP($K10,'Pokemon Editor'!$A:$A,'Pokemon Editor'!$D:$D,"")),1.5,1),eff,(INDEX('Type Chart'!$B:$S,MATCH(mtype,'Type Chart'!$A:$A,0),MATCH(XLOOKUP('Boss Editor'!$C$4,'Pokemon Editor'!$A:$A,'Pokemon Editor'!$C:$C,""),'Type Chart'!$B$1:$S$1,0))*IF(XLOOKUP('Boss Editor'!$C$4,'Pokemon Editor'!$A:$A,'Pokemon Editor'!$D:$D,"")="",1,INDEX('Type Chart'!$B:$S,MATCH(mtype,'Type Chart'!$A:$A,0),MATCH(XLOOKUP('Boss Editor'!$C$4,'Pokemon Editor'!$A:$A,'Pokemon Editor'!$D:$D,""),'Type Chart'!$B$1:$S$1,0)))),base,IF(OR(cat="Status",pow=0),0,FLOOR(FLOOR(FLOOR((2*$L10/5+2)*pow*atk/def)/50)+2)),modifier,stab*eff,FLOOR(base*modifier)),0) | W10: =IFERROR(LET(mtype,XLOOKUP($D10,'Move Editor'!$B:$B,'Move Editor'!$C:$C,""),cat,XLOOKUP($D10,'Move Editor'!$B:$B,'Move Editor'!$D:$D,""),pow,XLOOKUP($D10,'Move Editor'!$B:$B,'Move Editor'!$E:$E,0),acc,XLOOKUP($D10,'Move Editor'!$B:$B,'Move Editor'!$F:$F,100),atk,IF(cat="Physical",FLOOR((FLOOR(((2*XLOOKUP('Boss Editor'!$C$4,'Pokemon Editor'!$A:$A,'Pokemon Editor'!$F:$F,0)+31+FLOOR('Boss Editor'!$H$4/4))*'Boss Editor'!$D$4)/100)+5)*XLOOKUP('Boss Editor'!$E$4,'Nature Editor'!$A:$A,'Nature Editor'!$B:$B,1)),FLOOR((FLOOR(((2*XLOOKUP('Boss Editor'!$C$4,'Pokemon Editor'!$A:$A,'Pokemon Editor'!$H:$H,0)+31+FLOOR('Boss Editor'!$J$4/4))*'Boss Editor'!$D$4)/100)+5)*XLOOKUP('Boss Editor'!$E$4,'Nature Editor'!$A:$A,'Nature Editor'!$D:$D,1))),def,IF(cat="Physical",FLOOR((FLOOR(((2*XLOOKUP($K10,'Pokemon Editor'!$A:$A,'Pokemon Editor'!$G:$G,0)+31+FLOOR($Q10/4))*$L10)/100)+5)*XLOOKUP($M10,'Nature Editor'!$A:$A,'Nature Editor'!$C:$C,1)),FLOOR((FLOOR(((2*XLOOKUP($K10,'Pokemon Editor'!$A:$A,'Pokemon Editor'!$I:$I,0)+31+FLOOR($S10/4))*$L10)/100)+5)*XLOOKUP($M10,'Nature Editor'!$A:$A,'Nature Editor'!$E:$E,1))),stab,IF(OR(mtype=XLOOKUP('Boss Editor'!$C$4,'Pokemon Editor'!$A:$A,'Pokemon Editor'!$C:$C,""),mtype=XLOOKUP('Boss Editor'!$C$4,'Pokemon Editor'!$A:$A,'Pokemon Editor'!$D:$D,"")),1.5,1),eff,(INDEX('Type Chart'!$B:$S,MATCH(mtype,'Type Chart'!$A:$A,0),MATCH(XLOOKUP($K10,'Pokemon Editor'!$A:$A,'Pokemon Editor'!$C:$C,""),'Type Chart'!$B$1:$S$1,0))*IF(XLOOKUP($K10,'Pokemon Editor'!$A:$A,'Pokemon Editor'!$D:$D,"")="",1,INDEX('Type Chart'!$B:$S,MATCH(mtype,'Type Chart'!$A:$A,0),MATCH(XLOOKUP($K10,'Pokemon Editor'!$A:$A,'Pokemon Editor'!$D:$D,""),'Type Chart'!$B$1:$S$1,0)))),base,IF(OR(cat="Status",pow=0),0,FLOOR(FLOOR(FLOOR((2*'Boss Editor'!$D$4/5+2)*pow*atk/def)/50)+2)),modifier,stab*eff,FLOOR(base*modifier*0.85)),0) | X10: =IFERROR(LET(mtype,XLOOKUP($D10,'Move Editor'!$B:$B,'Move Editor'!$C:$C,""),cat,XLOOKUP($D10,'Move Editor'!$B:$B,'Move Editor'!$D:$D,""),pow,XLOOKUP($D10,'Move Editor'!$B:$B,'Move Editor'!$E:$E,0),acc,XLOOKUP($D10,'Move Editor'!$B:$B,'Move Editor'!$F:$F,100),atk,IF(cat="Physical",FLOOR((FLOOR(((2*XLOOKUP('Boss Editor'!$C$4,'Pokemon Editor'!$A:$A,'Pokemon Editor'!$F:$F,0)+31+FLOOR('Boss Editor'!$H$4/4))*'Boss Editor'!$D$4)/100)+5)*XLOOKUP('Boss Editor'!$E$4,'Nature Editor'!$A:$A,'Nature Editor'!$B:$B,1)),FLOOR((FLOOR(((2*XLOOKUP('Boss Editor'!$C$4,'Pokemon Editor'!$A:$A,'Pokemon Editor'!$H:$H,0)+31+FLOOR('Boss Editor'!$J$4/4))*'Boss Editor'!$D$4)/100)+5)*XLOOKUP('Boss Editor'!$E$4,'Nature Editor'!$A:$A,'Nature Editor'!$D:$D,1))),def,IF(cat="Physical",FLOOR((FLOOR(((2*XLOOKUP($K10,'Pokemon Editor'!$A:$A,'Pokemon Editor'!$G:$G,0)+31+FLOOR($Q10/4))*$L10)/100)+5)*XLOOKUP($M10,'Nature Editor'!$A:$A,'Nature Editor'!$C:$C,1)),FLOOR((FLOOR(((2*XLOOKUP($K10,'Pokemon Editor'!$A:$A,'Pokemon Editor'!$I:$I,0)+31+FLOOR($S10/4))*$L10)/100)+5)*XLOOKUP($M10,'Nature Editor'!$A:$A,'Nature Editor'!$E:$E,1))),stab,IF(OR(mtype=XLOOKUP('Boss Editor'!$C$4,'Pokemon Editor'!$A:$A,'Pokemon Editor'!$C:$C,""),mtype=XLOOKUP('Boss Editor'!$C$4,'Pokemon Editor'!$A:$A,'Pokemon Editor'!$D:$D,"")),1.5,1),eff,(INDEX('Type Chart'!$B:$S,MATCH(mtype,'Type Chart'!$A:$A,0),MATCH(XLOOKUP($K10,'Pokemon Editor'!$A:$A,'Pokemon Editor'!$C:$C,""),'Type Chart'!$B$1:$S$1,0))*IF(XLOOKUP($K10,'Pokemon Editor'!$A:$A,'Pokemon Editor'!$D:$D,"")="",1,INDEX('Type Chart'!$B:$S,MATCH(mtype,'Type Chart'!$A:$A,0),MATCH(XLOOKUP($K10,'Pokemon Editor'!$A:$A,'Pokemon Editor'!$D:$D,""),'Type Chart'!$B$1:$S$1,0)))),base,IF(OR(cat="Status",pow=0),0,FLOOR(FLOOR(FLOOR((2*'Boss Editor'!$D$4/5+2)*pow*atk/def)/50)+2)),modifier,stab*eff,FLOOR(base*modifier)),0) | Y10: SPECIES_SHINX
A11: =XLOOKUP(K11,'Pokemon Editor'!$A:$A,'Pokemon Editor'!$B:$B,K11) | B11: =IF($Z11<>"",$Z11,IFERROR(INDEX(FILTER('Move Comparison'!$D$2:$D,'Move Comparison'!$Q$2:$Q=$Y11,'Move Comparison'!$M$2:$M=MAXIFS('Move Comparison'!$M$2:$M,'Move Comparison'!$Q$2:$Q,$Y11),'Move Comparison'!$D$2:$D<>""),1),"")) | C11: =IFERROR(LET(mtype,XLOOKUP($B11,'Move Editor'!$B:$B,'Move Editor'!$C:$C,""),cat,XLOOKUP($B11,'Move Editor'!$B:$B,'Move Editor'!$D:$D,""),pow,XLOOKUP($B11,'Move Editor'!$B:$B,'Move Editor'!$E:$E,0),acc,XLOOKUP($B11,'Move Editor'!$B:$B,'Move Editor'!$F:$F,100),atk,IF(cat="Physical",FLOOR((FLOOR(((2*XLOOKUP($K11,'Pokemon Editor'!$A:$A,'Pokemon Editor'!$F:$F,0)+31+FLOOR($P11/4))*$L11)/100)+5)*XLOOKUP($M11,'Nature Editor'!$A:$A,'Nature Editor'!$B:$B,1)),FLOOR((FLOOR(((2*XLOOKUP($K11,'Pokemon Editor'!$A:$A,'Pokemon Editor'!$H:$H,0)+31+FLOOR($R11/4))*$L11)/100)+5)*XLOOKUP($M11,'Nature Editor'!$A:$A,'Nature Editor'!$D:$D,1))),def,IF(cat="Physical",FLOOR((FLOOR(((2*XLOOKUP('Boss Editor'!$C$4,'Pokemon Editor'!$A:$A,'Pokemon Editor'!$G:$G,0)+31+FLOOR('Boss Editor'!$I$4/4))*'Boss Editor'!$D$4)/100)+5)*XLOOKUP('Boss Editor'!$E$4,'Nature Editor'!$A:$A,'Nature Editor'!$C:$C,1)),FLOOR((FLOOR(((2*XLOOKUP('Boss Editor'!$C$4,'Pokemon Editor'!$A:$A,'Pokemon Editor'!$I:$I,0)+31+FLOOR('Boss Editor'!$K$4/4))*'Boss Editor'!$D$4)/100)+5)*XLOOKUP('Boss Editor'!$E$4,'Nature Editor'!$A:$A,'Nature Editor'!$E:$E,1))),stab,IF(OR(mtype=XLOOKUP($K11,'Pokemon Editor'!$A:$A,'Pokemon Editor'!$C:$C,""),mtype=XLOOKUP($K11,'Pokemon Editor'!$A:$A,'Pokemon Editor'!$D:$D,"")),1.5,1),eff,(INDEX('Type Chart'!$B:$S,MATCH(mtype,'Type Chart'!$A:$A,0),MATCH(XLOOKUP('Boss Editor'!$C$4,'Pokemon Editor'!$A:$A,'Pokemon Editor'!$C:$C,""),'Type Chart'!$B$1:$S$1,0))*IF(XLOOKUP('Boss Editor'!$C$4,'Pokemon Editor'!$A:$A,'Pokemon Editor'!$D:$D,"")="",1,INDEX('Type Chart'!$B:$S,MATCH(mtype,'Type Chart'!$A:$A,0),MATCH(XLOOKUP('Boss Editor'!$C$4,'Pokemon Editor'!$A:$A,'Pokemon Editor'!$D:$D,""),'Type Chart'!$B$1:$S$1,0)))),base,IF(OR(cat="Status",pow=0),0,FLOOR(FLOOR(FLOOR((2*$L11/5+2)*pow*atk/def)/50)+2)),modifier,stab*eff,AVERAGE(ARRAYFORMULA(FLOOR(base*modifier*SEQUENCE(16,1,85,1)/100)))/(FLOOR(((2*XLOOKUP('Boss Editor'!$C$4,'Pokemon Editor'!$A:$A,'Pokemon Editor'!$E:$E,0)+31+FLOOR('Boss Editor'!$G$4/4))*'Boss Editor'!$D$4)/100)+'Boss Editor'!$D$4+10)),0) | D11: Acid | E11: =IFERROR(LET(mtype,XLOOKUP($D11,'Move Editor'!$B:$B,'Move Editor'!$C:$C,""),cat,XLOOKUP($D11,'Move Editor'!$B:$B,'Move Editor'!$D:$D,""),pow,XLOOKUP($D11,'Move Editor'!$B:$B,'Move Editor'!$E:$E,0),acc,XLOOKUP($D11,'Move Editor'!$B:$B,'Move Editor'!$F:$F,100),atk,IF(cat="Physical",FLOOR((FLOOR(((2*XLOOKUP('Boss Editor'!$C$4,'Pokemon Editor'!$A:$A,'Pokemon Editor'!$F:$F,0)+31+FLOOR('Boss Editor'!$H$4/4))*'Boss Editor'!$D$4)/100)+5)*XLOOKUP('Boss Editor'!$E$4,'Nature Editor'!$A:$A,'Nature Editor'!$B:$B,1)),FLOOR((FLOOR(((2*XLOOKUP('Boss Editor'!$C$4,'Pokemon Editor'!$A:$A,'Pokemon Editor'!$H:$H,0)+31+FLOOR('Boss Editor'!$J$4/4))*'Boss Editor'!$D$4)/100)+5)*XLOOKUP('Boss Editor'!$E$4,'Nature Editor'!$A:$A,'Nature Editor'!$D:$D,1))),def,IF(cat="Physical",FLOOR((FLOOR(((2*XLOOKUP($K11,'Pokemon Editor'!$A:$A,'Pokemon Editor'!$G:$G,0)+31+FLOOR($Q11/4))*$L11)/100)+5)*XLOOKUP($M11,'Nature Editor'!$A:$A,'Nature Editor'!$C:$C,1)),FLOOR((FLOOR(((2*XLOOKUP($K11,'Pokemon Editor'!$A:$A,'Pokemon Editor'!$I:$I,0)+31+FLOOR($S11/4))*$L11)/100)+5)*XLOOKUP($M11,'Nature Editor'!$A:$A,'Nature Editor'!$E:$E,1))),stab,IF(OR(mtype=XLOOKUP('Boss Editor'!$C$4,'Pokemon Editor'!$A:$A,'Pokemon Editor'!$C:$C,""),mtype=XLOOKUP('Boss Editor'!$C$4,'Pokemon Editor'!$A:$A,'Pokemon Editor'!$D:$D,"")),1.5,1),eff,(INDEX('Type Chart'!$B:$S,MATCH(mtype,'Type Chart'!$A:$A,0),MATCH(XLOOKUP($K11,'Pokemon Editor'!$A:$A,'Pokemon Editor'!$C:$C,""),'Type Chart'!$B$1:$S$1,0))*IF(XLOOKUP($K11,'Pokemon Editor'!$A:$A,'Pokemon Editor'!$D:$D,"")="",1,INDEX('Type Chart'!$B:$S,MATCH(mtype,'Type Chart'!$A:$A,0),MATCH(XLOOKUP($K11,'Pokemon Editor'!$A:$A,'Pokemon Editor'!$D:$D,""),'Type Chart'!$B$1:$S$1,0)))),base,IF(OR(cat="Status",pow=0),0,FLOOR(FLOOR(FLOOR((2*'Boss Editor'!$D$4/5+2)*pow*atk/def)/50)+2)),modifier,stab*eff,AVERAGE(ARRAYFORMULA(FLOOR(base*modifier*SEQUENCE(16,1,85,1)/100)))/(FLOOR(((2*XLOOKUP($K11,'Pokemon Editor'!$A:$A,'Pokemon Editor'!$E:$E,0)+31+FLOOR($O11/4))*$L11)/100)+$L11+10)),0) | F11: =FLOOR((FLOOR(((2*XLOOKUP($K11,'Pokemon Editor'!$A:$A,'Pokemon Editor'!$J:$J,0)+31+FLOOR($T11/4))*$L11)/100)+5)*XLOOKUP($M11,'Nature Editor'!$A:$A,'Nature Editor'!$F:$F,1)) | G11: =FLOOR((FLOOR(((2*XLOOKUP('Boss Editor'!$C$4,'Pokemon Editor'!$A:$A,'Pokemon Editor'!$J:$J,0)+31+FLOOR('Boss Editor'!$L$4/4))*'Boss Editor'!$D$4)/100)+5)*XLOOKUP('Boss Editor'!$E$4,'Nature Editor'!$A:$A,'Nature Editor'!$F:$F,1)) | H11: =IF(F11>G11,"Yes","No") | I11: =C11-E11 | J11: =IFS(AND(C11>=0.5,E11<0.5),"Dominant",AND(C11>=0.35,E11<0.75),"Strong",AND(C11>=0.25,E11<1),"Viable",AND(C11>=0.15,E11<1.25),"Risky",TRUE,"Poor") | K11: =REDUCE($Y11,SEQUENCE(2),LAMBDA(current_species,unused_step,IFERROR(INDEX(FILTER('Evolution Editor'!$D$2:$D,'Evolution Editor'!$A$2:$A=current_species,'Evolution Editor'!$F$2:$F=TRUE,'Evolution Editor'!$E$2:$E<=$L11),1),current_species))) | L11: 15 | M11: Neutral | N11: ABILITY_RIVALRY | O11: 0 | P11: 0 | Q11: 0 | R11: 0 | S11: 0 | T11: 0 | U11: =IFERROR(LET(mtype,XLOOKUP($B11,'Move Editor'!$B:$B,'Move Editor'!$C:$C,""),cat,XLOOKUP($B11,'Move Editor'!$B:$B,'Move Editor'!$D:$D,""),pow,XLOOKUP($B11,'Move Editor'!$B:$B,'Move Editor'!$E:$E,0),acc,XLOOKUP($B11,'Move Editor'!$B:$B,'Move Editor'!$F:$F,100),atk,IF(cat="Physical",FLOOR((FLOOR(((2*XLOOKUP($K11,'Pokemon Editor'!$A:$A,'Pokemon Editor'!$F:$F,0)+31+FLOOR($P11/4))*$L11)/100)+5)*XLOOKUP($M11,'Nature Editor'!$A:$A,'Nature Editor'!$B:$B,1)),FLOOR((FLOOR(((2*XLOOKUP($K11,'Pokemon Editor'!$A:$A,'Pokemon Editor'!$H:$H,0)+31+FLOOR($R11/4))*$L11)/100)+5)*XLOOKUP($M11,'Nature Editor'!$A:$A,'Nature Editor'!$D:$D,1))),def,IF(cat="Physical",FLOOR((FLOOR(((2*XLOOKUP('Boss Editor'!$C$4,'Pokemon Editor'!$A:$A,'Pokemon Editor'!$G:$G,0)+31+FLOOR('Boss Editor'!$I$4/4))*'Boss Editor'!$D$4)/100)+5)*XLOOKUP('Boss Editor'!$E$4,'Nature Editor'!$A:$A,'Nature Editor'!$C:$C,1)),FLOOR((FLOOR(((2*XLOOKUP('Boss Editor'!$C$4,'Pokemon Editor'!$A:$A,'Pokemon Editor'!$I:$I,0)+31+FLOOR('Boss Editor'!$K$4/4))*'Boss Editor'!$D$4)/100)+5)*XLOOKUP('Boss Editor'!$E$4,'Nature Editor'!$A:$A,'Nature Editor'!$E:$E,1))),stab,IF(OR(mtype=XLOOKUP($K11,'Pokemon Editor'!$A:$A,'Pokemon Editor'!$C:$C,""),mtype=XLOOKUP($K11,'Pokemon Editor'!$A:$A,'Pokemon Editor'!$D:$D,"")),1.5,1),eff,(INDEX('Type Chart'!$B:$S,MATCH(mtype,'Type Chart'!$A:$A,0),MATCH(XLOOKUP('Boss Editor'!$C$4,'Pokemon Editor'!$A:$A,'Pokemon Editor'!$C:$C,""),'Type Chart'!$B$1:$S$1,0))*IF(XLOOKUP('Boss Editor'!$C$4,'Pokemon Editor'!$A:$A,'Pokemon Editor'!$D:$D,"")="",1,INDEX('Type Chart'!$B:$S,MATCH(mtype,'Type Chart'!$A:$A,0),MATCH(XLOOKUP('Boss Editor'!$C$4,'Pokemon Editor'!$A:$A,'Pokemon Editor'!$D:$D,""),'Type Chart'!$B$1:$S$1,0)))),base,IF(OR(cat="Status",pow=0),0,FLOOR(FLOOR(FLOOR((2*$L11/5+2)*pow*atk/def)/50)+2)),modifier,stab*eff,FLOOR(base*modifier*0.85)),0) | V11: =IFERROR(LET(mtype,XLOOKUP($B11,'Move Editor'!$B:$B,'Move Editor'!$C:$C,""),cat,XLOOKUP($B11,'Move Editor'!$B:$B,'Move Editor'!$D:$D,""),pow,XLOOKUP($B11,'Move Editor'!$B:$B,'Move Editor'!$E:$E,0),acc,XLOOKUP($B11,'Move Editor'!$B:$B,'Move Editor'!$F:$F,100),atk,IF(cat="Physical",FLOOR((FLOOR(((2*XLOOKUP($K11,'Pokemon Editor'!$A:$A,'Pokemon Editor'!$F:$F,0)+31+FLOOR($P11/4))*$L11)/100)+5)*XLOOKUP($M11,'Nature Editor'!$A:$A,'Nature Editor'!$B:$B,1)),FLOOR((FLOOR(((2*XLOOKUP($K11,'Pokemon Editor'!$A:$A,'Pokemon Editor'!$H:$H,0)+31+FLOOR($R11/4))*$L11)/100)+5)*XLOOKUP($M11,'Nature Editor'!$A:$A,'Nature Editor'!$D:$D,1))),def,IF(cat="Physical",FLOOR((FLOOR(((2*XLOOKUP('Boss Editor'!$C$4,'Pokemon Editor'!$A:$A,'Pokemon Editor'!$G:$G,0)+31+FLOOR('Boss Editor'!$I$4/4))*'Boss Editor'!$D$4)/100)+5)*XLOOKUP('Boss Editor'!$E$4,'Nature Editor'!$A:$A,'Nature Editor'!$C:$C,1)),FLOOR((FLOOR(((2*XLOOKUP('Boss Editor'!$C$4,'Pokemon Editor'!$A:$A,'Pokemon Editor'!$I:$I,0)+31+FLOOR('Boss Editor'!$K$4/4))*'Boss Editor'!$D$4)/100)+5)*XLOOKUP('Boss Editor'!$E$4,'Nature Editor'!$A:$A,'Nature Editor'!$E:$E,1))),stab,IF(OR(mtype=XLOOKUP($K11,'Pokemon Editor'!$A:$A,'Pokemon Editor'!$C:$C,""),mtype=XLOOKUP($K11,'Pokemon Editor'!$A:$A,'Pokemon Editor'!$D:$D,"")),1.5,1),eff,(INDEX('Type Chart'!$B:$S,MATCH(mtype,'Type Chart'!$A:$A,0),MATCH(XLOOKUP('Boss Editor'!$C$4,'Pokemon Editor'!$A:$A,'Pokemon Editor'!$C:$C,""),'Type Chart'!$B$1:$S$1,0))*IF(XLOOKUP('Boss Editor'!$C$4,'Pokemon Editor'!$A:$A,'Pokemon Editor'!$D:$D,"")="",1,INDEX('Type Chart'!$B:$S,MATCH(mtype,'Type Chart'!$A:$A,0),MATCH(XLOOKUP('Boss Editor'!$C$4,'Pokemon Editor'!$A:$A,'Pokemon Editor'!$D:$D,""),'Type Chart'!$B$1:$S$1,0)))),base,IF(OR(cat="Status",pow=0),0,FLOOR(FLOOR(FLOOR((2*$L11/5+2)*pow*atk/def)/50)+2)),modifier,stab*eff,FLOOR(base*modifier)),0) | W11: =IFERROR(LET(mtype,XLOOKUP($D11,'Move Editor'!$B:$B,'Move Editor'!$C:$C,""),cat,XLOOKUP($D11,'Move Editor'!$B:$B,'Move Editor'!$D:$D,""),pow,XLOOKUP($D11,'Move Editor'!$B:$B,'Move Editor'!$E:$E,0),acc,XLOOKUP($D11,'Move Editor'!$B:$B,'Move Editor'!$F:$F,100),atk,IF(cat="Physical",FLOOR((FLOOR(((2*XLOOKUP('Boss Editor'!$C$4,'Pokemon Editor'!$A:$A,'Pokemon Editor'!$F:$F,0)+31+FLOOR('Boss Editor'!$H$4/4))*'Boss Editor'!$D$4)/100)+5)*XLOOKUP('Boss Editor'!$E$4,'Nature Editor'!$A:$A,'Nature Editor'!$B:$B,1)),FLOOR((FLOOR(((2*XLOOKUP('Boss Editor'!$C$4,'Pokemon Editor'!$A:$A,'Pokemon Editor'!$H:$H,0)+31+FLOOR('Boss Editor'!$J$4/4))*'Boss Editor'!$D$4)/100)+5)*XLOOKUP('Boss Editor'!$E$4,'Nature Editor'!$A:$A,'Nature Editor'!$D:$D,1))),def,IF(cat="Physical",FLOOR((FLOOR(((2*XLOOKUP($K11,'Pokemon Editor'!$A:$A,'Pokemon Editor'!$G:$G,0)+31+FLOOR($Q11/4))*$L11)/100)+5)*XLOOKUP($M11,'Nature Editor'!$A:$A,'Nature Editor'!$C:$C,1)),FLOOR((FLOOR(((2*XLOOKUP($K11,'Pokemon Editor'!$A:$A,'Pokemon Editor'!$I:$I,0)+31+FLOOR($S11/4))*$L11)/100)+5)*XLOOKUP($M11,'Nature Editor'!$A:$A,'Nature Editor'!$E:$E,1))),stab,IF(OR(mtype=XLOOKUP('Boss Editor'!$C$4,'Pokemon Editor'!$A:$A,'Pokemon Editor'!$C:$C,""),mtype=XLOOKUP('Boss Editor'!$C$4,'Pokemon Editor'!$A:$A,'Pokemon Editor'!$D:$D,"")),1.5,1),eff,(INDEX('Type Chart'!$B:$S,MATCH(mtype,'Type Chart'!$A:$A,0),MATCH(XLOOKUP($K11,'Pokemon Editor'!$A:$A,'Pokemon Editor'!$C:$C,""),'Type Chart'!$B$1:$S$1,0))*IF(XLOOKUP($K11,'Pokemon Editor'!$A:$A,'Pokemon Editor'!$D:$D,"")="",1,INDEX('Type Chart'!$B:$S,MATCH(mtype,'Type Chart'!$A:$A,0),MATCH(XLOOKUP($K11,'Pokemon Editor'!$A:$A,'Pokemon Editor'!$D:$D,""),'Type Chart'!$B$1:$S$1,0)))),base,IF(OR(cat="Status",pow=0),0,FLOOR(FLOOR(FLOOR((2*'Boss Editor'!$D$4/5+2)*pow*atk/def)/50)+2)),modifier,stab*eff,FLOOR(base*modifier*0.85)),0) | X11: =IFERROR(LET(mtype,XLOOKUP($D11,'Move Editor'!$B:$B,'Move Editor'!$C:$C,""),cat,XLOOKUP($D11,'Move Editor'!$B:$B,'Move Editor'!$D:$D,""),pow,XLOOKUP($D11,'Move Editor'!$B:$B,'Move Editor'!$E:$E,0),acc,XLOOKUP($D11,'Move Editor'!$B:$B,'Move Editor'!$F:$F,100),atk,IF(cat="Physical",FLOOR((FLOOR(((2*XLOOKUP('Boss Editor'!$C$4,'Pokemon Editor'!$A:$A,'Pokemon Editor'!$F:$F,0)+31+FLOOR('Boss Editor'!$H$4/4))*'Boss Editor'!$D$4)/100)+5)*XLOOKUP('Boss Editor'!$E$4,'Nature Editor'!$A:$A,'Nature Editor'!$B:$B,1)),FLOOR((FLOOR(((2*XLOOKUP('Boss Editor'!$C$4,'Pokemon Editor'!$A:$A,'Pokemon Editor'!$H:$H,0)+31+FLOOR('Boss Editor'!$J$4/4))*'Boss Editor'!$D$4)/100)+5)*XLOOKUP('Boss Editor'!$E$4,'Nature Editor'!$A:$A,'Nature Editor'!$D:$D,1))),def,IF(cat="Physical",FLOOR((FLOOR(((2*XLOOKUP($K11,'Pokemon Editor'!$A:$A,'Pokemon Editor'!$G:$G,0)+31+FLOOR($Q11/4))*$L11)/100)+5)*XLOOKUP($M11,'Nature Editor'!$A:$A,'Nature Editor'!$C:$C,1)),FLOOR((FLOOR(((2*XLOOKUP($K11,'Pokemon Editor'!$A:$A,'Pokemon Editor'!$I:$I,0)+31+FLOOR($S11/4))*$L11)/100)+5)*XLOOKUP($M11,'Nature Editor'!$A:$A,'Nature Editor'!$E:$E,1))),stab,IF(OR(mtype=XLOOKUP('Boss Editor'!$C$4,'Pokemon Editor'!$A:$A,'Pokemon Editor'!$C:$C,""),mtype=XLOOKUP('Boss Editor'!$C$4,'Pokemon Editor'!$A:$A,'Pokemon Editor'!$D:$D,"")),1.5,1),eff,(INDEX('Type Chart'!$B:$S,MATCH(mtype,'Type Chart'!$A:$A,0),MATCH(XLOOKUP($K11,'Pokemon Editor'!$A:$A,'Pokemon Editor'!$C:$C,""),'Type Chart'!$B$1:$S$1,0))*IF(XLOOKUP($K11,'Pokemon Editor'!$A:$A,'Pokemon Editor'!$D:$D,"")="",1,INDEX('Type Chart'!$B:$S,MATCH(mtype,'Type Chart'!$A:$A,0),MATCH(XLOOKUP($K11,'Pokemon Editor'!$A:$A,'Pokemon Editor'!$D:$D,""),'Type Chart'!$B$1:$S$1,0)))),base,IF(OR(cat="Status",pow=0),0,FLOOR(FLOOR(FLOOR((2*'Boss Editor'!$D$4/5+2)*pow*atk/def)/50)+2)),modifier,stab*eff,FLOOR(base*modifier)),0) | Y11: SPECIES_LITLEO
A12: =XLOOKUP(K12,'Pokemon Editor'!$A:$A,'Pokemon Editor'!$B:$B,K12) | B12: =IF($Z12<>"",$Z12,IFERROR(INDEX(FILTER('Move Comparison'!$D$2:$D,'Move Comparison'!$Q$2:$Q=$Y12,'Move Comparison'!$M$2:$M=MAXIFS('Move Comparison'!$M$2:$M,'Move Comparison'!$Q$2:$Q,$Y12),'Move Comparison'!$D$2:$D<>""),1),"")) | C12: =IFERROR(LET(mtype,XLOOKUP($B12,'Move Editor'!$B:$B,'Move Editor'!$C:$C,""),cat,XLOOKUP($B12,'Move Editor'!$B:$B,'Move Editor'!$D:$D,""),pow,XLOOKUP($B12,'Move Editor'!$B:$B,'Move Editor'!$E:$E,0),acc,XLOOKUP($B12,'Move Editor'!$B:$B,'Move Editor'!$F:$F,100),atk,IF(cat="Physical",FLOOR((FLOOR(((2*XLOOKUP($K12,'Pokemon Editor'!$A:$A,'Pokemon Editor'!$F:$F,0)+31+FLOOR($P12/4))*$L12)/100)+5)*XLOOKUP($M12,'Nature Editor'!$A:$A,'Nature Editor'!$B:$B,1)),FLOOR((FLOOR(((2*XLOOKUP($K12,'Pokemon Editor'!$A:$A,'Pokemon Editor'!$H:$H,0)+31+FLOOR($R12/4))*$L12)/100)+5)*XLOOKUP($M12,'Nature Editor'!$A:$A,'Nature Editor'!$D:$D,1))),def,IF(cat="Physical",FLOOR((FLOOR(((2*XLOOKUP('Boss Editor'!$C$4,'Pokemon Editor'!$A:$A,'Pokemon Editor'!$G:$G,0)+31+FLOOR('Boss Editor'!$I$4/4))*'Boss Editor'!$D$4)/100)+5)*XLOOKUP('Boss Editor'!$E$4,'Nature Editor'!$A:$A,'Nature Editor'!$C:$C,1)),FLOOR((FLOOR(((2*XLOOKUP('Boss Editor'!$C$4,'Pokemon Editor'!$A:$A,'Pokemon Editor'!$I:$I,0)+31+FLOOR('Boss Editor'!$K$4/4))*'Boss Editor'!$D$4)/100)+5)*XLOOKUP('Boss Editor'!$E$4,'Nature Editor'!$A:$A,'Nature Editor'!$E:$E,1))),stab,IF(OR(mtype=XLOOKUP($K12,'Pokemon Editor'!$A:$A,'Pokemon Editor'!$C:$C,""),mtype=XLOOKUP($K12,'Pokemon Editor'!$A:$A,'Pokemon Editor'!$D:$D,"")),1.5,1),eff,(INDEX('Type Chart'!$B:$S,MATCH(mtype,'Type Chart'!$A:$A,0),MATCH(XLOOKUP('Boss Editor'!$C$4,'Pokemon Editor'!$A:$A,'Pokemon Editor'!$C:$C,""),'Type Chart'!$B$1:$S$1,0))*IF(XLOOKUP('Boss Editor'!$C$4,'Pokemon Editor'!$A:$A,'Pokemon Editor'!$D:$D,"")="",1,INDEX('Type Chart'!$B:$S,MATCH(mtype,'Type Chart'!$A:$A,0),MATCH(XLOOKUP('Boss Editor'!$C$4,'Pokemon Editor'!$A:$A,'Pokemon Editor'!$D:$D,""),'Type Chart'!$B$1:$S$1,0)))),base,IF(OR(cat="Status",pow=0),0,FLOOR(FLOOR(FLOOR((2*$L12/5+2)*pow*atk/def)/50)+2)),modifier,stab*eff,AVERAGE(ARRAYFORMULA(FLOOR(base*modifier*SEQUENCE(16,1,85,1)/100)))/(FLOOR(((2*XLOOKUP('Boss Editor'!$C$4,'Pokemon Editor'!$A:$A,'Pokemon Editor'!$E:$E,0)+31+FLOOR('Boss Editor'!$G$4/4))*'Boss Editor'!$D$4)/100)+'Boss Editor'!$D$4+10)),0) | D12: Acid | E12: =IFERROR(LET(mtype,XLOOKUP($D12,'Move Editor'!$B:$B,'Move Editor'!$C:$C,""),cat,XLOOKUP($D12,'Move Editor'!$B:$B,'Move Editor'!$D:$D,""),pow,XLOOKUP($D12,'Move Editor'!$B:$B,'Move Editor'!$E:$E,0),acc,XLOOKUP($D12,'Move Editor'!$B:$B,'Move Editor'!$F:$F,100),atk,IF(cat="Physical",FLOOR((FLOOR(((2*XLOOKUP('Boss Editor'!$C$4,'Pokemon Editor'!$A:$A,'Pokemon Editor'!$F:$F,0)+31+FLOOR('Boss Editor'!$H$4/4))*'Boss Editor'!$D$4)/100)+5)*XLOOKUP('Boss Editor'!$E$4,'Nature Editor'!$A:$A,'Nature Editor'!$B:$B,1)),FLOOR((FLOOR(((2*XLOOKUP('Boss Editor'!$C$4,'Pokemon Editor'!$A:$A,'Pokemon Editor'!$H:$H,0)+31+FLOOR('Boss Editor'!$J$4/4))*'Boss Editor'!$D$4)/100)+5)*XLOOKUP('Boss Editor'!$E$4,'Nature Editor'!$A:$A,'Nature Editor'!$D:$D,1))),def,IF(cat="Physical",FLOOR((FLOOR(((2*XLOOKUP($K12,'Pokemon Editor'!$A:$A,'Pokemon Editor'!$G:$G,0)+31+FLOOR($Q12/4))*$L12)/100)+5)*XLOOKUP($M12,'Nature Editor'!$A:$A,'Nature Editor'!$C:$C,1)),FLOOR((FLOOR(((2*XLOOKUP($K12,'Pokemon Editor'!$A:$A,'Pokemon Editor'!$I:$I,0)+31+FLOOR($S12/4))*$L12)/100)+5)*XLOOKUP($M12,'Nature Editor'!$A:$A,'Nature Editor'!$E:$E,1))),stab,IF(OR(mtype=XLOOKUP('Boss Editor'!$C$4,'Pokemon Editor'!$A:$A,'Pokemon Editor'!$C:$C,""),mtype=XLOOKUP('Boss Editor'!$C$4,'Pokemon Editor'!$A:$A,'Pokemon Editor'!$D:$D,"")),1.5,1),eff,(INDEX('Type Chart'!$B:$S,MATCH(mtype,'Type Chart'!$A:$A,0),MATCH(XLOOKUP($K12,'Pokemon Editor'!$A:$A,'Pokemon Editor'!$C:$C,""),'Type Chart'!$B$1:$S$1,0))*IF(XLOOKUP($K12,'Pokemon Editor'!$A:$A,'Pokemon Editor'!$D:$D,"")="",1,INDEX('Type Chart'!$B:$S,MATCH(mtype,'Type Chart'!$A:$A,0),MATCH(XLOOKUP($K12,'Pokemon Editor'!$A:$A,'Pokemon Editor'!$D:$D,""),'Type Chart'!$B$1:$S$1,0)))),base,IF(OR(cat="Status",pow=0),0,FLOOR(FLOOR(FLOOR((2*'Boss Editor'!$D$4/5+2)*pow*atk/def)/50)+2)),modifier,stab*eff,AVERAGE(ARRAYFORMULA(FLOOR(base*modifier*SEQUENCE(16,1,85,1)/100)))/(FLOOR(((2*XLOOKUP($K12,'Pokemon Editor'!$A:$A,'Pokemon Editor'!$E:$E,0)+31+FLOOR($O12/4))*$L12)/100)+$L12+10)),0) | F12: =FLOOR((FLOOR(((2*XLOOKUP($K12,'Pokemon Editor'!$A:$A,'Pokemon Editor'!$J:$J,0)+31+FLOOR($T12/4))*$L12)/100)+5)*XLOOKUP($M12,'Nature Editor'!$A:$A,'Nature Editor'!$F:$F,1)) | G12: =FLOOR((FLOOR(((2*XLOOKUP('Boss Editor'!$C$4,'Pokemon Editor'!$A:$A,'Pokemon Editor'!$J:$J,0)+31+FLOOR('Boss Editor'!$L$4/4))*'Boss Editor'!$D$4)/100)+5)*XLOOKUP('Boss Editor'!$E$4,'Nature Editor'!$A:$A,'Nature Editor'!$F:$F,1)) | H12: =IF(F12>G12,"Yes","No") | I12: =C12-E12 | J12: =IFS(AND(C12>=0.5,E12<0.5),"Dominant",AND(C12>=0.35,E12<0.75),"Strong",AND(C12>=0.25,E12<1),"Viable",AND(C12>=0.15,E12<1.25),"Risky",TRUE,"Poor") | K12: =REDUCE($Y12,SEQUENCE(2),LAMBDA(current_species,unused_step,IFERROR(INDEX(FILTER('Evolution Editor'!$D$2:$D,'Evolution Editor'!$A$2:$A=current_species,'Evolution Editor'!$F$2:$F=TRUE,'Evolution Editor'!$E$2:$E<=$L12),1),current_species))) | L12: 15 | M12: Neutral | N12: ABILITY_BLAZE | O12: 0 | P12: 0 | Q12: 0 | R12: 0 | S12: 0 | T12: 0 | U12: =IFERROR(LET(mtype,XLOOKUP($B12,'Move Editor'!$B:$B,'Move Editor'!$C:$C,""),cat,XLOOKUP($B12,'Move Editor'!$B:$B,'Move Editor'!$D:$D,""),pow,XLOOKUP($B12,'Move Editor'!$B:$B,'Move Editor'!$E:$E,0),acc,XLOOKUP($B12,'Move Editor'!$B:$B,'Move Editor'!$F:$F,100),atk,IF(cat="Physical",FLOOR((FLOOR(((2*XLOOKUP($K12,'Pokemon Editor'!$A:$A,'Pokemon Editor'!$F:$F,0)+31+FLOOR($P12/4))*$L12)/100)+5)*XLOOKUP($M12,'Nature Editor'!$A:$A,'Nature Editor'!$B:$B,1)),FLOOR((FLOOR(((2*XLOOKUP($K12,'Pokemon Editor'!$A:$A,'Pokemon Editor'!$H:$H,0)+31+FLOOR($R12/4))*$L12)/100)+5)*XLOOKUP($M12,'Nature Editor'!$A:$A,'Nature Editor'!$D:$D,1))),def,IF(cat="Physical",FLOOR((FLOOR(((2*XLOOKUP('Boss Editor'!$C$4,'Pokemon Editor'!$A:$A,'Pokemon Editor'!$G:$G,0)+31+FLOOR('Boss Editor'!$I$4/4))*'Boss Editor'!$D$4)/100)+5)*XLOOKUP('Boss Editor'!$E$4,'Nature Editor'!$A:$A,'Nature Editor'!$C:$C,1)),FLOOR((FLOOR(((2*XLOOKUP('Boss Editor'!$C$4,'Pokemon Editor'!$A:$A,'Pokemon Editor'!$I:$I,0)+31+FLOOR('Boss Editor'!$K$4/4))*'Boss Editor'!$D$4)/100)+5)*XLOOKUP('Boss Editor'!$E$4,'Nature Editor'!$A:$A,'Nature Editor'!$E:$E,1))),stab,IF(OR(mtype=XLOOKUP($K12,'Pokemon Editor'!$A:$A,'Pokemon Editor'!$C:$C,""),mtype=XLOOKUP($K12,'Pokemon Editor'!$A:$A,'Pokemon Editor'!$D:$D,"")),1.5,1),eff,(INDEX('Type Chart'!$B:$S,MATCH(mtype,'Type Chart'!$A:$A,0),MATCH(XLOOKUP('Boss Editor'!$C$4,'Pokemon Editor'!$A:$A,'Pokemon Editor'!$C:$C,""),'Type Chart'!$B$1:$S$1,0))*IF(XLOOKUP('Boss Editor'!$C$4,'Pokemon Editor'!$A:$A,'Pokemon Editor'!$D:$D,"")="",1,INDEX('Type Chart'!$B:$S,MATCH(mtype,'Type Chart'!$A:$A,0),MATCH(XLOOKUP('Boss Editor'!$C$4,'Pokemon Editor'!$A:$A,'Pokemon Editor'!$D:$D,""),'Type Chart'!$B$1:$S$1,0)))),base,IF(OR(cat="Status",pow=0),0,FLOOR(FLOOR(FLOOR((2*$L12/5+2)*pow*atk/def)/50)+2)),modifier,stab*eff,FLOOR(base*modifier*0.85)),0) | V12: =IFERROR(LET(mtype,XLOOKUP($B12,'Move Editor'!$B:$B,'Move Editor'!$C:$C,""),cat,XLOOKUP($B12,'Move Editor'!$B:$B,'Move Editor'!$D:$D,""),pow,XLOOKUP($B12,'Move Editor'!$B:$B,'Move Editor'!$E:$E,0),acc,XLOOKUP($B12,'Move Editor'!$B:$B,'Move Editor'!$F:$F,100),atk,IF(cat="Physical",FLOOR((FLOOR(((2*XLOOKUP($K12,'Pokemon Editor'!$A:$A,'Pokemon Editor'!$F:$F,0)+31+FLOOR($P12/4))*$L12)/100)+5)*XLOOKUP($M12,'Nature Editor'!$A:$A,'Nature Editor'!$B:$B,1)),FLOOR((FLOOR(((2*XLOOKUP($K12,'Pokemon Editor'!$A:$A,'Pokemon Editor'!$H:$H,0)+31+FLOOR($R12/4))*$L12)/100)+5)*XLOOKUP($M12,'Nature Editor'!$A:$A,'Nature Editor'!$D:$D,1))),def,IF(cat="Physical",FLOOR((FLOOR(((2*XLOOKUP('Boss Editor'!$C$4,'Pokemon Editor'!$A:$A,'Pokemon Editor'!$G:$G,0)+31+FLOOR('Boss Editor'!$I$4/4))*'Boss Editor'!$D$4)/100)+5)*XLOOKUP('Boss Editor'!$E$4,'Nature Editor'!$A:$A,'Nature Editor'!$C:$C,1)),FLOOR((FLOOR(((2*XLOOKUP('Boss Editor'!$C$4,'Pokemon Editor'!$A:$A,'Pokemon Editor'!$I:$I,0)+31+FLOOR('Boss Editor'!$K$4/4))*'Boss Editor'!$D$4)/100)+5)*XLOOKUP('Boss Editor'!$E$4,'Nature Editor'!$A:$A,'Nature Editor'!$E:$E,1))),stab,IF(OR(mtype=XLOOKUP($K12,'Pokemon Editor'!$A:$A,'Pokemon Editor'!$C:$C,""),mtype=XLOOKUP($K12,'Pokemon Editor'!$A:$A,'Pokemon Editor'!$D:$D,"")),1.5,1),eff,(INDEX('Type Chart'!$B:$S,MATCH(mtype,'Type Chart'!$A:$A,0),MATCH(XLOOKUP('Boss Editor'!$C$4,'Pokemon Editor'!$A:$A,'Pokemon Editor'!$C:$C,""),'Type Chart'!$B$1:$S$1,0))*IF(XLOOKUP('Boss Editor'!$C$4,'Pokemon Editor'!$A:$A,'Pokemon Editor'!$D:$D,"")="",1,INDEX('Type Chart'!$B:$S,MATCH(mtype,'Type Chart'!$A:$A,0),MATCH(XLOOKUP('Boss Editor'!$C$4,'Pokemon Editor'!$A:$A,'Pokemon Editor'!$D:$D,""),'Type Chart'!$B$1:$S$1,0)))),base,IF(OR(cat="Status",pow=0),0,FLOOR(FLOOR(FLOOR((2*$L12/5+2)*pow*atk/def)/50)+2)),modifier,stab*eff,FLOOR(base*modifier)),0) | W12: =IFERROR(LET(mtype,XLOOKUP($D12,'Move Editor'!$B:$B,'Move Editor'!$C:$C,""),cat,XLOOKUP($D12,'Move Editor'!$B:$B,'Move Editor'!$D:$D,""),pow,XLOOKUP($D12,'Move Editor'!$B:$B,'Move Editor'!$E:$E,0),acc,XLOOKUP($D12,'Move Editor'!$B:$B,'Move Editor'!$F:$F,100),atk,IF(cat="Physical",FLOOR((FLOOR(((2*XLOOKUP('Boss Editor'!$C$4,'Pokemon Editor'!$A:$A,'Pokemon Editor'!$F:$F,0)+31+FLOOR('Boss Editor'!$H$4/4))*'Boss Editor'!$D$4)/100)+5)*XLOOKUP('Boss Editor'!$E$4,'Nature Editor'!$A:$A,'Nature Editor'!$B:$B,1)),FLOOR((FLOOR(((2*XLOOKUP('Boss Editor'!$C$4,'Pokemon Editor'!$A:$A,'Pokemon Editor'!$H:$H,0)+31+FLOOR('Boss Editor'!$J$4/4))*'Boss Editor'!$D$4)/100)+5)*XLOOKUP('Boss Editor'!$E$4,'Nature Editor'!$A:$A,'Nature Editor'!$D:$D,1))),def,IF(cat="Physical",FLOOR((FLOOR(((2*XLOOKUP($K12,'Pokemon Editor'!$A:$A,'Pokemon Editor'!$G:$G,0)+31+FLOOR($Q12/4))*$L12)/100)+5)*XLOOKUP($M12,'Nature Editor'!$A:$A,'Nature Editor'!$C:$C,1)),FLOOR((FLOOR(((2*XLOOKUP($K12,'Pokemon Editor'!$A:$A,'Pokemon Editor'!$I:$I,0)+31+FLOOR($S12/4))*$L12)/100)+5)*XLOOKUP($M12,'Nature Editor'!$A:$A,'Nature Editor'!$E:$E,1))),stab,IF(OR(mtype=XLOOKUP('Boss Editor'!$C$4,'Pokemon Editor'!$A:$A,'Pokemon Editor'!$C:$C,""),mtype=XLOOKUP('Boss Editor'!$C$4,'Pokemon Editor'!$A:$A,'Pokemon Editor'!$D:$D,"")),1.5,1),eff,(INDEX('Type Chart'!$B:$S,MATCH(mtype,'Type Chart'!$A:$A,0),MATCH(XLOOKUP($K12,'Pokemon Editor'!$A:$A,'Pokemon Editor'!$C:$C,""),'Type Chart'!$B$1:$S$1,0))*IF(XLOOKUP($K12,'Pokemon Editor'!$A:$A,'Pokemon Editor'!$D:$D,"")="",1,INDEX('Type Chart'!$B:$S,MATCH(mtype,'Type Chart'!$A:$A,0),MATCH(XLOOKUP($K12,'Pokemon Editor'!$A:$A,'Pokemon Editor'!$D:$D,""),'Type Chart'!$B$1:$S$1,0)))),base,IF(OR(cat="Status",pow=0),0,FLOOR(FLOOR(FLOOR((2*'Boss Editor'!$D$4/5+2)*pow*atk/def)/50)+2)),modifier,stab*eff,FLOOR(base*modifier*0.85)),0) | X12: =IFERROR(LET(mtype,XLOOKUP($D12,'Move Editor'!$B:$B,'Move Editor'!$C:$C,""),cat,XLOOKUP($D12,'Move Editor'!$B:$B,'Move Editor'!$D:$D,""),pow,XLOOKUP($D12,'Move Editor'!$B:$B,'Move Editor'!$E:$E,0),acc,XLOOKUP($D12,'Move Editor'!$B:$B,'Move Editor'!$F:$F,100),atk,IF(cat="Physical",FLOOR((FLOOR(((2*XLOOKUP('Boss Editor'!$C$4,'Pokemon Editor'!$A:$A,'Pokemon Editor'!$F:$F,0)+31+FLOOR('Boss Editor'!$H$4/4))*'Boss Editor'!$D$4)/100)+5)*XLOOKUP('Boss Editor'!$E$4,'Nature Editor'!$A:$A,'Nature Editor'!$B:$B,1)),FLOOR((FLOOR(((2*XLOOKUP('Boss Editor'!$C$4,'Pokemon Editor'!$A:$A,'Pokemon Editor'!$H:$H,0)+31+FLOOR('Boss Editor'!$J$4/4))*'Boss Editor'!$D$4)/100)+5)*XLOOKUP('Boss Editor'!$E$4,'Nature Editor'!$A:$A,'Nature Editor'!$D:$D,1))),def,IF(cat="Physical",FLOOR((FLOOR(((2*XLOOKUP($K12,'Pokemon Editor'!$A:$A,'Pokemon Editor'!$G:$G,0)+31+FLOOR($Q12/4))*$L12)/100)+5)*XLOOKUP($M12,'Nature Editor'!$A:$A,'Nature Editor'!$C:$C,1)),FLOOR((FLOOR(((2*XLOOKUP($K12,'Pokemon Editor'!$A:$A,'Pokemon Editor'!$I:$I,0)+31+FLOOR($S12/4))*$L12)/100)+5)*XLOOKUP($M12,'Nature Editor'!$A:$A,'Nature Editor'!$E:$E,1))),stab,IF(OR(mtype=XLOOKUP('Boss Editor'!$C$4,'Pokemon Editor'!$A:$A,'Pokemon Editor'!$C:$C,""),mtype=XLOOKUP('Boss Editor'!$C$4,'Pokemon Editor'!$A:$A,'Pokemon Editor'!$D:$D,"")),1.5,1),eff,(INDEX('Type Chart'!$B:$S,MATCH(mtype,'Type Chart'!$A:$A,0),MATCH(XLOOKUP($K12,'Pokemon Editor'!$A:$A,'Pokemon Editor'!$C:$C,""),'Type Chart'!$B$1:$S$1,0))*IF(XLOOKUP($K12,'Pokemon Editor'!$A:$A,'Pokemon Editor'!$D:$D,"")="",1,INDEX('Type Chart'!$B:$S,MATCH(mtype,'Type Chart'!$A:$A,0),MATCH(XLOOKUP($K12,'Pokemon Editor'!$A:$A,'Pokemon Editor'!$D:$D,""),'Type Chart'!$B$1:$S$1,0)))),base,IF(OR(cat="Status",pow=0),0,FLOOR(FLOOR(FLOOR((2*'Boss Editor'!$D$4/5+2)*pow*atk/def)/50)+2)),modifier,stab*eff,FLOOR(base*modifier)),0) | Y12: SPECIES_TORCHIC
A13: =XLOOKUP(K13,'Pokemon Editor'!$A:$A,'Pokemon Editor'!$B:$B,K13) | B13: =IF($Z13<>"",$Z13,IFERROR(INDEX(FILTER('Move Comparison'!$D$2:$D,'Move Comparison'!$Q$2:$Q=$Y13,'Move Comparison'!$M$2:$M=MAXIFS('Move Comparison'!$M$2:$M,'Move Comparison'!$Q$2:$Q,$Y13),'Move Comparison'!$D$2:$D<>""),1),"")) | C13: =IFERROR(LET(mtype,XLOOKUP($B13,'Move Editor'!$B:$B,'Move Editor'!$C:$C,""),cat,XLOOKUP($B13,'Move Editor'!$B:$B,'Move Editor'!$D:$D,""),pow,XLOOKUP($B13,'Move Editor'!$B:$B,'Move Editor'!$E:$E,0),acc,XLOOKUP($B13,'Move Editor'!$B:$B,'Move Editor'!$F:$F,100),atk,IF(cat="Physical",FLOOR((FLOOR(((2*XLOOKUP($K13,'Pokemon Editor'!$A:$A,'Pokemon Editor'!$F:$F,0)+31+FLOOR($P13/4))*$L13)/100)+5)*XLOOKUP($M13,'Nature Editor'!$A:$A,'Nature Editor'!$B:$B,1)),FLOOR((FLOOR(((2*XLOOKUP($K13,'Pokemon Editor'!$A:$A,'Pokemon Editor'!$H:$H,0)+31+FLOOR($R13/4))*$L13)/100)+5)*XLOOKUP($M13,'Nature Editor'!$A:$A,'Nature Editor'!$D:$D,1))),def,IF(cat="Physical",FLOOR((FLOOR(((2*XLOOKUP('Boss Editor'!$C$4,'Pokemon Editor'!$A:$A,'Pokemon Editor'!$G:$G,0)+31+FLOOR('Boss Editor'!$I$4/4))*'Boss Editor'!$D$4)/100)+5)*XLOOKUP('Boss Editor'!$E$4,'Nature Editor'!$A:$A,'Nature Editor'!$C:$C,1)),FLOOR((FLOOR(((2*XLOOKUP('Boss Editor'!$C$4,'Pokemon Editor'!$A:$A,'Pokemon Editor'!$I:$I,0)+31+FLOOR('Boss Editor'!$K$4/4))*'Boss Editor'!$D$4)/100)+5)*XLOOKUP('Boss Editor'!$E$4,'Nature Editor'!$A:$A,'Nature Editor'!$E:$E,1))),stab,IF(OR(mtype=XLOOKUP($K13,'Pokemon Editor'!$A:$A,'Pokemon Editor'!$C:$C,""),mtype=XLOOKUP($K13,'Pokemon Editor'!$A:$A,'Pokemon Editor'!$D:$D,"")),1.5,1),eff,(INDEX('Type Chart'!$B:$S,MATCH(mtype,'Type Chart'!$A:$A,0),MATCH(XLOOKUP('Boss Editor'!$C$4,'Pokemon Editor'!$A:$A,'Pokemon Editor'!$C:$C,""),'Type Chart'!$B$1:$S$1,0))*IF(XLOOKUP('Boss Editor'!$C$4,'Pokemon Editor'!$A:$A,'Pokemon Editor'!$D:$D,"")="",1,INDEX('Type Chart'!$B:$S,MATCH(mtype,'Type Chart'!$A:$A,0),MATCH(XLOOKUP('Boss Editor'!$C$4,'Pokemon Editor'!$A:$A,'Pokemon Editor'!$D:$D,""),'Type Chart'!$B$1:$S$1,0)))),base,IF(OR(cat="Status",pow=0),0,FLOOR(FLOOR(FLOOR((2*$L13/5+2)*pow*atk/def)/50)+2)),modifier,stab*eff,AVERAGE(ARRAYFORMULA(FLOOR(base*modifier*SEQUENCE(16,1,85,1)/100)))/(FLOOR(((2*XLOOKUP('Boss Editor'!$C$4,'Pokemon Editor'!$A:$A,'Pokemon Editor'!$E:$E,0)+31+FLOOR('Boss Editor'!$G$4/4))*'Boss Editor'!$D$4)/100)+'Boss Editor'!$D$4+10)),0) | D13: Astonish | E13: =IFERROR(LET(mtype,XLOOKUP($D13,'Move Editor'!$B:$B,'Move Editor'!$C:$C,""),cat,XLOOKUP($D13,'Move Editor'!$B:$B,'Move Editor'!$D:$D,""),pow,XLOOKUP($D13,'Move Editor'!$B:$B,'Move Editor'!$E:$E,0),acc,XLOOKUP($D13,'Move Editor'!$B:$B,'Move Editor'!$F:$F,100),atk,IF(cat="Physical",FLOOR((FLOOR(((2*XLOOKUP('Boss Editor'!$C$4,'Pokemon Editor'!$A:$A,'Pokemon Editor'!$F:$F,0)+31+FLOOR('Boss Editor'!$H$4/4))*'Boss Editor'!$D$4)/100)+5)*XLOOKUP('Boss Editor'!$E$4,'Nature Editor'!$A:$A,'Nature Editor'!$B:$B,1)),FLOOR((FLOOR(((2*XLOOKUP('Boss Editor'!$C$4,'Pokemon Editor'!$A:$A,'Pokemon Editor'!$H:$H,0)+31+FLOOR('Boss Editor'!$J$4/4))*'Boss Editor'!$D$4)/100)+5)*XLOOKUP('Boss Editor'!$E$4,'Nature Editor'!$A:$A,'Nature Editor'!$D:$D,1))),def,IF(cat="Physical",FLOOR((FLOOR(((2*XLOOKUP($K13,'Pokemon Editor'!$A:$A,'Pokemon Editor'!$G:$G,0)+31+FLOOR($Q13/4))*$L13)/100)+5)*XLOOKUP($M13,'Nature Editor'!$A:$A,'Nature Editor'!$C:$C,1)),FLOOR((FLOOR(((2*XLOOKUP($K13,'Pokemon Editor'!$A:$A,'Pokemon Editor'!$I:$I,0)+31+FLOOR($S13/4))*$L13)/100)+5)*XLOOKUP($M13,'Nature Editor'!$A:$A,'Nature Editor'!$E:$E,1))),stab,IF(OR(mtype=XLOOKUP('Boss Editor'!$C$4,'Pokemon Editor'!$A:$A,'Pokemon Editor'!$C:$C,""),mtype=XLOOKUP('Boss Editor'!$C$4,'Pokemon Editor'!$A:$A,'Pokemon Editor'!$D:$D,"")),1.5,1),eff,(INDEX('Type Chart'!$B:$S,MATCH(mtype,'Type Chart'!$A:$A,0),MATCH(XLOOKUP($K13,'Pokemon Editor'!$A:$A,'Pokemon Editor'!$C:$C,""),'Type Chart'!$B$1:$S$1,0))*IF(XLOOKUP($K13,'Pokemon Editor'!$A:$A,'Pokemon Editor'!$D:$D,"")="",1,INDEX('Type Chart'!$B:$S,MATCH(mtype,'Type Chart'!$A:$A,0),MATCH(XLOOKUP($K13,'Pokemon Editor'!$A:$A,'Pokemon Editor'!$D:$D,""),'Type Chart'!$B$1:$S$1,0)))),base,IF(OR(cat="Status",pow=0),0,FLOOR(FLOOR(FLOOR((2*'Boss Editor'!$D$4/5+2)*pow*atk/def)/50)+2)),modifier,stab*eff,AVERAGE(ARRAYFORMULA(FLOOR(base*modifier*SEQUENCE(16,1,85,1)/100)))/(FLOOR(((2*XLOOKUP($K13,'Pokemon Editor'!$A:$A,'Pokemon Editor'!$E:$E,0)+31+FLOOR($O13/4))*$L13)/100)+$L13+10)),0) | F13: =FLOOR((FLOOR(((2*XLOOKUP($K13,'Pokemon Editor'!$A:$A,'Pokemon Editor'!$J:$J,0)+31+FLOOR($T13/4))*$L13)/100)+5)*XLOOKUP($M13,'Nature Editor'!$A:$A,'Nature Editor'!$F:$F,1)) | G13: =FLOOR((FLOOR(((2*XLOOKUP('Boss Editor'!$C$4,'Pokemon Editor'!$A:$A,'Pokemon Editor'!$J:$J,0)+31+FLOOR('Boss Editor'!$L$4/4))*'Boss Editor'!$D$4)/100)+5)*XLOOKUP('Boss Editor'!$E$4,'Nature Editor'!$A:$A,'Nature Editor'!$F:$F,1)) | H13: =IF(F13>G13,"Yes","No") | I13: =C13-E13 | J13: =IFS(AND(C13>=0.5,E13<0.5),"Dominant",AND(C13>=0.35,E13<0.75),"Strong",AND(C13>=0.25,E13<1),"Viable",AND(C13>=0.15,E13<1.25),"Risky",TRUE,"Poor") | K13: =REDUCE($Y13,SEQUENCE(2),LAMBDA(current_species,unused_step,IFERROR(INDEX(FILTER('Evolution Editor'!$D$2:$D,'Evolution Editor'!$A$2:$A=current_species,'Evolution Editor'!$F$2:$F=TRUE,'Evolution Editor'!$E$2:$E<=$L13),1),current_species))) | L13: 15 | M13: Neutral | N13: ABILITY_NATURAL_CURE | O13: 0 | P13: 0 | Q13: 0 | R13: 0 | S13: 0 | T13: 0 | U13: =IFERROR(LET(mtype,XLOOKUP($B13,'Move Editor'!$B:$B,'Move Editor'!$C:$C,""),cat,XLOOKUP($B13,'Move Editor'!$B:$B,'Move Editor'!$D:$D,""),pow,XLOOKUP($B13,'Move Editor'!$B:$B,'Move Editor'!$E:$E,0),acc,XLOOKUP($B13,'Move Editor'!$B:$B,'Move Editor'!$F:$F,100),atk,IF(cat="Physical",FLOOR((FLOOR(((2*XLOOKUP($K13,'Pokemon Editor'!$A:$A,'Pokemon Editor'!$F:$F,0)+31+FLOOR($P13/4))*$L13)/100)+5)*XLOOKUP($M13,'Nature Editor'!$A:$A,'Nature Editor'!$B:$B,1)),FLOOR((FLOOR(((2*XLOOKUP($K13,'Pokemon Editor'!$A:$A,'Pokemon Editor'!$H:$H,0)+31+FLOOR($R13/4))*$L13)/100)+5)*XLOOKUP($M13,'Nature Editor'!$A:$A,'Nature Editor'!$D:$D,1))),def,IF(cat="Physical",FLOOR((FLOOR(((2*XLOOKUP('Boss Editor'!$C$4,'Pokemon Editor'!$A:$A,'Pokemon Editor'!$G:$G,0)+31+FLOOR('Boss Editor'!$I$4/4))*'Boss Editor'!$D$4)/100)+5)*XLOOKUP('Boss Editor'!$E$4,'Nature Editor'!$A:$A,'Nature Editor'!$C:$C,1)),FLOOR((FLOOR(((2*XLOOKUP('Boss Editor'!$C$4,'Pokemon Editor'!$A:$A,'Pokemon Editor'!$I:$I,0)+31+FLOOR('Boss Editor'!$K$4/4))*'Boss Editor'!$D$4)/100)+5)*XLOOKUP('Boss Editor'!$E$4,'Nature Editor'!$A:$A,'Nature Editor'!$E:$E,1))),stab,IF(OR(mtype=XLOOKUP($K13,'Pokemon Editor'!$A:$A,'Pokemon Editor'!$C:$C,""),mtype=XLOOKUP($K13,'Pokemon Editor'!$A:$A,'Pokemon Editor'!$D:$D,"")),1.5,1),eff,(INDEX('Type Chart'!$B:$S,MATCH(mtype,'Type Chart'!$A:$A,0),MATCH(XLOOKUP('Boss Editor'!$C$4,'Pokemon Editor'!$A:$A,'Pokemon Editor'!$C:$C,""),'Type Chart'!$B$1:$S$1,0))*IF(XLOOKUP('Boss Editor'!$C$4,'Pokemon Editor'!$A:$A,'Pokemon Editor'!$D:$D,"")="",1,INDEX('Type Chart'!$B:$S,MATCH(mtype,'Type Chart'!$A:$A,0),MATCH(XLOOKUP('Boss Editor'!$C$4,'Pokemon Editor'!$A:$A,'Pokemon Editor'!$D:$D,""),'Type Chart'!$B$1:$S$1,0)))),base,IF(OR(cat="Status",pow=0),0,FLOOR(FLOOR(FLOOR((2*$L13/5+2)*pow*atk/def)/50)+2)),modifier,stab*eff,FLOOR(base*modifier*0.85)),0) | V13: =IFERROR(LET(mtype,XLOOKUP($B13,'Move Editor'!$B:$B,'Move Editor'!$C:$C,""),cat,XLOOKUP($B13,'Move Editor'!$B:$B,'Move Editor'!$D:$D,""),pow,XLOOKUP($B13,'Move Editor'!$B:$B,'Move Editor'!$E:$E,0),acc,XLOOKUP($B13,'Move Editor'!$B:$B,'Move Editor'!$F:$F,100),atk,IF(cat="Physical",FLOOR((FLOOR(((2*XLOOKUP($K13,'Pokemon Editor'!$A:$A,'Pokemon Editor'!$F:$F,0)+31+FLOOR($P13/4))*$L13)/100)+5)*XLOOKUP($M13,'Nature Editor'!$A:$A,'Nature Editor'!$B:$B,1)),FLOOR((FLOOR(((2*XLOOKUP($K13,'Pokemon Editor'!$A:$A,'Pokemon Editor'!$H:$H,0)+31+FLOOR($R13/4))*$L13)/100)+5)*XLOOKUP($M13,'Nature Editor'!$A:$A,'Nature Editor'!$D:$D,1))),def,IF(cat="Physical",FLOOR((FLOOR(((2*XLOOKUP('Boss Editor'!$C$4,'Pokemon Editor'!$A:$A,'Pokemon Editor'!$G:$G,0)+31+FLOOR('Boss Editor'!$I$4/4))*'Boss Editor'!$D$4)/100)+5)*XLOOKUP('Boss Editor'!$E$4,'Nature Editor'!$A:$A,'Nature Editor'!$C:$C,1)),FLOOR((FLOOR(((2*XLOOKUP('Boss Editor'!$C$4,'Pokemon Editor'!$A:$A,'Pokemon Editor'!$I:$I,0)+31+FLOOR('Boss Editor'!$K$4/4))*'Boss Editor'!$D$4)/100)+5)*XLOOKUP('Boss Editor'!$E$4,'Nature Editor'!$A:$A,'Nature Editor'!$E:$E,1))),stab,IF(OR(mtype=XLOOKUP($K13,'Pokemon Editor'!$A:$A,'Pokemon Editor'!$C:$C,""),mtype=XLOOKUP($K13,'Pokemon Editor'!$A:$A,'Pokemon Editor'!$D:$D,"")),1.5,1),eff,(INDEX('Type Chart'!$B:$S,MATCH(mtype,'Type Chart'!$A:$A,0),MATCH(XLOOKUP('Boss Editor'!$C$4,'Pokemon Editor'!$A:$A,'Pokemon Editor'!$C:$C,""),'Type Chart'!$B$1:$S$1,0))*IF(XLOOKUP('Boss Editor'!$C$4,'Pokemon Editor'!$A:$A,'Pokemon Editor'!$D:$D,"")="",1,INDEX('Type Chart'!$B:$S,MATCH(mtype,'Type Chart'!$A:$A,0),MATCH(XLOOKUP('Boss Editor'!$C$4,'Pokemon Editor'!$A:$A,'Pokemon Editor'!$D:$D,""),'Type Chart'!$B$1:$S$1,0)))),base,IF(OR(cat="Status",pow=0),0,FLOOR(FLOOR(FLOOR((2*$L13/5+2)*pow*atk/def)/50)+2)),modifier,stab*eff,FLOOR(base*modifier)),0) | W13: =IFERROR(LET(mtype,XLOOKUP($D13,'Move Editor'!$B:$B,'Move Editor'!$C:$C,""),cat,XLOOKUP($D13,'Move Editor'!$B:$B,'Move Editor'!$D:$D,""),pow,XLOOKUP($D13,'Move Editor'!$B:$B,'Move Editor'!$E:$E,0),acc,XLOOKUP($D13,'Move Editor'!$B:$B,'Move Editor'!$F:$F,100),atk,IF(cat="Physical",FLOOR((FLOOR(((2*XLOOKUP('Boss Editor'!$C$4,'Pokemon Editor'!$A:$A,'Pokemon Editor'!$F:$F,0)+31+FLOOR('Boss Editor'!$H$4/4))*'Boss Editor'!$D$4)/100)+5)*XLOOKUP('Boss Editor'!$E$4,'Nature Editor'!$A:$A,'Nature Editor'!$B:$B,1)),FLOOR((FLOOR(((2*XLOOKUP('Boss Editor'!$C$4,'Pokemon Editor'!$A:$A,'Pokemon Editor'!$H:$H,0)+31+FLOOR('Boss Editor'!$J$4/4))*'Boss Editor'!$D$4)/100)+5)*XLOOKUP('Boss Editor'!$E$4,'Nature Editor'!$A:$A,'Nature Editor'!$D:$D,1))),def,IF(cat="Physical",FLOOR((FLOOR(((2*XLOOKUP($K13,'Pokemon Editor'!$A:$A,'Pokemon Editor'!$G:$G,0)+31+FLOOR($Q13/4))*$L13)/100)+5)*XLOOKUP($M13,'Nature Editor'!$A:$A,'Nature Editor'!$C:$C,1)),FLOOR((FLOOR(((2*XLOOKUP($K13,'Pokemon Editor'!$A:$A,'Pokemon Editor'!$I:$I,0)+31+FLOOR($S13/4))*$L13)/100)+5)*XLOOKUP($M13,'Nature Editor'!$A:$A,'Nature Editor'!$E:$E,1))),stab,IF(OR(mtype=XLOOKUP('Boss Editor'!$C$4,'Pokemon Editor'!$A:$A,'Pokemon Editor'!$C:$C,""),mtype=XLOOKUP('Boss Editor'!$C$4,'Pokemon Editor'!$A:$A,'Pokemon Editor'!$D:$D,"")),1.5,1),eff,(INDEX('Type Chart'!$B:$S,MATCH(mtype,'Type Chart'!$A:$A,0),MATCH(XLOOKUP($K13,'Pokemon Editor'!$A:$A,'Pokemon Editor'!$C:$C,""),'Type Chart'!$B$1:$S$1,0))*IF(XLOOKUP($K13,'Pokemon Editor'!$A:$A,'Pokemon Editor'!$D:$D,"")="",1,INDEX('Type Chart'!$B:$S,MATCH(mtype,'Type Chart'!$A:$A,0),MATCH(XLOOKUP($K13,'Pokemon Editor'!$A:$A,'Pokemon Editor'!$D:$D,""),'Type Chart'!$B$1:$S$1,0)))),base,IF(OR(cat="Status",pow=0),0,FLOOR(FLOOR(FLOOR((2*'Boss Editor'!$D$4/5+2)*pow*atk/def)/50)+2)),modifier,stab*eff,FLOOR(base*modifier*0.85)),0) | X13: =IFERROR(LET(mtype,XLOOKUP($D13,'Move Editor'!$B:$B,'Move Editor'!$C:$C,""),cat,XLOOKUP($D13,'Move Editor'!$B:$B,'Move Editor'!$D:$D,""),pow,XLOOKUP($D13,'Move Editor'!$B:$B,'Move Editor'!$E:$E,0),acc,XLOOKUP($D13,'Move Editor'!$B:$B,'Move Editor'!$F:$F,100),atk,IF(cat="Physical",FLOOR((FLOOR(((2*XLOOKUP('Boss Editor'!$C$4,'Pokemon Editor'!$A:$A,'Pokemon Editor'!$F:$F,0)+31+FLOOR('Boss Editor'!$H$4/4))*'Boss Editor'!$D$4)/100)+5)*XLOOKUP('Boss Editor'!$E$4,'Nature Editor'!$A:$A,'Nature Editor'!$B:$B,1)),FLOOR((FLOOR(((2*XLOOKUP('Boss Editor'!$C$4,'Pokemon Editor'!$A:$A,'Pokemon Editor'!$H:$H,0)+31+FLOOR('Boss Editor'!$J$4/4))*'Boss Editor'!$D$4)/100)+5)*XLOOKUP('Boss Editor'!$E$4,'Nature Editor'!$A:$A,'Nature Editor'!$D:$D,1))),def,IF(cat="Physical",FLOOR((FLOOR(((2*XLOOKUP($K13,'Pokemon Editor'!$A:$A,'Pokemon Editor'!$G:$G,0)+31+FLOOR($Q13/4))*$L13)/100)+5)*XLOOKUP($M13,'Nature Editor'!$A:$A,'Nature Editor'!$C:$C,1)),FLOOR((FLOOR(((2*XLOOKUP($K13,'Pokemon Editor'!$A:$A,'Pokemon Editor'!$I:$I,0)+31+FLOOR($S13/4))*$L13)/100)+5)*XLOOKUP($M13,'Nature Editor'!$A:$A,'Nature Editor'!$E:$E,1))),stab,IF(OR(mtype=XLOOKUP('Boss Editor'!$C$4,'Pokemon Editor'!$A:$A,'Pokemon Editor'!$C:$C,""),mtype=XLOOKUP('Boss Editor'!$C$4,'Pokemon Editor'!$A:$A,'Pokemon Editor'!$D:$D,"")),1.5,1),eff,(INDEX('Type Chart'!$B:$S,MATCH(mtype,'Type Chart'!$A:$A,0),MATCH(XLOOKUP($K13,'Pokemon Editor'!$A:$A,'Pokemon Editor'!$C:$C,""),'Type Chart'!$B$1:$S$1,0))*IF(XLOOKUP($K13,'Pokemon Editor'!$A:$A,'Pokemon Editor'!$D:$D,"")="",1,INDEX('Type Chart'!$B:$S,MATCH(mtype,'Type Chart'!$A:$A,0),MATCH(XLOOKUP($K13,'Pokemon Editor'!$A:$A,'Pokemon Editor'!$D:$D,""),'Type Chart'!$B$1:$S$1,0)))),base,IF(OR(cat="Status",pow=0),0,FLOOR(FLOOR(FLOOR((2*'Boss Editor'!$D$4/5+2)*pow*atk/def)/50)+2)),modifier,stab*eff,FLOOR(base*modifier)),0) | Y13: SPECIES_BUDEW
... A33: =XLOOKUP(K33,'Pokemon Editor'!$A:$A,'Pokemon Editor'!$B:$B,K33) | B33: =IF($Z33<>"",$Z33,IFERROR(INDEX(FILTER('Move Comparison'!$D$2:$D,'Move Comparison'!$Q$2:$Q=$Y33,'Move Comparison'!$M$2:$M=MAXIFS('Move Comparison'!$M$2:$M,'Move Comparison'!$Q$2:$Q,$Y33),'Move Comparison'!$D$2:$D<>""),1),"")) | C33: =IFERROR(LET(mtype,XLOOKUP($B33,'Move Editor'!$B:$B,'Move Editor'!$C:$C,""),cat,XLOOKUP($B33,'Move Editor'!$B:$B,'Move Editor'!$D:$D,""),pow,XLOOKUP($B33,'Move Editor'!$B:$B,'Move Editor'!$E:$E,0),acc,XLOOKUP($B33,'Move Editor'!$B:$B,'Move Editor'!$F:$F,100),atk,IF(cat="Physical",FLOOR((FLOOR(((2*XLOOKUP($K33,'Pokemon Editor'!$A:$A,'Pokemon Editor'!$F:$F,0)+31+FLOOR($P33/4))*$L33)/100)+5)*XLOOKUP($M33,'Nature Editor'!$A:$A,'Nature Editor'!$B:$B,1)),FLOOR((FLOOR(((2*XLOOKUP($K33,'Pokemon Editor'!$A:$A,'Pokemon Editor'!$H:$H,0)+31+FLOOR($R33/4))*$L33)/100)+5)*XLOOKUP($M33,'Nature Editor'!$A:$A,'Nature Editor'!$D:$D,1))),def,IF(cat="Physical",FLOOR((FLOOR(((2*XLOOKUP('Boss Editor'!$C$4,'Pokemon Editor'!$A:$A,'Pokemon Editor'!$G:$G,0)+31+FLOOR('Boss Editor'!$I$4/4))*'Boss Editor'!$D$4)/100)+5)*XLOOKUP('Boss Editor'!$E$4,'Nature Editor'!$A:$A,'Nature Editor'!$C:$C,1)),FLOOR((FLOOR(((2*XLOOKUP('Boss Editor'!$C$4,'Pokemon Editor'!$A:$A,'Pokemon Editor'!$I:$I,0)+31+FLOOR('Boss Editor'!$K$4/4))*'Boss Editor'!$D$4)/100)+5)*XLOOKUP('Boss Editor'!$E$4,'Nature Editor'!$A:$A,'Nature Editor'!$E:$E,1))),stab,IF(OR(mtype=XLOOKUP($K33,'Pokemon Editor'!$A:$A,'Pokemon Editor'!$C:$C,""),mtype=XLOOKUP($K33,'Pokemon Editor'!$A:$A,'Pokemon Editor'!$D:$D,"")),1.5,1),eff,(INDEX('Type Chart'!$B:$S,MATCH(mtype,'Type Chart'!$A:$A,0),MATCH(XLOOKUP('Boss Editor'!$C$4,'Pokemon Editor'!$A:$A,'Pokemon Editor'!$C:$C,""),'Type Chart'!$B$1:$S$1,0))*IF(XLOOKUP('Boss Editor'!$C$4,'Pokemon Editor'!$A:$A,'Pokemon Editor'!$D:$D,"")="",1,INDEX('Type Chart'!$B:$S,MATCH(mtype,'Type Chart'!$A:$A,0),MATCH(XLOOKUP('Boss Editor'!$C$4,'Pokemon Editor'!$A:$A,'Pokemon Editor'!$D:$D,""),'Type Chart'!$B$1:$S$1,0)))),base,IF(OR(cat="Status",pow=0),0,FLOOR(FLOOR(FLOOR((2*$L33/5+2)*pow*atk/def)/50)+2)),modifier,stab*eff,AVERAGE(ARRAYFORMULA(FLOOR(base*modifier*SEQUENCE(16,1,85,1)/100)))/(FLOOR(((2*XLOOKUP('Boss Editor'!$C$4,'Pokemon Editor'!$A:$A,'Pokemon Editor'!$E:$E,0)+31+FLOOR('Boss Editor'!$G$4/4))*'Boss Editor'!$D$4)/100)+'Boss Editor'!$D$4+10)),0) | D33: Acid | E33: =IFERROR(LET(mtype,XLOOKUP($D33,'Move Editor'!$B:$B,'Move Editor'!$C:$C,""),cat,XLOOKUP($D33,'Move Editor'!$B:$B,'Move Editor'!$D:$D,""),pow,XLOOKUP($D33,'Move Editor'!$B:$B,'Move Editor'!$E:$E,0),acc,XLOOKUP($D33,'Move Editor'!$B:$B,'Move Editor'!$F:$F,100),atk,IF(cat="Physical",FLOOR((FLOOR(((2*XLOOKUP('Boss Editor'!$C$4,'Pokemon Editor'!$A:$A,'Pokemon Editor'!$F:$F,0)+31+FLOOR('Boss Editor'!$H$4/4))*'Boss Editor'!$D$4)/100)+5)*XLOOKUP('Boss Editor'!$E$4,'Nature Editor'!$A:$A,'Nature Editor'!$B:$B,1)),FLOOR((FLOOR(((2*XLOOKUP('Boss Editor'!$C$4,'Pokemon Editor'!$A:$A,'Pokemon Editor'!$H:$H,0)+31+FLOOR('Boss Editor'!$J$4/4))*'Boss Editor'!$D$4)/100)+5)*XLOOKUP('Boss Editor'!$E$4,'Nature Editor'!$A:$A,'Nature Editor'!$D:$D,1))),def,IF(cat="Physical",FLOOR((FLOOR(((2*XLOOKUP($K33,'Pokemon Editor'!$A:$A,'Pokemon Editor'!$G:$G,0)+31+FLOOR($Q33/4))*$L33)/100)+5)*XLOOKUP($M33,'Nature Editor'!$A:$A,'Nature Editor'!$C:$C,1)),FLOOR((FLOOR(((2*XLOOKUP($K33,'Pokemon Editor'!$A:$A,'Pokemon Editor'!$I:$I,0)+31+FLOOR($S33/4))*$L33)/100)+5)*XLOOKUP($M33,'Nature Editor'!$A:$A,'Nature Editor'!$E:$E,1))),stab,IF(OR(mtype=XLOOKUP('Boss Editor'!$C$4,'Pokemon Editor'!$A:$A,'Pokemon Editor'!$C:$C,""),mtype=XLOOKUP('Boss Editor'!$C$4,'Pokemon Editor'!$A:$A,'Pokemon Editor'!$D:$D,"")),1.5,1),eff,(INDEX('Type Chart'!$B:$S,MATCH(mtype,'Type Chart'!$A:$A,0),MATCH(XLOOKUP($K33,'Pokemon Editor'!$A:$A,'Pokemon Editor'!$C:$C,""),'Type Chart'!$B$1:$S$1,0))*IF(XLOOKUP($K33,'Pokemon Editor'!$A:$A,'Pokemon Editor'!$D:$D,"")="",1,INDEX('Type Chart'!$B:$S,MATCH(mtype,'Type Chart'!$A:$A,0),MATCH(XLOOKUP($K33,'Pokemon Editor'!$A:$A,'Pokemon Editor'!$D:$D,""),'Type Chart'!$B$1:$S$1,0)))),base,IF(OR(cat="Status",pow=0),0,FLOOR(FLOOR(FLOOR((2*'Boss Editor'!$D$4/5+2)*pow*atk/def)/50)+2)),modifier,stab*eff,AVERAGE(ARRAYFORMULA(FLOOR(base*modifier*SEQUENCE(16,1,85,1)/100)))/(FLOOR(((2*XLOOKUP($K33,'Pokemon Editor'!$A:$A,'Pokemon Editor'!$E:$E,0)+31+FLOOR($O33/4))*$L33)/100)+$L33+10)),0) | F33: =FLOOR((FLOOR(((2*XLOOKUP($K33,'Pokemon Editor'!$A:$A,'Pokemon Editor'!$J:$J,0)+31+FLOOR($T33/4))*$L33)/100)+5)*XLOOKUP($M33,'Nature Editor'!$A:$A,'Nature Editor'!$F:$F,1)) | G33: =FLOOR((FLOOR(((2*XLOOKUP('Boss Editor'!$C$4,'Pokemon Editor'!$A:$A,'Pokemon Editor'!$J:$J,0)+31+FLOOR('Boss Editor'!$L$4/4))*'Boss Editor'!$D$4)/100)+5)*XLOOKUP('Boss Editor'!$E$4,'Nature Editor'!$A:$A,'Nature Editor'!$F:$F,1)) | H33: =IF(F33>G33,"Yes","No") | I33: =C33-E33 | J33: =IFS(AND(C33>=0.5,E33<0.5),"Dominant",AND(C33>=0.35,E33<0.75),"Strong",AND(C33>=0.25,E33<1),"Viable",AND(C33>=0.15,E33<1.25),"Risky",TRUE,"Poor") | K33: =REDUCE($Y33,SEQUENCE(2),LAMBDA(current_species,unused_step,IFERROR(INDEX(FILTER('Evolution Editor'!$D$2:$D,'Evolution Editor'!$A$2:$A=current_species,'Evolution Editor'!$F$2:$F=TRUE,'Evolution Editor'!$E$2:$E<=$L33),1),current_species))) | L33: 15 | M33: Neutral | N33: ABILITY_CUTE_CHARM | O33: 0 | P33: 0 | Q33: 0 | R33: 0 | S33: 0 | T33: 0 | U33: =IFERROR(LET(mtype,XLOOKUP($B33,'Move Editor'!$B:$B,'Move Editor'!$C:$C,""),cat,XLOOKUP($B33,'Move Editor'!$B:$B,'Move Editor'!$D:$D,""),pow,XLOOKUP($B33,'Move Editor'!$B:$B,'Move Editor'!$E:$E,0),acc,XLOOKUP($B33,'Move Editor'!$B:$B,'Move Editor'!$F:$F,100),atk,IF(cat="Physical",FLOOR((FLOOR(((2*XLOOKUP($K33,'Pokemon Editor'!$A:$A,'Pokemon Editor'!$F:$F,0)+31+FLOOR($P33/4))*$L33)/100)+5)*XLOOKUP($M33,'Nature Editor'!$A:$A,'Nature Editor'!$B:$B,1)),FLOOR((FLOOR(((2*XLOOKUP($K33,'Pokemon Editor'!$A:$A,'Pokemon Editor'!$H:$H,0)+31+FLOOR($R33/4))*$L33)/100)+5)*XLOOKUP($M33,'Nature Editor'!$A:$A,'Nature Editor'!$D:$D,1))),def,IF(cat="Physical",FLOOR((FLOOR(((2*XLOOKUP('Boss Editor'!$C$4,'Pokemon Editor'!$A:$A,'Pokemon Editor'!$G:$G,0)+31+FLOOR('Boss Editor'!$I$4/4))*'Boss Editor'!$D$4)/100)+5)*XLOOKUP('Boss Editor'!$E$4,'Nature Editor'!$A:$A,'Nature Editor'!$C:$C,1)),FLOOR((FLOOR(((2*XLOOKUP('Boss Editor'!$C$4,'Pokemon Editor'!$A:$A,'Pokemon Editor'!$I:$I,0)+31+FLOOR('Boss Editor'!$K$4/4))*'Boss Editor'!$D$4)/100)+5)*XLOOKUP('Boss Editor'!$E$4,'Nature Editor'!$A:$A,'Nature Editor'!$E:$E,1))),stab,IF(OR(mtype=XLOOKUP($K33,'Pokemon Editor'!$A:$A,'Pokemon Editor'!$C:$C,""),mtype=XLOOKUP($K33,'Pokemon Editor'!$A:$A,'Pokemon Editor'!$D:$D,"")),1.5,1),eff,(INDEX('Type Chart'!$B:$S,MATCH(mtype,'Type Chart'!$A:$A,0),MATCH(XLOOKUP('Boss Editor'!$C$4,'Pokemon Editor'!$A:$A,'Pokemon Editor'!$C:$C,""),'Type Chart'!$B$1:$S$1,0))*IF(XLOOKUP('Boss Editor'!$C$4,'Pokemon Editor'!$A:$A,'Pokemon Editor'!$D:$D,"")="",1,INDEX('Type Chart'!$B:$S,MATCH(mtype,'Type Chart'!$A:$A,0),MATCH(XLOOKUP('Boss Editor'!$C$4,'Pokemon Editor'!$A:$A,'Pokemon Editor'!$D:$D,""),'Type Chart'!$B$1:$S$1,0)))),base,IF(OR(cat="Status",pow=0),0,FLOOR(FLOOR(FLOOR((2*$L33/5+2)*pow*atk/def)/50)+2)),modifier,stab*eff,FLOOR(base*modifier*0.85)),0) | V33: =IFERROR(LET(mtype,XLOOKUP($B33,'Move Editor'!$B:$B,'Move Editor'!$C:$C,""),cat,XLOOKUP($B33,'Move Editor'!$B:$B,'Move Editor'!$D:$D,""),pow,XLOOKUP($B33,'Move Editor'!$B:$B,'Move Editor'!$E:$E,0),acc,XLOOKUP($B33,'Move Editor'!$B:$B,'Move Editor'!$F:$F,100),atk,IF(cat="Physical",FLOOR((FLOOR(((2*XLOOKUP($K33,'Pokemon Editor'!$A:$A,'Pokemon Editor'!$F:$F,0)+31+FLOOR($P33/4))*$L33)/100)+5)*XLOOKUP($M33,'Nature Editor'!$A:$A,'Nature Editor'!$B:$B,1)),FLOOR((FLOOR(((2*XLOOKUP($K33,'Pokemon Editor'!$A:$A,'Pokemon Editor'!$H:$H,0)+31+FLOOR($R33/4))*$L33)/100)+5)*XLOOKUP($M33,'Nature Editor'!$A:$A,'Nature Editor'!$D:$D,1))),def,IF(cat="Physical",FLOOR((FLOOR(((2*XLOOKUP('Boss Editor'!$C$4,'Pokemon Editor'!$A:$A,'Pokemon Editor'!$G:$G,0)+31+FLOOR('Boss Editor'!$I$4/4))*'Boss Editor'!$D$4)/100)+5)*XLOOKUP('Boss Editor'!$E$4,'Nature Editor'!$A:$A,'Nature Editor'!$C:$C,1)),FLOOR((FLOOR(((2*XLOOKUP('Boss Editor'!$C$4,'Pokemon Editor'!$A:$A,'Pokemon Editor'!$I:$I,0)+31+FLOOR('Boss Editor'!$K$4/4))*'Boss Editor'!$D$4)/100)+5)*XLOOKUP('Boss Editor'!$E$4,'Nature Editor'!$A:$A,'Nature Editor'!$E:$E,1))),stab,IF(OR(mtype=XLOOKUP($K33,'Pokemon Editor'!$A:$A,'Pokemon Editor'!$C:$C,""),mtype=XLOOKUP($K33,'Pokemon Editor'!$A:$A,'Pokemon Editor'!$D:$D,"")),1.5,1),eff,(INDEX('Type Chart'!$B:$S,MATCH(mtype,'Type Chart'!$A:$A,0),MATCH(XLOOKUP('Boss Editor'!$C$4,'Pokemon Editor'!$A:$A,'Pokemon Editor'!$C:$C,""),'Type Chart'!$B$1:$S$1,0))*IF(XLOOKUP('Boss Editor'!$C$4,'Pokemon Editor'!$A:$A,'Pokemon Editor'!$D:$D,"")="",1,INDEX('Type Chart'!$B:$S,MATCH(mtype,'Type Chart'!$A:$A,0),MATCH(XLOOKUP('Boss Editor'!$C$4,'Pokemon Editor'!$A:$A,'Pokemon Editor'!$D:$D,""),'Type Chart'!$B$1:$S$1,0)))),base,IF(OR(cat="Status",pow=0),0,FLOOR(FLOOR(FLOOR((2*$L33/5+2)*pow*atk/def)/50)+2)),modifier,stab*eff,FLOOR(base*modifier)),0) | W33: =IFERROR(LET(mtype,XLOOKUP($D33,'Move Editor'!$B:$B,'Move Editor'!$C:$C,""),cat,XLOOKUP($D33,'Move Editor'!$B:$B,'Move Editor'!$D:$D,""),pow,XLOOKUP($D33,'Move Editor'!$B:$B,'Move Editor'!$E:$E,0),acc,XLOOKUP($D33,'Move Editor'!$B:$B,'Move Editor'!$F:$F,100),atk,IF(cat="Physical",FLOOR((FLOOR(((2*XLOOKUP('Boss Editor'!$C$4,'Pokemon Editor'!$A:$A,'Pokemon Editor'!$F:$F,0)+31+FLOOR('Boss Editor'!$H$4/4))*'Boss Editor'!$D$4)/100)+5)*XLOOKUP('Boss Editor'!$E$4,'Nature Editor'!$A:$A,'Nature Editor'!$B:$B,1)),FLOOR((FLOOR(((2*XLOOKUP('Boss Editor'!$C$4,'Pokemon Editor'!$A:$A,'Pokemon Editor'!$H:$H,0)+31+FLOOR('Boss Editor'!$J$4/4))*'Boss Editor'!$D$4)/100)+5)*XLOOKUP('Boss Editor'!$E$4,'Nature Editor'!$A:$A,'Nature Editor'!$D:$D,1))),def,IF(cat="Physical",FLOOR((FLOOR(((2*XLOOKUP($K33,'Pokemon Editor'!$A:$A,'Pokemon Editor'!$G:$G,0)+31+FLOOR($Q33/4))*$L33)/100)+5)*XLOOKUP($M33,'Nature Editor'!$A:$A,'Nature Editor'!$C:$C,1)),FLOOR((FLOOR(((2*XLOOKUP($K33,'Pokemon Editor'!$A:$A,'Pokemon Editor'!$I:$I,0)+31+FLOOR($S33/4))*$L33)/100)+5)*XLOOKUP($M33,'Nature Editor'!$A:$A,'Nature Editor'!$E:$E,1))),stab,IF(OR(mtype=XLOOKUP('Boss Editor'!$C$4,'Pokemon Editor'!$A:$A,'Pokemon Editor'!$C:$C,""),mtype=XLOOKUP('Boss Editor'!$C$4,'Pokemon Editor'!$A:$A,'Pokemon Editor'!$D:$D,"")),1.5,1),eff,(INDEX('Type Chart'!$B:$S,MATCH(mtype,'Type Chart'!$A:$A,0),MATCH(XLOOKUP($K33,'Pokemon Editor'!$A:$A,'Pokemon Editor'!$C:$C,""),'Type Chart'!$B$1:$S$1,0))*IF(XLOOKUP($K33,'Pokemon Editor'!$A:$A,'Pokemon Editor'!$D:$D,"")="",1,INDEX('Type Chart'!$B:$S,MATCH(mtype,'Type Chart'!$A:$A,0),MATCH(XLOOKUP($K33,'Pokemon Editor'!$A:$A,'Pokemon Editor'!$D:$D,""),'Type Chart'!$B$1:$S$1,0)))),base,IF(OR(cat="Status",pow=0),0,FLOOR(FLOOR(FLOOR((2*'Boss Editor'!$D$4/5+2)*pow*atk/def)/50)+2)),modifier,stab*eff,FLOOR(base*modifier*0.85)),0) | X33: =IFERROR(LET(mtype,XLOOKUP($D33,'Move Editor'!$B:$B,'Move Editor'!$C:$C,""),cat,XLOOKUP($D33,'Move Editor'!$B:$B,'Move Editor'!$D:$D,""),pow,XLOOKUP($D33,'Move Editor'!$B:$B,'Move Editor'!$E:$E,0),acc,XLOOKUP($D33,'Move Editor'!$B:$B,'Move Editor'!$F:$F,100),atk,IF(cat="Physical",FLOOR((FLOOR(((2*XLOOKUP('Boss Editor'!$C$4,'Pokemon Editor'!$A:$A,'Pokemon Editor'!$F:$F,0)+31+FLOOR('Boss Editor'!$H$4/4))*'Boss Editor'!$D$4)/100)+5)*XLOOKUP('Boss Editor'!$E$4,'Nature Editor'!$A:$A,'Nature Editor'!$B:$B,1)),FLOOR((FLOOR(((2*XLOOKUP('Boss Editor'!$C$4,'Pokemon Editor'!$A:$A,'Pokemon Editor'!$H:$H,0)+31+FLOOR('Boss Editor'!$J$4/4))*'Boss Editor'!$D$4)/100)+5)*XLOOKUP('Boss Editor'!$E$4,'Nature Editor'!$A:$A,'Nature Editor'!$D:$D,1))),def,IF(cat="Physical",FLOOR((FLOOR(((2*XLOOKUP($K33,'Pokemon Editor'!$A:$A,'Pokemon Editor'!$G:$G,0)+31+FLOOR($Q33/4))*$L33)/100)+5)*XLOOKUP($M33,'Nature Editor'!$A:$A,'Nature Editor'!$C:$C,1)),FLOOR((FLOOR(((2*XLOOKUP($K33,'Pokemon Editor'!$A:$A,'Pokemon Editor'!$I:$I,0)+31+FLOOR($S33/4))*$L33)/100)+5)*XLOOKUP($M33,'Nature Editor'!$A:$A,'Nature Editor'!$E:$E,1))),stab,IF(OR(mtype=XLOOKUP('Boss Editor'!$C$4,'Pokemon Editor'!$A:$A,'Pokemon Editor'!$C:$C,""),mtype=XLOOKUP('Boss Editor'!$C$4,'Pokemon Editor'!$A:$A,'Pokemon Editor'!$D:$D,"")),1.5,1),eff,(INDEX('Type Chart'!$B:$S,MATCH(mtype,'Type Chart'!$A:$A,0),MATCH(XLOOKUP($K33,'Pokemon Editor'!$A:$A,'Pokemon Editor'!$C:$C,""),'Type Chart'!$B$1:$S$1,0))*IF(XLOOKUP($K33,'Pokemon Editor'!$A:$A,'Pokemon Editor'!$D:$D,"")="",1,INDEX('Type Chart'!$B:$S,MATCH(mtype,'Type Chart'!$A:$A,0),MATCH(XLOOKUP($K33,'Pokemon Editor'!$A:$A,'Pokemon Editor'!$D:$D,""),'Type Chart'!$B$1:$S$1,0)))),base,IF(OR(cat="Status",pow=0),0,FLOOR(FLOOR(FLOOR((2*'Boss Editor'!$D$4/5+2)*pow*atk/def)/50)+2)),modifier,stab*eff,FLOOR(base*modifier)),0) | Y33: SPECIES_MINCCINO

Sheet Player vs Boss
A1: Pokémon | B1: Available from | C1: Level | D1: Nature | E1: Ability | F1: Best move | G1: Type | H1: Category | I1: Power | J1: Accuracy | K1: Min damage | L1: Max damage | M1: Average damage | N1: Expected damage | O1: Average % HP | P1: KO threshold | Q1: Calculation notes | R1: Species ID
A2: =XLOOKUP($R2,'Threshold Summary'!$Y:$Y,'Threshold Summary'!$A:$A,"") | B2: Petalburg Woods / Land / night | C2: =XLOOKUP($R2,'Threshold Summary'!$Y:$Y,'Threshold Summary'!$L:$L,"") | D2: =XLOOKUP($R2,'Threshold Summary'!$Y:$Y,'Threshold Summary'!$M:$M,"") | E2: =XLOOKUP($R2,'Threshold Summary'!$Y:$Y,'Threshold Summary'!$N:$N,"") | F2: =XLOOKUP($R2,'Threshold Summary'!$Y:$Y,'Threshold Summary'!$B:$B,"") | G2: =XLOOKUP(F2,'Move Editor'!$B:$B,'Move Editor'!$C:$C,"") | H2: =XLOOKUP(F2,'Move Editor'!$B:$B,'Move Editor'!$D:$D,"") | I2: =XLOOKUP(F2,'Move Editor'!$B:$B,'Move Editor'!$E:$E,0) | J2: =XLOOKUP(F2,'Move Editor'!$B:$B,'Move Editor'!$F:$F,0) | K2: =XLOOKUP($R2,'Threshold Summary'!$Y:$Y,'Threshold Summary'!$U:$U,"") | L2: =XLOOKUP($R2,'Threshold Summary'!$Y:$Y,'Threshold Summary'!$V:$V,"") | M2: =AVERAGE(K2:L2) | N2: =M2*J2/100 | O2: =XLOOKUP($R2,'Threshold Summary'!$Y:$Y,'Threshold Summary'!$C:$C,"") | P2: =IF(O2>=1,"OHKO",IF(O2>=0.5,"2HKO",IF(O2>=0.333,"3HKO",IF(O2>=0.25,"4HKO","5HKO+")))) | Q2: Live from Threshold Summary and editor tabs | R2: SPECIES_PARAS
A3: =XLOOKUP($R3,'Threshold Summary'!$Y:$Y,'Threshold Summary'!$A:$A,"") | B3: Route 103 / Land / day | C3: =XLOOKUP($R3,'Threshold Summary'!$Y:$Y,'Threshold Summary'!$L:$L,"") | D3: =XLOOKUP($R3,'Threshold Summary'!$Y:$Y,'Threshold Summary'!$M:$M,"") | E3: =XLOOKUP($R3,'Threshold Summary'!$Y:$Y,'Threshold Summary'!$N:$N,"") | F3: =XLOOKUP($R3,'Threshold Summary'!$Y:$Y,'Threshold Summary'!$B:$B,"") | G3: =XLOOKUP(F3,'Move Editor'!$B:$B,'Move Editor'!$C:$C,"") | H3: =XLOOKUP(F3,'Move Editor'!$B:$B,'Move Editor'!$D:$D,"") | I3: =XLOOKUP(F3,'Move Editor'!$B:$B,'Move Editor'!$E:$E,0) | J3: =XLOOKUP(F3,'Move Editor'!$B:$B,'Move Editor'!$F:$F,0) | K3: =XLOOKUP($R3,'Threshold Summary'!$Y:$Y,'Threshold Summary'!$U:$U,"") | L3: =XLOOKUP($R3,'Threshold Summary'!$Y:$Y,'Threshold Summary'!$V:$V,"") | M3: =AVERAGE(K3:L3) | N3: =M3*J3/100 | O3: =XLOOKUP($R3,'Threshold Summary'!$Y:$Y,'Threshold Summary'!$C:$C,"") | P3: =IF(O3>=1,"OHKO",IF(O3>=0.5,"2HKO",IF(O3>=0.333,"3HKO",IF(O3>=0.25,"4HKO","5HKO+")))) | Q3: Live from Threshold Summary and editor tabs | R3: SPECIES_SENTRET
A4: =XLOOKUP($R4,'Threshold Summary'!$Y:$Y,'Threshold Summary'!$A:$A,"") | B4: Route 102 / Land / day | C4: =XLOOKUP($R4,'Threshold Summary'!$Y:$Y,'Threshold Summary'!$L:$L,"") | D4: =XLOOKUP($R4,'Threshold Summary'!$Y:$Y,'Threshold Summary'!$M:$M,"") | E4: =XLOOKUP($R4,'Threshold Summary'!$Y:$Y,'Threshold Summary'!$N:$N,"") | F4: =XLOOKUP($R4,'Threshold Summary'!$Y:$Y,'Threshold Summary'!$B:$B,"") | G4: =XLOOKUP(F4,'Move Editor'!$B:$B,'Move Editor'!$C:$C,"") | H4: =XLOOKUP(F4,'Move Editor'!$B:$B,'Move Editor'!$D:$D,"") | I4: =XLOOKUP(F4,'Move Editor'!$B:$B,'Move Editor'!$E:$E,0) | J4: =XLOOKUP(F4,'Move Editor'!$B:$B,'Move Editor'!$F:$F,0) | K4: =XLOOKUP($R4,'Threshold Summary'!$Y:$Y,'Threshold Summary'!$U:$U,"") | L4: =XLOOKUP($R4,'Threshold Summary'!$Y:$Y,'Threshold Summary'!$V:$V,"") | M4: =AVERAGE(K4:L4) | N4: =M4*J4/100 | O4: =XLOOKUP($R4,'Threshold Summary'!$Y:$Y,'Threshold Summary'!$C:$C,"") | P4: =IF(O4>=1,"OHKO",IF(O4>=0.5,"2HKO",IF(O4>=0.333,"3HKO",IF(O4>=0.25,"4HKO","5HKO+")))) | Q4: Live from Threshold Summary and editor tabs | R4: SPECIES_MAREEP
A5: =XLOOKUP($R5,'Threshold Summary'!$Y:$Y,'Threshold Summary'!$A:$A,"") | B5: Starter | C5: =XLOOKUP($R5,'Threshold Summary'!$Y:$Y,'Threshold Summary'!$L:$L,"") | D5: =XLOOKUP($R5,'Threshold Summary'!$Y:$Y,'Threshold Summary'!$M:$M,"") | E5: =XLOOKUP($R5,'Threshold Summary'!$Y:$Y,'Threshold Summary'!$N:$N,"") | F5: =XLOOKUP($R5,'Threshold Summary'!$Y:$Y,'Threshold Summary'!$B:$B,"") | G5: =XLOOKUP(F5,'Move Editor'!$B:$B,'Move Editor'!$C:$C,"") | H5: =XLOOKUP(F5,'Move Editor'!$B:$B,'Move Editor'!$D:$D,"") | I5: =XLOOKUP(F5,'Move Editor'!$B:$B,'Move Editor'!$E:$E,0) | J5: =XLOOKUP(F5,'Move Editor'!$B:$B,'Move Editor'!$F:$F,0) | K5: =XLOOKUP($R5,'Threshold Summary'!$Y:$Y,'Threshold Summary'!$U:$U,"") | L5: =XLOOKUP($R5,'Threshold Summary'!$Y:$Y,'Threshold Summary'!$V:$V,"") | M5: =AVERAGE(K5:L5) | N5: =M5*J5/100 | O5: =XLOOKUP($R5,'Threshold Summary'!$Y:$Y,'Threshold Summary'!$C:$C,"") | P5: =IF(O5>=1,"OHKO",IF(O5>=0.5,"2HKO",IF(O5>=0.333,"3HKO",IF(O5>=0.25,"4HKO","5HKO+")))) | Q5: Live from Threshold Summary and editor tabs | R5: SPECIES_TREECKO
A6: =XLOOKUP($R6,'Threshold Summary'!$Y:$Y,'Threshold Summary'!$A:$A,"") | B6: Starter | C6: =XLOOKUP($R6,'Threshold Summary'!$Y:$Y,'Threshold Summary'!$L:$L,"") | D6: =XLOOKUP($R6,'Threshold Summary'!$Y:$Y,'Threshold Summary'!$M:$M,"") | E6: =XLOOKUP($R6,'Threshold Summary'!$Y:$Y,'Threshold Summary'!$N:$N,"") | F6: =XLOOKUP($R6,'Threshold Summary'!$Y:$Y,'Threshold Summary'!$B:$B,"") | G6: =XLOOKUP(F6,'Move Editor'!$B:$B,'Move Editor'!$C:$C,"") | H6: =XLOOKUP(F6,'Move Editor'!$B:$B,'Move Editor'!$D:$D,"") | I6: =XLOOKUP(F6,'Move Editor'!$B:$B,'Move Editor'!$E:$E,0) | J6: =XLOOKUP(F6,'Move Editor'!$B:$B,'Move Editor'!$F:$F,0) | K6: =XLOOKUP($R6,'Threshold Summary'!$Y:$Y,'Threshold Summary'!$U:$U,"") | L6: =XLOOKUP($R6,'Threshold Summary'!$Y:$Y,'Threshold Summary'!$V:$V,"") | M6: =AVERAGE(K6:L6) | N6: =M6*J6/100 | O6: =XLOOKUP($R6,'Threshold Summary'!$Y:$Y,'Threshold Summary'!$C:$C,"") | P6: =IF(O6>=1,"OHKO",IF(O6>=0.5,"2HKO",IF(O6>=0.333,"3HKO",IF(O6>=0.25,"4HKO","5HKO+")))) | Q6: Live from Threshold Summary and editor tabs | R6: SPECIES_TORCHIC
A7: =XLOOKUP($R7,'Threshold Summary'!$Y:$Y,'Threshold Summary'!$A:$A,"") | B7: Starter | C7: =XLOOKUP($R7,'Threshold Summary'!$Y:$Y,'Threshold Summary'!$L:$L,"") | D7: =XLOOKUP($R7,'Threshold Summary'!$Y:$Y,'Threshold Summary'!$M:$M,"") | E7: =XLOOKUP($R7,'Threshold Summary'!$Y:$Y,'Threshold Summary'!$N:$N,"") | F7: =XLOOKUP($R7,'Threshold Summary'!$Y:$Y,'Threshold Summary'!$B:$B,"") | G7: =XLOOKUP(F7,'Move Editor'!$B:$B,'Move Editor'!$C:$C,"") | H7: =XLOOKUP(F7,'Move Editor'!$B:$B,'Move Editor'!$D:$D,"") | I7: =XLOOKUP(F7,'Move Editor'!$B:$B,'Move Editor'!$E:$E,0) | J7: =XLOOKUP(F7,'Move Editor'!$B:$B,'Move Editor'!$F:$F,0) | K7: =XLOOKUP($R7,'Threshold Summary'!$Y:$Y,'Threshold Summary'!$U:$U,"") | L7: =XLOOKUP($R7,'Threshold Summary'!$Y:$Y,'Threshold Summary'!$V:$V,"") | M7: =AVERAGE(K7:L7) | N7: =M7*J7/100 | O7: =XLOOKUP($R7,'Threshold Summary'!$Y:$Y,'Threshold Summary'!$C:$C,"") | P7: =IF(O7>=1,"OHKO",IF(O7>=0.5,"2HKO",IF(O7>=0.333,"3HKO",IF(O7>=0.25,"4HKO","5HKO+")))) | Q7: Live from Threshold Summary and editor tabs | R7: SPECIES_MUDKIP
A8: =XLOOKUP($R8,'Threshold Summary'!$Y:$Y,'Threshold Summary'!$A:$A,"") | B8: Route 104 / Land / north | C8: =XLOOKUP($R8,'Threshold Summary'!$Y:$Y,'Threshold Summary'!$L:$L,"") | D8: =XLOOKUP($R8,'Threshold Summary'!$Y:$Y,'Threshold Summary'!$M:$M,"") | E8: =XLOOKUP($R8,'Threshold Summary'!$Y:$Y,'Threshold Summary'!$N:$N,"") | F8: =XLOOKUP($R8,'Threshold Summary'!$Y:$Y,'Threshold Summary'!$B:$B,"") | G8: =XLOOKUP(F8,'Move Editor'!$B:$B,'Move Editor'!$C:$C,"") | H8: =XLOOKUP(F8,'Move Editor'!$B:$B,'Move Editor'!$D:$D,"") | I8: =XLOOKUP(F8,'Move Editor'!$B:$B,'Move Editor'!$E:$E,0) | J8: =XLOOKUP(F8,'Move Editor'!$B:$B,'Move Editor'!$F:$F,0) | K8: =XLOOKUP($R8,'Threshold Summary'!$Y:$Y,'Threshold Summary'!$U:$U,"") | L8: =XLOOKUP($R8,'Threshold Summary'!$Y:$Y,'Threshold Summary'!$V:$V,"") | M8: =AVERAGE(K8:L8) | N8: =M8*J8/100 | O8: =XLOOKUP($R8,'Threshold Summary'!$Y:$Y,'Threshold Summary'!$C:$C,"") | P8: =IF(O8>=1,"OHKO",IF(O8>=0.5,"2HKO",IF(O8>=0.333,"3HKO",IF(O8>=0.25,"4HKO","5HKO+")))) | Q8: Live from Threshold Summary and editor tabs | R8: SPECIES_TAILLOW
A9: =XLOOKUP($R9,'Threshold Summary'!$Y:$Y,'Threshold Summary'!$A:$A,"") | B9: Route 102 / Land / day, Route 102 / Land / night | C9: =XLOOKUP($R9,'Threshold Summary'!$Y:$Y,'Threshold Summary'!$L:$L,"") | D9: =XLOOKUP($R9,'Threshold Summary'!$Y:$Y,'Threshold Summary'!$M:$M,"") | E9: =XLOOKUP($R9,'Threshold Summary'!$Y:$Y,'Threshold Summary'!$N:$N,"") | F9: =XLOOKUP($R9,'Threshold Summary'!$Y:$Y,'Threshold Summary'!$B:$B,"") | G9: =XLOOKUP(F9,'Move Editor'!$B:$B,'Move Editor'!$C:$C,"") | H9: =XLOOKUP(F9,'Move Editor'!$B:$B,'Move Editor'!$D:$D,"") | I9: =XLOOKUP(F9,'Move Editor'!$B:$B,'Move Editor'!$E:$E,0) | J9: =XLOOKUP(F9,'Move Editor'!$B:$B,'Move Editor'!$F:$F,0) | K9: =XLOOKUP($R9,'Threshold Summary'!$Y:$Y,'Threshold Summary'!$U:$U,"") | L9: =XLOOKUP($R9,'Threshold Summary'!$Y:$Y,'Threshold Summary'!$V:$V,"") | M9: =AVERAGE(K9:L9) | N9: =M9*J9/100 | O9: =XLOOKUP($R9,'Threshold Summary'!$Y:$Y,'Threshold Summary'!$C:$C,"") | P9: =IF(O9>=1,"OHKO",IF(O9>=0.5,"2HKO",IF(O9>=0.333,"3HKO",IF(O9>=0.25,"4HKO","5HKO+")))) | Q9: Live from Threshold Summary and editor tabs | R9: SPECIES_RALTS
A10: =XLOOKUP($R10,'Threshold Summary'!$Y:$Y,'Threshold Summary'!$A:$A,"") | B10: Petalburg Woods / Land / day | C10: =XLOOKUP($R10,'Threshold Summary'!$Y:$Y,'Threshold Summary'!$L:$L,"") | D10: =XLOOKUP($R10,'Threshold Summary'!$Y:$Y,'Threshold Summary'!$M:$M,"") | E10: =XLOOKUP($R10,'Threshold Summary'!$Y:$Y,'Threshold Summary'!$N:$N,"") | F10: =XLOOKUP($R10,'Threshold Summary'!$Y:$Y,'Threshold Summary'!$B:$B,"") | G10: =XLOOKUP(F10,'Move Editor'!$B:$B,'Move Editor'!$C:$C,"") | H10: =XLOOKUP(F10,'Move Editor'!$B:$B,'Move Editor'!$D:$D,"") | I10: =XLOOKUP(F10,'Move Editor'!$B:$B,'Move Editor'!$E:$E,0) | J10: =XLOOKUP(F10,'Move Editor'!$B:$B,'Move Editor'!$F:$F,0) | K10: =XLOOKUP($R10,'Threshold Summary'!$Y:$Y,'Threshold Summary'!$U:$U,"") | L10: =XLOOKUP($R10,'Threshold Summary'!$Y:$Y,'Threshold Summary'!$V:$V,"") | M10: =AVERAGE(K10:L10) | N10: =M10*J10/100 | O10: =XLOOKUP($R10,'Threshold Summary'!$Y:$Y,'Threshold Summary'!$C:$C,"") | P10: =IF(O10>=1,"OHKO",IF(O10>=0.5,"2HKO",IF(O10>=0.333,"3HKO",IF(O10>=0.25,"4HKO","5HKO+")))) | Q10: Live from Threshold Summary and editor tabs | R10: SPECIES_BUDEW
A11: =XLOOKUP($R11,'Threshold Summary'!$Y:$Y,'Threshold Summary'!$A:$A,"") | B11: Route 101 / Land / night, Route 103 / Land / night, Route 116 / Land / night | C11: =XLOOKUP($R11,'Threshold Summary'!$Y:$Y,'Threshold Summary'!$L:$L,"") | D11: =XLOOKUP($R11,'Threshold Summary'!$Y:$Y,'Threshold Summary'!$M:$M,"") | E11: =XLOOKUP($R11,'Threshold Summary'!$Y:$Y,'Threshold Summary'!$N:$N,"") | F11: =XLOOKUP($R11,'Threshold Summary'!$Y:$Y,'Threshold Summary'!$B:$B,"") | G11: =XLOOKUP(F11,'Move Editor'!$B:$B,'Move Editor'!$C:$C,"") | H11: =XLOOKUP(F11,'Move Editor'!$B:$B,'Move Editor'!$D:$D,"") | I11: =XLOOKUP(F11,'Move Editor'!$B:$B,'Move Editor'!$E:$E,0) | J11: =XLOOKUP(F11,'Move Editor'!$B:$B,'Move Editor'!$F:$F,0) | K11: =XLOOKUP($R11,'Threshold Summary'!$Y:$Y,'Threshold Summary'!$U:$U,"") | L11: =XLOOKUP($R11,'Threshold Summary'!$Y:$Y,'Threshold Summary'!$V:$V,"") | M11: =AVERAGE(K11:L11) | N11: =M11*J11/100 | O11: =XLOOKUP($R11,'Threshold Summary'!$Y:$Y,'Threshold Summary'!$C:$C,"") | P11: =IF(O11>=1,"OHKO",IF(O11>=0.5,"2HKO",IF(O11>=0.333,"3HKO",IF(O11>=0.25,"4HKO","5HKO+")))) | Q11: Live from Threshold Summary and editor tabs | R11: SPECIES_STARLY
A12: =XLOOKUP($R12,'Threshold Summary'!$Y:$Y,'Threshold Summary'!$A:$A,"") | B12: Route 102 / Land / night | C12: =XLOOKUP($R12,'Threshold Summary'!$Y:$Y,'Threshold Summary'!$L:$L,"") | D12: =XLOOKUP($R12,'Threshold Summary'!$Y:$Y,'Threshold Summary'!$M:$M,"") | E12: =XLOOKUP($R12,'Threshold Summary'!$Y:$Y,'Threshold Summary'!$N:$N,"") | F12: =XLOOKUP($R12,'Threshold Summary'!$Y:$Y,'Threshold Summary'!$B:$B,"") | G12: =XLOOKUP(F12,'Move Editor'!$B:$B,'Move Editor'!$C:$C,"") | H12: =XLOOKUP(F12,'Move Editor'!$B:$B,'Move Editor'!$D:$D,"") | I12: =XLOOKUP(F12,'Move Editor'!$B:$B,'Move Editor'!$E:$E,0) | J12: =XLOOKUP(F12,'Move Editor'!$B:$B,'Move Editor'!$F:$F,0) | K12: =XLOOKUP($R12,'Threshold Summary'!$Y:$Y,'Threshold Summary'!$U:$U,"") | L12: =XLOOKUP($R12,'Threshold Summary'!$Y:$Y,'Threshold Summary'!$V:$V,"") | M12: =AVERAGE(K12:L12) | N12: =M12*J12/100 | O12: =XLOOKUP($R12,'Threshold Summary'!$Y:$Y,'Threshold Summary'!$C:$C,"") | P12: =IF(O12>=1,"OHKO",IF(O12>=0.5,"2HKO",IF(O12>=0.333,"3HKO",IF(O12>=0.25,"4HKO","5HKO+")))) | Q12: Live from Threshold Summary and editor tabs | R12: SPECIES_SHINX
A13: =XLOOKUP($R13,'Threshold Summary'!$Y:$Y,'Threshold Summary'!$A:$A,"") | B13: Petalburg Woods / Land / day | C13: =XLOOKUP($R13,'Threshold Summary'!$Y:$Y,'Threshold Summary'!$L:$L,"") | D13: =XLOOKUP($R13,'Threshold Summary'!$Y:$Y,'Threshold Summary'!$M:$M,"") | E13: =XLOOKUP($R13,'Threshold Summary'!$Y:$Y,'Threshold Summary'!$N:$N,"") | F13: =XLOOKUP($R13,'Threshold Summary'!$Y:$Y,'Threshold Summary'!$B:$B,"") | G13: =XLOOKUP(F13,'Move Editor'!$B:$B,'Move Editor'!$C:$C,"") | H13: =XLOOKUP(F13,'Move Editor'!$B:$B,'Move Editor'!$D:$D,"") | I13: =XLOOKUP(F13,'Move Editor'!$B:$B,'Move Editor'!$E:$E,0) | J13: =XLOOKUP(F13,'Move Editor'!$B:$B,'Move Editor'!$F:$F,0) | K13: =XLOOKUP($R13,'Threshold Summary'!$Y:$Y,'Threshold Summary'!$U:$U,"") | L13: =XLOOKUP($R13,'Threshold Summary'!$Y:$Y,'Threshold Summary'!$V:$V,"") | M13: =AVERAGE(K13:L13) | N13: =M13*J13/100 | O13: =XLOOKUP($R13,'Threshold Summary'!$Y:$Y,'Threshold Summary'!$C:$C,"") | P13: =IF(O13>=1,"OHKO",IF(O13>=0.5,"2HKO",IF(O13>=0.333,"3HKO",IF(O13>=0.25,"4HKO","5HKO+")))) | Q13: Live from Threshold Summary and editor tabs | R13: SPECIES_COMBEE
... A33: =XLOOKUP($R33,'Threshold Summary'!$Y:$Y,'Threshold Summary'!$A:$A,"") | B33: Route 116 / Land / night | C33: =XLOOKUP($R33,'Threshold Summary'!$Y:$Y,'Threshold Summary'!$L:$L,"") | D33: =XLOOKUP($R33,'Threshold Summary'!$Y:$Y,'Threshold Summary'!$M:$M,"") | E33: =XLOOKUP($R33,'Threshold Summary'!$Y:$Y,'Threshold Summary'!$N:$N,"") | F33: =XLOOKUP($R33,'Threshold Summary'!$Y:$Y,'Threshold Summary'!$B:$B,"") | G33: =XLOOKUP(F33,'Move Editor'!$B:$B,'Move Editor'!$C:$C,"") | H33: =XLOOKUP(F33,'Move Editor'!$B:$B,'Move Editor'!$D:$D,"") | I33: =XLOOKUP(F33,'Move Editor'!$B:$B,'Move Editor'!$E:$E,0) | J33: =XLOOKUP(F33,'Move Editor'!$B:$B,'Move Editor'!$F:$F,0) | K33: =XLOOKUP($R33,'Threshold Summary'!$Y:$Y,'Threshold Summary'!$U:$U,"") | L33: =XLOOKUP($R33,'Threshold Summary'!$Y:$Y,'Threshold Summary'!$V:$V,"") | M33: =AVERAGE(K33:L33) | N33: =M33*J33/100 | O33: =XLOOKUP($R33,'Threshold Summary'!$Y:$Y,'Threshold Summary'!$C:$C,"") | P33: =IF(O33>=1,"OHKO",IF(O33>=0.5,"2HKO",IF(O33>=0.333,"3HKO",IF(O33>=0.25,"4HKO","5HKO+")))) | Q33: Live from Threshold Summary and editor tabs | R33: SPECIES_TINKATINK

Sheet Boss vs Players
A1: Player Pokémon | B1: Nature | C1: Ability | D1: Player HP | E1: Boss attacker | F1: Best boss move | G1: Type | H1: Category | I1: Min damage | J1: Max damage | K1: Average damage | L1: Expected damage | M1: Average % HP | N1: KO threshold | O1: Player outspeeds? | P1: Calculation notes | Q1: Species ID
A2: =XLOOKUP($Q2,'Threshold Summary'!$Y:$Y,'Threshold Summary'!$A:$A,"") | B2: =XLOOKUP($Q2,'Threshold Summary'!$Y:$Y,'Threshold Summary'!$M:$M,"") | C2: =XLOOKUP($Q2,'Threshold Summary'!$Y:$Y,'Threshold Summary'!$N:$N,"") | D2: =(FLOOR(((2*XLOOKUP(XLOOKUP($Q2,'Threshold Summary'!$Y:$Y,'Threshold Summary'!$K:$K,""),'Pokemon Editor'!$A:$A,'Pokemon Editor'!$E:$E,0)+31+FLOOR(XLOOKUP($Q2,'Threshold Summary'!$Y:$Y,'Threshold Summary'!$O:$O,"")/4))*XLOOKUP($Q2,'Threshold Summary'!$Y:$Y,'Threshold Summary'!$L:$L,""))/100)+XLOOKUP($Q2,'Threshold Summary'!$Y:$Y,'Threshold Summary'!$L:$L,"")+10) | E2: Lileep | F2: =XLOOKUP($Q2,'Threshold Summary'!$Y:$Y,'Threshold Summary'!$D:$D,"") | G2: =XLOOKUP(F2,'Move Editor'!$B:$B,'Move Editor'!$C:$C,"") | H2: =XLOOKUP(F2,'Move Editor'!$B:$B,'Move Editor'!$D:$D,"") | I2: =XLOOKUP($Q2,'Threshold Summary'!$Y:$Y,'Threshold Summary'!$W:$W,"") | J2: =XLOOKUP($Q2,'Threshold Summary'!$Y:$Y,'Threshold Summary'!$X:$X,"") | K2: =AVERAGE(I2:J2) | L2: =K2*XLOOKUP(F2,'Move Editor'!$B:$B,'Move Editor'!$F:$F,100)/100 | M2: =XLOOKUP($Q2,'Threshold Summary'!$Y:$Y,'Threshold Summary'!$E:$E,"") | N2: =IF(M2>=1,"OHKO",IF(M2>=0.5,"2HKO",IF(M2>=0.333,"3HKO",IF(M2>=0.25,"4HKO","5HKO+")))) | O2: =XLOOKUP($Q2,'Threshold Summary'!$Y:$Y,'Threshold Summary'!$H:$H,"") | P2: Live from Threshold Summary and editor tabs | Q2: SPECIES_PARAS
A3: =XLOOKUP($Q3,'Threshold Summary'!$Y:$Y,'Threshold Summary'!$A:$A,"") | B3: =XLOOKUP($Q3,'Threshold Summary'!$Y:$Y,'Threshold Summary'!$M:$M,"") | C3: =XLOOKUP($Q3,'Threshold Summary'!$Y:$Y,'Threshold Summary'!$N:$N,"") | D3: =(FLOOR(((2*XLOOKUP(XLOOKUP($Q3,'Threshold Summary'!$Y:$Y,'Threshold Summary'!$K:$K,""),'Pokemon Editor'!$A:$A,'Pokemon Editor'!$E:$E,0)+31+FLOOR(XLOOKUP($Q3,'Threshold Summary'!$Y:$Y,'Threshold Summary'!$O:$O,"")/4))*XLOOKUP($Q3,'Threshold Summary'!$Y:$Y,'Threshold Summary'!$L:$L,""))/100)+XLOOKUP($Q3,'Threshold Summary'!$Y:$Y,'Threshold Summary'!$L:$L,"")+10) | E3: Lileep | F3: =XLOOKUP($Q3,'Threshold Summary'!$Y:$Y,'Threshold Summary'!$D:$D,"") | G3: =XLOOKUP(F3,'Move Editor'!$B:$B,'Move Editor'!$C:$C,"") | H3: =XLOOKUP(F3,'Move Editor'!$B:$B,'Move Editor'!$D:$D,"") | I3: =XLOOKUP($Q3,'Threshold Summary'!$Y:$Y,'Threshold Summary'!$W:$W,"") | J3: =XLOOKUP($Q3,'Threshold Summary'!$Y:$Y,'Threshold Summary'!$X:$X,"") | K3: =AVERAGE(I3:J3) | L3: =K3*XLOOKUP(F3,'Move Editor'!$B:$B,'Move Editor'!$F:$F,100)/100 | M3: =XLOOKUP($Q3,'Threshold Summary'!$Y:$Y,'Threshold Summary'!$E:$E,"") | N3: =IF(M3>=1,"OHKO",IF(M3>=0.5,"2HKO",IF(M3>=0.333,"3HKO",IF(M3>=0.25,"4HKO","5HKO+")))) | O3: =XLOOKUP($Q3,'Threshold Summary'!$Y:$Y,'Threshold Summary'!$H:$H,"") | P3: Live from Threshold Summary and editor tabs | Q3: SPECIES_SENTRET
A4: =XLOOKUP($Q4,'Threshold Summary'!$Y:$Y,'Threshold Summary'!$A:$A,"") | B4: =XLOOKUP($Q4,'Threshold Summary'!$Y:$Y,'Threshold Summary'!$M:$M,"") | C4: =XLOOKUP($Q4,'Threshold Summary'!$Y:$Y,'Threshold Summary'!$N:$N,"") | D4: =(FLOOR(((2*XLOOKUP(XLOOKUP($Q4,'Threshold Summary'!$Y:$Y,'Threshold Summary'!$K:$K,""),'Pokemon Editor'!$A:$A,'Pokemon Editor'!$E:$E,0)+31+FLOOR(XLOOKUP($Q4,'Threshold Summary'!$Y:$Y,'Threshold Summary'!$O:$O,"")/4))*XLOOKUP($Q4,'Threshold Summary'!$Y:$Y,'Threshold Summary'!$L:$L,""))/100)+XLOOKUP($Q4,'Threshold Summary'!$Y:$Y,'Threshold Summary'!$L:$L,"")+10) | E4: Lileep | F4: =XLOOKUP($Q4,'Threshold Summary'!$Y:$Y,'Threshold Summary'!$D:$D,"") | G4: =XLOOKUP(F4,'Move Editor'!$B:$B,'Move Editor'!$C:$C,"") | H4: =XLOOKUP(F4,'Move Editor'!$B:$B,'Move Editor'!$D:$D,"") | I4: =XLOOKUP($Q4,'Threshold Summary'!$Y:$Y,'Threshold Summary'!$W:$W,"") | J4: =XLOOKUP($Q4,'Threshold Summary'!$Y:$Y,'Threshold Summary'!$X:$X,"") | K4: =AVERAGE(I4:J4) | L4: =K4*XLOOKUP(F4,'Move Editor'!$B:$B,'Move Editor'!$F:$F,100)/100 | M4: =XLOOKUP($Q4,'Threshold Summary'!$Y:$Y,'Threshold Summary'!$E:$E,"") | N4: =IF(M4>=1,"OHKO",IF(M4>=0.5,"2HKO",IF(M4>=0.333,"3HKO",IF(M4>=0.25,"4HKO","5HKO+")))) | O4: =XLOOKUP($Q4,'Threshold Summary'!$Y:$Y,'Threshold Summary'!$H:$H,"") | P4: Live from Threshold Summary and editor tabs | Q4: SPECIES_MAREEP
A5: =XLOOKUP($Q5,'Threshold Summary'!$Y:$Y,'Threshold Summary'!$A:$A,"") | B5: =XLOOKUP($Q5,'Threshold Summary'!$Y:$Y,'Threshold Summary'!$M:$M,"") | C5: =XLOOKUP($Q5,'Threshold Summary'!$Y:$Y,'Threshold Summary'!$N:$N,"") | D5: =(FLOOR(((2*XLOOKUP(XLOOKUP($Q5,'Threshold Summary'!$Y:$Y,'Threshold Summary'!$K:$K,""),'Pokemon Editor'!$A:$A,'Pokemon Editor'!$E:$E,0)+31+FLOOR(XLOOKUP($Q5,'Threshold Summary'!$Y:$Y,'Threshold Summary'!$O:$O,"")/4))*XLOOKUP($Q5,'Threshold Summary'!$Y:$Y,'Threshold Summary'!$L:$L,""))/100)+XLOOKUP($Q5,'Threshold Summary'!$Y:$Y,'Threshold Summary'!$L:$L,"")+10) | E5: Lileep | F5: =XLOOKUP($Q5,'Threshold Summary'!$Y:$Y,'Threshold Summary'!$D:$D,"") | G5: =XLOOKUP(F5,'Move Editor'!$B:$B,'Move Editor'!$C:$C,"") | H5: =XLOOKUP(F5,'Move Editor'!$B:$B,'Move Editor'!$D:$D,"") | I5: =XLOOKUP($Q5,'Threshold Summary'!$Y:$Y,'Threshold Summary'!$W:$W,"") | J5: =XLOOKUP($Q5,'Threshold Summary'!$Y:$Y,'Threshold Summary'!$X:$X,"") | K5: =AVERAGE(I5:J5) | L5: =K5*XLOOKUP(F5,'Move Editor'!$B:$B,'Move Editor'!$F:$F,100)/100 | M5: =XLOOKUP($Q5,'Threshold Summary'!$Y:$Y,'Threshold Summary'!$E:$E,"") | N5: =IF(M5>=1,"OHKO",IF(M5>=0.5,"2HKO",IF(M5>=0.333,"3HKO",IF(M5>=0.25,"4HKO","5HKO+")))) | O5: =XLOOKUP($Q5,'Threshold Summary'!$Y:$Y,'Threshold Summary'!$H:$H,"") | P5: Live from Threshold Summary and editor tabs | Q5: SPECIES_TREECKO
A6: =XLOOKUP($Q6,'Threshold Summary'!$Y:$Y,'Threshold Summary'!$A:$A,"") | B6: =XLOOKUP($Q6,'Threshold Summary'!$Y:$Y,'Threshold Summary'!$M:$M,"") | C6: =XLOOKUP($Q6,'Threshold Summary'!$Y:$Y,'Threshold Summary'!$N:$N,"") | D6: =(FLOOR(((2*XLOOKUP(XLOOKUP($Q6,'Threshold Summary'!$Y:$Y,'Threshold Summary'!$K:$K,""),'Pokemon Editor'!$A:$A,'Pokemon Editor'!$E:$E,0)+31+FLOOR(XLOOKUP($Q6,'Threshold Summary'!$Y:$Y,'Threshold Summary'!$O:$O,"")/4))*XLOOKUP($Q6,'Threshold Summary'!$Y:$Y,'Threshold Summary'!$L:$L,""))/100)+XLOOKUP($Q6,'Threshold Summary'!$Y:$Y,'Threshold Summary'!$L:$L,"")+10) | E6: Lileep | F6: =XLOOKUP($Q6,'Threshold Summary'!$Y:$Y,'Threshold Summary'!$D:$D,"") | G6: =XLOOKUP(F6,'Move Editor'!$B:$B,'Move Editor'!$C:$C,"") | H6: =XLOOKUP(F6,'Move Editor'!$B:$B,'Move Editor'!$D:$D,"") | I6: =XLOOKUP($Q6,'Threshold Summary'!$Y:$Y,'Threshold Summary'!$W:$W,"") | J6: =XLOOKUP($Q6,'Threshold Summary'!$Y:$Y,'Threshold Summary'!$X:$X,"") | K6: =AVERAGE(I6:J6) | L6: =K6*XLOOKUP(F6,'Move Editor'!$B:$B,'Move Editor'!$F:$F,100)/100 | M6: =XLOOKUP($Q6,'Threshold Summary'!$Y:$Y,'Threshold Summary'!$E:$E,"") | N6: =IF(M6>=1,"OHKO",IF(M6>=0.5,"2HKO",IF(M6>=0.333,"3HKO",IF(M6>=0.25,"4HKO","5HKO+")))) | O6: =XLOOKUP($Q6,'Threshold Summary'!$Y:$Y,'Threshold Summary'!$H:$H,"") | P6: Live from Threshold Summary and editor tabs | Q6: SPECIES_TORCHIC
A7: =XLOOKUP($Q7,'Threshold Summary'!$Y:$Y,'Threshold Summary'!$A:$A,"") | B7: =XLOOKUP($Q7,'Threshold Summary'!$Y:$Y,'Threshold Summary'!$M:$M,"") | C7: =XLOOKUP($Q7,'Threshold Summary'!$Y:$Y,'Threshold Summary'!$N:$N,"") | D7: =(FLOOR(((2*XLOOKUP(XLOOKUP($Q7,'Threshold Summary'!$Y:$Y,'Threshold Summary'!$K:$K,""),'Pokemon Editor'!$A:$A,'Pokemon Editor'!$E:$E,0)+31+FLOOR(XLOOKUP($Q7,'Threshold Summary'!$Y:$Y,'Threshold Summary'!$O:$O,"")/4))*XLOOKUP($Q7,'Threshold Summary'!$Y:$Y,'Threshold Summary'!$L:$L,""))/100)+XLOOKUP($Q7,'Threshold Summary'!$Y:$Y,'Threshold Summary'!$L:$L,"")+10) | E7: Lileep | F7: =XLOOKUP($Q7,'Threshold Summary'!$Y:$Y,'Threshold Summary'!$D:$D,"") | G7: =XLOOKUP(F7,'Move Editor'!$B:$B,'Move Editor'!$C:$C,"") | H7: =XLOOKUP(F7,'Move Editor'!$B:$B,'Move Editor'!$D:$D,"") | I7: =XLOOKUP($Q7,'Threshold Summary'!$Y:$Y,'Threshold Summary'!$W:$W,"") | J7: =XLOOKUP($Q7,'Threshold Summary'!$Y:$Y,'Threshold Summary'!$X:$X,"") | K7: =AVERAGE(I7:J7) | L7: =K7*XLOOKUP(F7,'Move Editor'!$B:$B,'Move Editor'!$F:$F,100)/100 | M7: =XLOOKUP($Q7,'Threshold Summary'!$Y:$Y,'Threshold Summary'!$E:$E,"") | N7: =IF(M7>=1,"OHKO",IF(M7>=0.5,"2HKO",IF(M7>=0.333,"3HKO",IF(M7>=0.25,"4HKO","5HKO+")))) | O7: =XLOOKUP($Q7,'Threshold Summary'!$Y:$Y,'Threshold Summary'!$H:$H,"") | P7: Live from Threshold Summary and editor tabs | Q7: SPECIES_MUDKIP
A8: =XLOOKUP($Q8,'Threshold Summary'!$Y:$Y,'Threshold Summary'!$A:$A,"") | B8: =XLOOKUP($Q8,'Threshold Summary'!$Y:$Y,'Threshold Summary'!$M:$M,"") | C8: =XLOOKUP($Q8,'Threshold Summary'!$Y:$Y,'Threshold Summary'!$N:$N,"") | D8: =(FLOOR(((2*XLOOKUP(XLOOKUP($Q8,'Threshold Summary'!$Y:$Y,'Threshold Summary'!$K:$K,""),'Pokemon Editor'!$A:$A,'Pokemon Editor'!$E:$E,0)+31+FLOOR(XLOOKUP($Q8,'Threshold Summary'!$Y:$Y,'Threshold Summary'!$O:$O,"")/4))*XLOOKUP($Q8,'Threshold Summary'!$Y:$Y,'Threshold Summary'!$L:$L,""))/100)+XLOOKUP($Q8,'Threshold Summary'!$Y:$Y,'Threshold Summary'!$L:$L,"")+10) | E8: Lileep | F8: =XLOOKUP($Q8,'Threshold Summary'!$Y:$Y,'Threshold Summary'!$D:$D,"") | G8: =XLOOKUP(F8,'Move Editor'!$B:$B,'Move Editor'!$C:$C,"") | H8: =XLOOKUP(F8,'Move Editor'!$B:$B,'Move Editor'!$D:$D,"") | I8: =XLOOKUP($Q8,'Threshold Summary'!$Y:$Y,'Threshold Summary'!$W:$W,"") | J8: =XLOOKUP($Q8,'Threshold Summary'!$Y:$Y,'Threshold Summary'!$X:$X,"") | K8: =AVERAGE(I8:J8) | L8: =K8*XLOOKUP(F8,'Move Editor'!$B:$B,'Move Editor'!$F:$F,100)/100 | M8: =XLOOKUP($Q8,'Threshold Summary'!$Y:$Y,'Threshold Summary'!$E:$E,"") | N8: =IF(M8>=1,"OHKO",IF(M8>=0.5,"2HKO",IF(M8>=0.333,"3HKO",IF(M8>=0.25,"4HKO","5HKO+")))) | O8: =XLOOKUP($Q8,'Threshold Summary'!$Y:$Y,'Threshold Summary'!$H:$H,"") | P8: Live from Threshold Summary and editor tabs | Q8: SPECIES_TAILLOW
A9: =XLOOKUP($Q9,'Threshold Summary'!$Y:$Y,'Threshold Summary'!$A:$A,"") | B9: =XLOOKUP($Q9,'Threshold Summary'!$Y:$Y,'Threshold Summary'!$M:$M,"") | C9: =XLOOKUP($Q9,'Threshold Summary'!$Y:$Y,'Threshold Summary'!$N:$N,"") | D9: =(FLOOR(((2*XLOOKUP(XLOOKUP($Q9,'Threshold Summary'!$Y:$Y,'Threshold Summary'!$K:$K,""),'Pokemon Editor'!$A:$A,'Pokemon Editor'!$E:$E,0)+31+FLOOR(XLOOKUP($Q9,'Threshold Summary'!$Y:$Y,'Threshold Summary'!$O:$O,"")/4))*XLOOKUP($Q9,'Threshold Summary'!$Y:$Y,'Threshold Summary'!$L:$L,""))/100)+XLOOKUP($Q9,'Threshold Summary'!$Y:$Y,'Threshold Summary'!$L:$L,"")+10) | E9: Lileep | F9: =XLOOKUP($Q9,'Threshold Summary'!$Y:$Y,'Threshold Summary'!$D:$D,"") | G9: =XLOOKUP(F9,'Move Editor'!$B:$B,'Move Editor'!$C:$C,"") | H9: =XLOOKUP(F9,'Move Editor'!$B:$B,'Move Editor'!$D:$D,"") | I9: =XLOOKUP($Q9,'Threshold Summary'!$Y:$Y,'Threshold Summary'!$W:$W,"") | J9: =XLOOKUP($Q9,'Threshold Summary'!$Y:$Y,'Threshold Summary'!$X:$X,"") | K9: =AVERAGE(I9:J9) | L9: =K9*XLOOKUP(F9,'Move Editor'!$B:$B,'Move Editor'!$F:$F,100)/100 | M9: =XLOOKUP($Q9,'Threshold Summary'!$Y:$Y,'Threshold Summary'!$E:$E,"") | N9: =IF(M9>=1,"OHKO",IF(M9>=0.5,"2HKO",IF(M9>=0.333,"3HKO",IF(M9>=0.25,"4HKO","5HKO+")))) | O9: =XLOOKUP($Q9,'Threshold Summary'!$Y:$Y,'Threshold Summary'!$H:$H,"") | P9: Live from Threshold Summary and editor tabs | Q9: SPECIES_RALTS
A10: =XLOOKUP($Q10,'Threshold Summary'!$Y:$Y,'Threshold Summary'!$A:$A,"") | B10: =XLOOKUP($Q10,'Threshold Summary'!$Y:$Y,'Threshold Summary'!$M:$M,"") | C10: =XLOOKUP($Q10,'Threshold Summary'!$Y:$Y,'Threshold Summary'!$N:$N,"") | D10: =(FLOOR(((2*XLOOKUP(XLOOKUP($Q10,'Threshold Summary'!$Y:$Y,'Threshold Summary'!$K:$K,""),'Pokemon Editor'!$A:$A,'Pokemon Editor'!$E:$E,0)+31+FLOOR(XLOOKUP($Q10,'Threshold Summary'!$Y:$Y,'Threshold Summary'!$O:$O,"")/4))*XLOOKUP($Q10,'Threshold Summary'!$Y:$Y,'Threshold Summary'!$L:$L,""))/100)+XLOOKUP($Q10,'Threshold Summary'!$Y:$Y,'Threshold Summary'!$L:$L,"")+10) | E10: Lileep | F10: =XLOOKUP($Q10,'Threshold Summary'!$Y:$Y,'Threshold Summary'!$D:$D,"") | G10: =XLOOKUP(F10,'Move Editor'!$B:$B,'Move Editor'!$C:$C,"") | H10: =XLOOKUP(F10,'Move Editor'!$B:$B,'Move Editor'!$D:$D,"") | I10: =XLOOKUP($Q10,'Threshold Summary'!$Y:$Y,'Threshold Summary'!$W:$W,"") | J10: =XLOOKUP($Q10,'Threshold Summary'!$Y:$Y,'Threshold Summary'!$X:$X,"") | K10: =AVERAGE(I10:J10) | L10: =K10*XLOOKUP(F10,'Move Editor'!$B:$B,'Move Editor'!$F:$F,100)/100 | M10: =XLOOKUP($Q10,'Threshold Summary'!$Y:$Y,'Threshold Summary'!$E:$E,"") | N10: =IF(M10>=1,"OHKO",IF(M10>=0.5,"2HKO",IF(M10>=0.333,"3HKO",IF(M10>=0.25,"4HKO","5HKO+")))) | O10: =XLOOKUP($Q10,'Threshold Summary'!$Y:$Y,'Threshold Summary'!$H:$H,"") | P10: Live from Threshold Summary and editor tabs | Q10: SPECIES_BUDEW
A11: =XLOOKUP($Q11,'Threshold Summary'!$Y:$Y,'Threshold Summary'!$A:$A,"") | B11: =XLOOKUP($Q11,'Threshold Summary'!$Y:$Y,'Threshold Summary'!$M:$M,"") | C11: =XLOOKUP($Q11,'Threshold Summary'!$Y:$Y,'Threshold Summary'!$N:$N,"") | D11: =(FLOOR(((2*XLOOKUP(XLOOKUP($Q11,'Threshold Summary'!$Y:$Y,'Threshold Summary'!$K:$K,""),'Pokemon Editor'!$A:$A,'Pokemon Editor'!$E:$E,0)+31+FLOOR(XLOOKUP($Q11,'Threshold Summary'!$Y:$Y,'Threshold Summary'!$O:$O,"")/4))*XLOOKUP($Q11,'Threshold Summary'!$Y:$Y,'Threshold Summary'!$L:$L,""))/100)+XLOOKUP($Q11,'Threshold Summary'!$Y:$Y,'Threshold Summary'!$L:$L,"")+10) | E11: Lileep | F11: =XLOOKUP($Q11,'Threshold Summary'!$Y:$Y,'Threshold Summary'!$D:$D,"") | G11: =XLOOKUP(F11,'Move Editor'!$B:$B,'Move Editor'!$C:$C,"") | H11: =XLOOKUP(F11,'Move Editor'!$B:$B,'Move Editor'!$D:$D,"") | I11: =XLOOKUP($Q11,'Threshold Summary'!$Y:$Y,'Threshold Summary'!$W:$W,"") | J11: =XLOOKUP($Q11,'Threshold Summary'!$Y:$Y,'Threshold Summary'!$X:$X,"") | K11: =AVERAGE(I11:J11) | L11: =K11*XLOOKUP(F11,'Move Editor'!$B:$B,'Move Editor'!$F:$F,100)/100 | M11: =XLOOKUP($Q11,'Threshold Summary'!$Y:$Y,'Threshold Summary'!$E:$E,"") | N11: =IF(M11>=1,"OHKO",IF(M11>=0.5,"2HKO",IF(M11>=0.333,"3HKO",IF(M11>=0.25,"4HKO","5HKO+")))) | O11: =XLOOKUP($Q11,'Threshold Summary'!$Y:$Y,'Threshold Summary'!$H:$H,"") | P11: Live from Threshold Summary and editor tabs | Q11: SPECIES_STARLY
A12: =XLOOKUP($Q12,'Threshold Summary'!$Y:$Y,'Threshold Summary'!$A:$A,"") | B12: =XLOOKUP($Q12,'Threshold Summary'!$Y:$Y,'Threshold Summary'!$M:$M,"") | C12: =XLOOKUP($Q12,'Threshold Summary'!$Y:$Y,'Threshold Summary'!$N:$N,"") | D12: =(FLOOR(((2*XLOOKUP(XLOOKUP($Q12,'Threshold Summary'!$Y:$Y,'Threshold Summary'!$K:$K,""),'Pokemon Editor'!$A:$A,'Pokemon Editor'!$E:$E,0)+31+FLOOR(XLOOKUP($Q12,'Threshold Summary'!$Y:$Y,'Threshold Summary'!$O:$O,"")/4))*XLOOKUP($Q12,'Threshold Summary'!$Y:$Y,'Threshold Summary'!$L:$L,""))/100)+XLOOKUP($Q12,'Threshold Summary'!$Y:$Y,'Threshold Summary'!$L:$L,"")+10) | E12: Lileep | F12: =XLOOKUP($Q12,'Threshold Summary'!$Y:$Y,'Threshold Summary'!$D:$D,"") | G12: =XLOOKUP(F12,'Move Editor'!$B:$B,'Move Editor'!$C:$C,"") | H12: =XLOOKUP(F12,'Move Editor'!$B:$B,'Move Editor'!$D:$D,"") | I12: =XLOOKUP($Q12,'Threshold Summary'!$Y:$Y,'Threshold Summary'!$W:$W,"") | J12: =XLOOKUP($Q12,'Threshold Summary'!$Y:$Y,'Threshold Summary'!$X:$X,"") | K12: =AVERAGE(I12:J12) | L12: =K12*XLOOKUP(F12,'Move Editor'!$B:$B,'Move Editor'!$F:$F,100)/100 | M12: =XLOOKUP($Q12,'Threshold Summary'!$Y:$Y,'Threshold Summary'!$E:$E,"") | N12: =IF(M12>=1,"OHKO",IF(M12>=0.5,"2HKO",IF(M12>=0.333,"3HKO",IF(M12>=0.25,"4HKO","5HKO+")))) | O12: =XLOOKUP($Q12,'Threshold Summary'!$Y:$Y,'Threshold Summary'!$H:$H,"") | P12: Live from Threshold Summary and editor tabs | Q12: SPECIES_SHINX
A13: =XLOOKUP($Q13,'Threshold Summary'!$Y:$Y,'Threshold Summary'!$A:$A,"") | B13: =XLOOKUP($Q13,'Threshold Summary'!$Y:$Y,'Threshold Summary'!$M:$M,"") | C13: =XLOOKUP($Q13,'Threshold Summary'!$Y:$Y,'Threshold Summary'!$N:$N,"") | D13: =(FLOOR(((2*XLOOKUP(XLOOKUP($Q13,'Threshold Summary'!$Y:$Y,'Threshold Summary'!$K:$K,""),'Pokemon Editor'!$A:$A,'Pokemon Editor'!$E:$E,0)+31+FLOOR(XLOOKUP($Q13,'Threshold Summary'!$Y:$Y,'Threshold Summary'!$O:$O,"")/4))*XLOOKUP($Q13,'Threshold Summary'!$Y:$Y,'Threshold Summary'!$L:$L,""))/100)+XLOOKUP($Q13,'Threshold Summary'!$Y:$Y,'Threshold Summary'!$L:$L,"")+10) | E13: Lileep | F13: =XLOOKUP($Q13,'Threshold Summary'!$Y:$Y,'Threshold Summary'!$D:$D,"") | G13: =XLOOKUP(F13,'Move Editor'!$B:$B,'Move Editor'!$C:$C,"") | H13: =XLOOKUP(F13,'Move Editor'!$B:$B,'Move Editor'!$D:$D,"") | I13: =XLOOKUP($Q13,'Threshold Summary'!$Y:$Y,'Threshold Summary'!$W:$W,"") | J13: =XLOOKUP($Q13,'Threshold Summary'!$Y:$Y,'Threshold Summary'!$X:$X,"") | K13: =AVERAGE(I13:J13) | L13: =K13*XLOOKUP(F13,'Move Editor'!$B:$B,'Move Editor'!$F:$F,100)/100 | M13: =XLOOKUP($Q13,'Threshold Summary'!$Y:$Y,'Threshold Summary'!$E:$E,"") | N13: =IF(M13>=1,"OHKO",IF(M13>=0.5,"2HKO",IF(M13>=0.333,"3HKO",IF(M13>=0.25,"4HKO","5HKO+")))) | O13: =XLOOKUP($Q13,'Threshold Summary'!$Y:$Y,'Threshold Summary'!$H:$H,"") | P13: Live from Threshold Summary and editor tabs | Q13: SPECIES_COMBEE
... A33: =XLOOKUP($Q33,'Threshold Summary'!$Y:$Y,'Threshold Summary'!$A:$A,"") | B33: =XLOOKUP($Q33,'Threshold Summary'!$Y:$Y,'Threshold Summary'!$M:$M,"") | C33: =XLOOKUP($Q33,'Threshold Summary'!$Y:$Y,'Threshold Summary'!$N:$N,"") | D33: =(FLOOR(((2*XLOOKUP(XLOOKUP($Q33,'Threshold Summary'!$Y:$Y,'Threshold Summary'!$K:$K,""),'Pokemon Editor'!$A:$A,'Pokemon Editor'!$E:$E,0)+31+FLOOR(XLOOKUP($Q33,'Threshold Summary'!$Y:$Y,'Threshold Summary'!$O:$O,"")/4))*XLOOKUP($Q33,'Threshold Summary'!$Y:$Y,'Threshold Summary'!$L:$L,""))/100)+XLOOKUP($Q33,'Threshold Summary'!$Y:$Y,'Threshold Summary'!$L:$L,"")+10) | E33: Lileep | F33: =XLOOKUP($Q33,'Threshold Summary'!$Y:$Y,'Threshold Summary'!$D:$D,"") | G33: =XLOOKUP(F33,'Move Editor'!$B:$B,'Move Editor'!$C:$C,"") | H33: =XLOOKUP(F33,'Move Editor'!$B:$B,'Move Editor'!$D:$D,"") | I33: =XLOOKUP($Q33,'Threshold Summary'!$Y:$Y,'Threshold Summary'!$W:$W,"") | J33: =XLOOKUP($Q33,'Threshold Summary'!$Y:$Y,'Threshold Summary'!$X:$X,"") | K33: =AVERAGE(I33:J33) | L33: =K33*XLOOKUP(F33,'Move Editor'!$B:$B,'Move Editor'!$F:$F,100)/100 | M33: =XLOOKUP($Q33,'Threshold Summary'!$Y:$Y,'Threshold Summary'!$E:$E,"") | N33: =IF(M33>=1,"OHKO",IF(M33>=0.5,"2HKO",IF(M33>=0.333,"3HKO",IF(M33>=0.25,"4HKO","5HKO+")))) | O33: =XLOOKUP($Q33,'Threshold Summary'!$Y:$Y,'Threshold Summary'!$H:$H,"") | P33: Live from Threshold Summary and editor tabs | Q33: SPECIES_TINKATINK

Sheet Move Comparison
A1: Pokémon | B1: Nature | C1: Ability | D1: Move | E1: Type | F1: Category | G1: Power | H1: Accuracy | I1: Effectiveness | J1: Min damage | K1: Max damage | L1: Average damage | M1: Expected damage | N1: Average % HP | O1: KO threshold | P1: Calculation notes | Q1: Origin Species ID | R1: Move slot
